Workbook
Name Engagement_Q3: Analysis!$B$5
Name Engagement_Threshold: Analysis!$B$5
Name Slicer_Discount_Category: #N/A
Name Slicer_Price_Category: #N/A
Name Slicer_Rating_Category: #N/A

Sheet Raw data
A1: Product | B1: Current price | C1: old price | D1: Discount | E1: Review | F1: Ratingd
A2: 115 Piece Set Of Multifunctional Precision Screwdrivers | B2: KSh 950 | C2: KSh 1,525 | D2: 0.38 | E2: -2 | F2: 4.5 out of 5
A3: Metal Decorative Hooks Key Hangers Entryway Wall Hooks Towel Hooks - Home | B3: KSh 527 | C3: KSh 999 | D3: 0.47 | E3: -14 | F3: 4.1 out of 5
A4: Portable Mini Cordless Car Vacuum Cleaner - Blue | B4: KSh 2,199 | C4: KSh 2,923 | D4: 0.25 | E4: -24 | F4: 4.6 out of 5
A5: Weighing Scale Digital Bathroom Body Fat Scale USB-Black | B5: KSh 1,580 | C5: KSh 2,499 | D5: 0.37 | E5: -7 | F5: 4.7 out of 5
A6: Portable Home Small Air Humidifier 3-Speed Fan - Green | B6: KSh 1,740 | C6: KSh 2,356 | D6: 0.26 | E6: -5 | F6: 4.8 out of 5
A7: 220V 60W Electric Soldering Iron Kits With Tools, Tips, And Multimeter | B7: KSh 2,999 | C7: KSh 3,290 | D7: 0.09 | E7: -15 | F7: 4 out of 5
A8: 137 Pieces Cake Decorating Tool Set Baking Supplies | B8: KSh 2,319 | C8: KSh 3,032 | D8: 0.24 | E8: -55 | F8: 4.6 out of 5
A9: Desk Foldable Fan Adjustable Fan Strong Wind 3 Gear Usb | B9: KSh 988 | C9: KSh 1,580 | D9: 0.37 | E9: -2 | F9: 4 out of 5
A10: LASA FOLDING TABLE SERVING STAND | B10: KSh 1,274 | C10: KSh 2,800 | D10: 0.55 | E10: -5 | F10: 4.8 out of 5
A11: 13 In 1 Home Repair Tools Box Kit Set | B11: KSh 1,600 | C11: KSh 2,929 | D11: 0.45 | E11: -5 | F11: 3.8 out of 5
A12: Genebre 115 In 1 Screwdriver Repairing Tool Set For IPhone Cellphone Hand Tool | B12: KSh 799 | C12: KSh 999 | D12: 0.2 | E12: -12 | F12: 4.1 out of 5
A13: 100 Pcs Crochet Hook Tool Set Knitting Hook Set With Box | B13: KSh 990 | C13: KSh 1,500 | D13: 0.34 | E13: -39 | F13: 4.7 out of 5
... A22: 3PCS Single Head Knitting Crochet Sweater Needle Set | B22: KSh 38 | C22: KSh 80 | D22: 0.53 | E22: -13 | F22: 3.3 out of 5
A23: 4pcs Bathroom/Kitchen Towel Rack,Roll Paper Holder,Towel Bars,Hook | B23: KSh 1,860 | C23: KSh 3,220 | D23: 0.42
A24: LED Romantic Spaceship Starry Sky Projector,Children's Bedroom Night Light-Blue | B24: KSh 880 | C24: KSh 1,350 | D24: 0.35 | E24: -6 | F24: 4 out of 5
A25: Foldable Overbed Table/Desk | B25: KSh 1,650 | C25: KSh 2,150 | D25: 0.23 | E25: -14 | F25: 4.4 out of 5
A26: LASA 3 Tier Bamboo Shoe Bench Storage Shelf | B26: KSh 2,048 | C26: KSh 4,500 | D26: 0.54 | E26: -7 | F26: 4.3 out of 5
A27: Electronic Digital Display Vernier Caliper | B27: KSh 420 | C27: KSh 647 | D27: 0.35 | E27: -49 | F27: 4.6 out of 5
A28: Portable Wardrobe Nonwoven With 3 Hanging Rods And 6 Storage Shelves | B28: KSh 2,880 | C28: KSh 3,520 | D28: 0.18 | E28: -12 | F28: 3.8 out of 5
A29: 12 Litre Black Insulated Lunch Box | B29: KSh 1,350 | C29: KSh 1,990 | D29: 0.32 | E29: -13 | F29: 3.8 out of 5
A30: 52 Pieces Cake Decorating Tool Set Gift Kit Baking Supplies | B30: KSh 1,758 | C30: KSh 2,499 | D30: 0.3 | E30: -20 | F30: 4.1 out of 5
A31: MultiFunctional Storage Rack Multi-layer Bookshelf | B31: KSh 2,200 | C31: KSh 4,080 | D31: 0.46
A32: Exfoliate And Exfoliate Face Towel - Black | B32: KSh 185 | C32: KSh 382 | D32: 0.52 | E32: -9 | F32: 4.3 out of 5
A33: 12 Litre Insulated Lunch Box Grey | B33: KSh 980 | C33: KSh 1,490 | D33: 0.34 | E33: -12 | F33: 4.7 out of 5
A34: LED Eye Protection Desk Lamp , Study, Reading, USB Fan - Double Pen Holder | B34: KSh 1,820 | C34: KSh 3,490 | D34: 0.48 | E34: -9 | F34: 4.3 out of 5
A35: 53Pcs/Set Yarn Knitting Crochet Hooks With Bag - Fortune Cat | B35: KSh 1,940 | C35: KSh 2,650 | D35: 0.27 | E35: -20 | F35: 4.7 out of 5
A36: 53 Pieces/Set Yarn Knitting Crochet Hooks With Bag - Pansies | B36: KSh 1,980 | C36: KSh 2,699 | D36: 0.27 | E36: -32 | F36: 4.5 out of 5
A37: DIY File Folder, Office Drawer File Holder, Pen Holder, Desktop Storage Rack | B37: KSh 1,620 | C37: KSh 2,690 | D37: 0.4 | E37: -1 | F37: 5 out of 5
A38: Classic Black Cat Cotton Hemp Pillow Case For Home Car | B38: KSh 171 | C38: KSh 360 | D38: 0.53 | E38: -2 | F38: 5 out of 5
A39: Punch-free Great Load Bearing Bathroom Storage Rack Wall Shelf-White | B39: KSh 389 | C39: KSh 656 | D39: 0.41 | E39: -36 | F39: 4.3 out of 5
A40: 1/2/3 Seater Elastic Sofa Cover,Living Room/Home Decor Chair Cover-Grey | B40: KSh 1,620 - KSh 1,980 | C40: KSh 2,200 - KSh 3,200 | D40: 0.38 | E40: -2 | F40: 4.5 out of 5
A41: LASA Stainless Steel Double Wall Mount Soap Dispenser - 500ml | B41: KSh 2,750 | C41: KSh 4,471 | D41: 0.38
A42: 4M Float Switch Water Level Controller -Water Tank | B42: KSh 475 | C42: KSh 931 | D42: 0.49
A43: Modern Sofa Throw Pillow Cover-45x45cm-Blue&Red | B43: KSh 238 | C43: KSh 476 | D43: 0.5
A44: Balloon Insert, Birthday Party Balloon Set, PU Leather | B44: KSh 610 | C44: KSh 1,060 | D44: 0.42
A45: Balloon Insert, Birthday Party Balloon Set, PU Leather | B45: KSh 610 | C45: KSh 1,060 | D45: 0.42
A46: Shower Cap Wide Elastic Band Cover Reusable Bashroom Cap | B46: KSh 2,132 | C46: KSh 2,169 | D46: 0.02
A47: Christmas Elk Fence Yard Lawn Decorations Cute For Holidays | B47: KSh 999 | C47: KSh 2,000 | D47: 0.5
A48: 60W Hot Melt Glue Sprayer - Efficient And Stable Glue Dispensing | B48: KSh 1,190 | C48: KSh 1,785 | D48: 0.33
A49: Car Phone Charging Stand | B49: KSh 671 | C49: KSh 1,316 | D49: 0.49
A50: 2pcs Solar Street Light Flood Light Outdoor | B50: KSh 1,200 | C50: KSh 1,950 | D50: 0.38
A51: Creative Owl Shape Keychain Black | B51: KSh 199 | C51: KSh 504 | D51: 0.61
A52: Brush & Paintbrush Cleaning Tool Pink | B52: KSh 299 | C52: KSh 600 | D52: 0.5
... A61: Simple Metal Dog Art Sculpture Decoration For Home Office | B61: KSh 399 | C61: KSh 896 | D61: 0.55
A62: 5 Pieces/set Of Stainless Steel Induction Cooker Pots | B62: KSh 2,170 | C62: KSh 2,500 | D62: 0.13 | E62: -6 | F62: 2.5 out of 5
A63: Mythco 120COB Solar Wall Ligt With Motion Sensor And Remote Control 3 Modes | B63: KSh 458 | C63: KSh 986 | D63: 0.54 | E63: -10 | F63: 3 out of 5
A64: 5-PCS Stainless Steel Cooking Pot Set With Steamed Slices | B64: KSh 2,115 | C64: KSh 4,700 | D64: 0.55 | E64: -13 | F64: 2.1 out of 5
A65: 120W Cordless Vacuum Cleaners Handheld Electric Vacuum Cleaner | B65: KSh 445 | C65: KSh 873 | D65: 0.49 | E65: -69 | F65: 2.8 out of 5
A66: Intelligent LED Body Sensor Wireless Lighting Night Light USB | B66: KSh 325 | C66: KSh 680 | D66: 0.52 | E66: -15 | F66: 2.7 out of 5
A67: VIC Wireless Vacuum Cleaner Dual Use For Home And Car 120W High Power Powerful | B67: KSh 1,220 | C67: KSh 1,555 | D67: 0.22 | E67: -16 | F67: 2.9 out of 5
A68: Artificial Potted Flowers Room Decorative Flowers (2 Pieces) | B68: KSh 990 | C68: KSh 1,814 | D68: 0.45 | E68: -6 | F68: 2.2 out of 5
A69: 380ML USB Rechargeable Portable Small Blenders And Juicers | B69: KSh 1,000 | C69: KSh 2,000 | D69: 0.5 | E69: -7 | F69: 2.3 out of 5
A70: 32PCS Portable Cordless Drill Set With Cyclic Battery Drive -26 Variable Speed | B70: KSh 3,750 | C70: KSh 6,143 | D70: 0.39 | E70: -5 | F70: 3 out of 5
A71: Agapeon Toothbrush Holder And Toothpaste Dispenser | B71: KSh 382 | C71: KSh 700 | D71: 0.45 | E71: -17 | F71: 2.6 out of 5
A72: Large Lazy Inflatable Sofa Chairs PVC Lounger Seat Bag | B72: KSh 2,300 | C72: KSh 3,240 | D72: 0.29 | E72: -5 | F72: 3 out of 5
A73: Watercolour Gold Foil Textured Print Pillow Cover | B73: KSh 345 | C73: KSh 602 | D73: 0.43 | E73: -6 | F73: 2.3 out of 5
... A76: Electric LED UV Mosquito Killer Lamp, Outdoor/Indoor Fly Killer Trap Light -USB | B76: KSh 1,570 | C76: KSh 2,988 | D76: 0.47 | E76: -7 | F76: 2.1 out of 5
A77: 2PCS/LOT Solar LED Outdoor Intelligent Light Controlled Wall Lamp | B77: KSh 790 | C77: KSh 1,485 | D77: 0.47
A78: 3PCS Rotary Scraper Thermomix For Kitchen | B78: KSh 690 | C78: KSh 1,200 | D78: 0.43
A79: Cushion Silicone Butt Cushion Summer Ice Cushion Honeycomb Gel Cushion | B79: KSh 1,732 | C79: KSh 1,799 | D79: 0.04
A80: 7PCS Silicone Thumb Knife Finger Protector Vegetable Harvesting Knife | B80: KSh 230 | C80: KSh 450 | D80: 0.49
A81: Memory Foam Neck Pillow Cover, With Pillow Core - 50*30cm | B81: KSh 1,189 | C81: KSh 2,199 | D81: 0.46 | E81: -1 | F81: 3 out of 5
A82: Bedroom Simple Floor Hanging Clothes Rack Single Pole Hat Rack - White | B82: KSh 979 | C82: KSh 1,920 | D82: 0.49 | E82: -1 | F82: 5 out of 5
A83: 5m Waterproof Spherical LED String Lights Outdoor Ball Chain Lights Party Lighting Decoration Adjustable | B83: KSh 1,460 | C83: KSh 2,290 | D83: 0.36
A84: 2 Pairs Cowhide Split Leather Work Gloves.32℉ Or Above Welding Gloves | B84: KSh 1,666 | C84: KSh 1,699 | D84: 0.02
A85: Household Pineapple Peeler Peeler | B85: KSh 330 | C85: KSh 647 | D85: 0.49 | E85: -1 | F85: 4 out of 5
A86: Balloon Insert, Birthday Party Balloon Set, PU Leather | B86: KSh 610 | C86: KSh 1,060 | D86: 0.42
A87: Creative Owl Shape Keychain Black | B87: KSh 176 | C87: KSh 345 | D87: 0.49
A88: Office Chair Lumbar Back Support Spine Posture Correction Pillow Car Cushion | B88: KSh 1,466 | C88: KSh 1,699 | D88: 0.14
A89: Cartoon Car Decoration Cute Individuality For Car Home Desk | B89: KSh 274 | C89: KSh 537 | D89: 0.49
A90: Outdoor Portable Water Bottle With Medicine Box - 600ML - Black | B90: KSh 799 | C90: KSh 900 | D90: 0.11
A91: Angle Measuring Tool Full Metal Multi Angle Measuring Tool | B91: KSh 657 | C91: KSh 1,288 | D91: 0.49
A92: Wall-Mounted Toothbrush Toothpaste Holder With Multiple Slots | B92: KSh 1,468 | C92: KSh 1,699 | D92: 0.14
A93: Multifunctional Hanging Storage Box Storage Bag (4 Layers) | B93: KSh 630 | C93: KSh 1,100 | D93: 0.43
A94: Wall Clock With Hidden Safe Box | B94: KSh 850 | C94: KSh 1,700 | D94: 0.5
A95: Portable Wine Table With Folding Round Table | B95: KSh 1,300 | C95: KSh 2,500 | D95: 0.48
A96: Sewing Machine Needle Threader Stitch Insertion Tool Automatic Quick Sewing | B96: KSh 105 | C96: KSh 200 | D96: 0.48
A97: 6 Layers Steel Pipe Assembling Dustproof Storage Shoe Cabinet | B97: KSh 899 | C97: KSh 1,699 | D97: 0.47
... A105: 8in1 Screwdriver With LED Light | B105: KSh 1,080 | C105: KSh 1,874 | D105: 0.42
A106: Konka Healty Electric Kettle, 24-hour Heat Preservation,1.5L,800W, White | B106: KSh 3,640 | C106: KSh 4,588 | D106: 0.21 | E106: -1 | F106: 5 out of 5
A107: 9pcs Gas Mask, For Painting, Dust, Formaldehyde Grinding, Polishing | B107: KSh 1,420 | C107: KSh 2,420 | D107: 0.41
A108: 24 Grid Wall-mounted Sundries Organiser Fabric Closet Bag Storage Rack | B108: KSh 1,875 | C108: KSh 1,899 | D108: 0.01
A109: 1PC Refrigerator Food Seal Pocket Fridge Bags | B109: KSh 198 | C109: KSh 260 | D109: 0.24
A110: LED Solar Street Light-fake Camera | B110: KSh 1,150 | C110: KSh 1,737 | D110: 0.34
A111: Cartoon Embroidered Mini Towel Bear Cotton Wash Cloth Hand 4pcs | B111: KSh 1,190 | C111: KSh 1,810 | D111: 0.34
A112: Shower Nozzle Cleaning Unclogging Needle Mini Crevice Small Hole Cleaning Brush | B112: KSh 1,658 | C112: KSh 1,699 | D112: 0.02
A113: Thickening Multipurpose Non Stick Easy To Clean Heat Resistant Spoon Pad | B113: KSh 1,768 | C113: KSh 1,799 | D113: 0.02
A114: 6 In 1 Bottle Can Opener Multifunctional Easy Opener | B114: KSh 199 | C114: KSh 553 | D114: 0.64
A115: Wall-mounted Sticker Punch-free Plug Fixer | B115: KSh 450 | C115: KSh 900 | D115: 0.5 | E115: -1 | F115: 2 out of 5
A116: Black Simple Water Cup Wine Coaster Anti Slip Absorbent | B116: KSh 169 | C116: KSh 320 | D116: 0.47

Sheet tblProducts
A1: Product | B1: Current Price | C1: Old Price | D1: Discount | E1: Review | F1: Rating | G1: Discount Amount | H1: Rating Category | I1: Discount Category | J1: Price Category | K1: Engagement | L1: High discount + low rating | M1: High discount + low engagement | N1: Many reviews + average rating | O1: Strong engagement + excellent rating | P1: Rating Status | Q1: Calculated Discount | R1: Discount Difference | S1: Rating check | T1: Discount Check | U1: Price check
A2: 115 Piece Set Of Multifunctional Precision Screwdrivers | B2: 950 | C2: 1525 | D2: 0.38 | E2: 2 | F2: 4.5 | G2: =Cleaned_Data[[#This Row],[Old Price]]-Cleaned_Data[[#This Row],[Current Price]] -> 575 | H2: =IF(Cleaned_Data[[#This Row],[Rating]]="","Missing",IF(Cleaned_Data[[#This Row],[Rating]]<3,"Poor",IF(Cleaned_Data[[#This Row],[Rating]]<=4.5,"Average","Excellent"))) -> Average | I2: =IF( Cleaned_Data[[#This Row],[Discount]]="", "Missing", IF( Cleaned_Data[[#This Row],[Discount]]<20%, "Low Discount", IF( Cleaned_Data[[#This Row],[Discount]]<=40%, "Medium Discount", "High Discount" ) ) ) -> Medium Discount | J2: =IF( Cleaned_Data[[#This Row],[Current Price]]="", "Missing", IF( Cleaned_Data[[#This Row],[Current Price]]<=Analysis!$B$3, "Low Price", IF( Cleaned_Data[[#This Row],[Current Price]]<=Analysis!$B$4, "Medium Price", "High Price" ) ) ) -> Medium Price | K2: =IF(Cleaned_Data[[#This Row],[Review]]="","Missing",IF(Cleaned_Data[[#This Row],[Review]]>=Engagement_Threshold,"Strong Engagement","Weak Engagement")) -> Weak Engagement | L2: =IF(OR(Cleaned_Data[[#This Row],[Discount]]="",Cleaned_Data[[#This Row],[Rating]]=""),"Missing",IF(AND(Cleaned_Data[[#This Row],[Discount Category]]="High Discount",Cleaned_Data[[#This Row],[Rating Category]]="Poor"),"Flag","OK")) -> OK | M2: =IF(OR(Cleaned_Data[[#This Row],[Discount]]="",Cleaned_Data[[#This Row],[Review]]=""),"Missing",IF(AND(Cleaned_Data[[#This Row],[Discount Category]]="High Discount",Cleaned_Data[[#This Row],[Engagement]]="Weak Engagement"),"Flag","OK")) -> OK | N2: =IF(OR(Cleaned_Data[[#This Row],[Review]]="",Cleaned_Data[[#This Row],[Rating]]=""),"Missing",IF(AND(Cleaned_Data[[#This Row],[Engagement]]="Strong Engagement",Cleaned_Data[[#This Row],[Rating Category]]="Average"),"Flag","OK")) -> OK | O2: =IF(OR(Cleaned_Data[[#This Row],[Review]]="",Cleaned_Data[[#This Row],[Rating]]=""),"Missing",IF(AND(Cleaned_Data[[#This Row],[Engagement]]="Strong Engagement",Cleaned_Data[[#This Row],[Rating Category]]="Excellent"),"Flag","OK")) -> OK | P2: =IF(Cleaned_Data[[#This Row],[Rating]]="","Missing Rating","Has Rating") -> Has Rating | Q2: =IFERROR( (Cleaned_Data[[#This Row],[Old Price]]-Cleaned_Data[[#This Row],[Current Price]])/Cleaned_Data[[#This Row],[Old Price]], "" ) -> 0.37704918 | R2: =IF( Cleaned_Data[[#This Row],[Discount]] - Cleaned_Data[[#This Row],[Calculated Discount]]>2%, "Check", "OK" ) -> OK | S2: =IF(OR(Cleaned_Data[[#This Row],[Rating]]<0,Cleaned_Data[[#This Row],[Rating]]>5),"Check rating","OK") -> OK | T2: =IF(OR(Cleaned_Data[[#This Row],[Discount]]<0,Cleaned_Data[[#This Row],[Discount]]>1),"Check discount","OK") -> OK | U2: =IF(Cleaned_Data[[#This Row],[Current Price]]>Cleaned_Data[[#This Row],[Old Price]],"Check prices","OK") -> OK
A3: Metal Decorative Hooks Key Hangers Entryway Wall Hooks Towel Hooks - Home | B3: 527 | C3: 999 | D3: 0.47 | E3: 14 | F3: 4.1 | G3: =Cleaned_Data[[#This Row],[Old Price]]-Cleaned_Data[[#This Row],[Current Price]] -> 472 | H3: =IF(Cleaned_Data[[#This Row],[Rating]]="","Missing",IF(Cleaned_Data[[#This Row],[Rating]]<3,"Poor",IF(Cleaned_Data[[#This Row],[Rating]]<=4.5,"Average","Excellent"))) -> Average | I3: =IF( Cleaned_Data[[#This Row],[Discount]]="", "Missing", IF( Cleaned_Data[[#This Row],[Discount]]<20%, "Low Discount", IF( Cleaned_Data[[#This Row],[Discount]]<=40%, "Medium Discount", "High Discount" ) ) ) -> High Discount | J3: =IF( Cleaned_Data[[#This Row],[Current Price]]="", "Missing", IF( Cleaned_Data[[#This Row],[Current Price]]<=Analysis!$B$3, "Low Price", IF( Cleaned_Data[[#This Row],[Current Price]]<=Analysis!$B$4, "Medium Price", "High Price" ) ) ) -> Medium Price | K3: =IF(Cleaned_Data[[#This Row],[Review]]="","Missing",IF(Cleaned_Data[[#This Row],[Review]]>=Engagement_Threshold,"Strong Engagement","Weak Engagement")) -> Strong Engagement | L3: =IF(OR(Cleaned_Data[[#This Row],[Discount]]="",Cleaned_Data[[#This Row],[Rating]]=""),"Missing",IF(AND(Cleaned_Data[[#This Row],[Discount Category]]="High Discount",Cleaned_Data[[#This Row],[Rating Category]]="Poor"),"Flag","OK")) -> OK | M3: =IF(OR(Cleaned_Data[[#This Row],[Discount]]="",Cleaned_Data[[#This Row],[Review]]=""),"Missing",IF(AND(Cleaned_Data[[#This Row],[Discount Category]]="High Discount",Cleaned_Data[[#This Row],[Engagement]]="Weak Engagement"),"Flag","OK")) -> OK | N3: =IF(OR(Cleaned_Data[[#This Row],[Review]]="",Cleaned_Data[[#This Row],[Rating]]=""),"Missing",IF(AND(Cleaned_Data[[#This Row],[Engagement]]="Strong Engagement",Cleaned_Data[[#This Row],[Rating Category]]="Average"),"Flag","OK")) -> Flag | O3: =IF(OR(Cleaned_Data[[#This Row],[Review]]="",Cleaned_Data[[#This Row],[Rating]]=""),"Missing",IF(AND(Cleaned_Data[[#This Row],[Engagement]]="Strong Engagement",Cleaned_Data[[#This Row],[Rating Category]]="Excellent"),"Flag","OK")) -> OK | P3: =IF(Cleaned_Data[[#This Row],[Rating]]="","Missing Rating","Has Rating") -> Has Rating | Q3: =IFERROR( (Cleaned_Data[[#This Row],[Old Price]]-Cleaned_Data[[#This Row],[Current Price]])/Cleaned_Data[[#This Row],[Old Price]], "" ) -> 0.47247247 | R3: =IF( Cleaned_Data[[#This Row],[Discount]] - Cleaned_Data[[#This Row],[Calculated Discount]]>2%, "Check", "OK" ) -> OK | S3: =IF(OR(Cleaned_Data[[#This Row],[Rating]]<0,Cleaned_Data[[#This Row],[Rating]]>5),"Check rating","OK") -> OK | T3: =IF(OR(Cleaned_Data[[#This Row],[Discount]]<0,Cleaned_Data[[#This Row],[Discount]]>1),"Check discount","OK") -> OK | U3: =IF(Cleaned_Data[[#This Row],[Current Price]]>Cleaned_Data[[#This Row],[Old Price]],"Check prices","OK") -> OK
A4: Portable Mini Cordless Car Vacuum Cleaner - Blue | B4: 2199 | C4: 2923 | D4: 0.25 | E4: 24 | F4: 4.6 | G4: =Cleaned_Data[[#This Row],[Old Price]]-Cleaned_Data[[#This Row],[Current Price]] -> 724 | H4: =IF(Cleaned_Data[[#This Row],[Rating]]="","Missing",IF(Cleaned_Data[[#This Row],[Rating]]<3,"Poor",IF(Cleaned_Data[[#This Row],[Rating]]<=4.5,"Average","Excellent"))) -> Excellent | I4: =IF( Cleaned_Data[[#This Row],[Discount]]="", "Missing", IF( Cleaned_Data[[#This Row],[Discount]]<20%, "Low Discount", IF( Cleaned_Data[[#This Row],[Discount]]<=40%, "Medium Discount", "High Discount" ) ) ) -> Medium Discount | J4: =IF( Cleaned_Data[[#This Row],[Current Price]]="", "Missing", IF( Cleaned_Data[[#This Row],[Current Price]]<=Analysis!$B$3, "Low Price", IF( Cleaned_Data[[#This Row],[Current Price]]<=Analysis!$B$4, "Medium Price", "High Price" ) ) ) -> High Price | K4: =IF(Cleaned_Data[[#This Row],[Review]]="","Missing",IF(Cleaned_Data[[#This Row],[Review]]>=Engagement_Threshold,"Strong Engagement","Weak Engagement")) -> Strong Engagement | L4: =IF(OR(Cleaned_Data[[#This Row],[Discount]]="",Cleaned_Data[[#This Row],[Rating]]=""),"Missing",IF(AND(Cleaned_Data[[#This Row],[Discount Category]]="High Discount",Cleaned_Data[[#This Row],[Rating Category]]="Poor"),"Flag","OK")) -> OK | M4: =IF(OR(Cleaned_Data[[#This Row],[Discount]]="",Cleaned_Data[[#This Row],[Review]]=""),"Missing",IF(AND(Cleaned_Data[[#This Row],[Discount Category]]="High Discount",Cleaned_Data[[#This Row],[Engagement]]="Weak Engagement"),"Flag","OK")) -> OK | N4: =IF(OR(Cleaned_Data[[#This Row],[Review]]="",Cleaned_Data[[#This Row],[Rating]]=""),"Missing",IF(AND(Cleaned_Data[[#This Row],[Engagement]]="Strong Engagement",Cleaned_Data[[#This Row],[Rating Category]]="Average"),"Flag","OK")) -> OK | O4: =IF(OR(Cleaned_Data[[#This Row],[Review]]="",Cleaned_Data[[#This Row],[Rating]]=""),"Missing",IF(AND(Cleaned_Data[[#This Row],[Engagement]]="Strong Engagement",Cleaned_Data[[#This Row],[Rating Category]]="Excellent"),"Flag","OK")) -> Flag | P4: =IF(Cleaned_Data[[#This Row],[Rating]]="","Missing Rating","Has Rating") -> Has Rating | Q4: =IFERROR( (Cleaned_Data[[#This Row],[Old Price]]-Cleaned_Data[[#This Row],[Current Price]])/Cleaned_Data[[#This Row],[Old Price]], "" ) -> 0.24769073 | R4: =IF( Cleaned_Data[[#This Row],[Discount]] - Cleaned_Data[[#This Row],[Calculated Discount]]>2%, "Check", "OK" ) -> OK | S4: =IF(OR(Cleaned_Data[[#This Row],[Rating]]<0,Cleaned_Data[[#This Row],[Rating]]>5),"Check rating","OK") -> OK | T4: =IF(OR(Cleaned_Data[[#This Row],[Discount]]<0,Cleaned_Data[[#This Row],[Discount]]>1),"Check discount","OK") -> OK | U4: =IF(Cleaned_Data[[#This Row],[Current Price]]>Cleaned_Data[[#This Row],[Old Price]],"Check prices","OK") -> OK
A5: Weighing Scale Digital Bathroom Body Fat Scale USB-Black | B5: 1580 | C5: 2499 | D5: 0.37 | E5: 7 | F5: 4.7 | G5: =Cleaned_Data[[#This Row],[Old Price]]-Cleaned_Data[[#This Row],[Current Price]] -> 919 | H5: =IF(Cleaned_Data[[#This Row],[Rating]]="","Missing",IF(Cleaned_Data[[#This Row],[Rating]]<3,"Poor",IF(Cleaned_Data[[#This Row],[Rating]]<=4.5,"Average","Excellent"))) -> Excellent | I5: =IF( Cleaned_Data[[#This Row],[Discount]]="", "Missing", IF( Cleaned_Data[[#This Row],[Discount]]<20%, "Low Discount", IF( Cleaned_Data[[#This Row],[Discount]]<=40%, "Medium Discount", "High Discount" ) ) ) -> Medium Discount | J5: =IF( Cleaned_Data[[#This Row],[Current Price]]="", "Missing", IF( Cleaned_Data[[#This Row],[Current Price]]<=Analysis!$B$3, "Low Price", IF( Cleaned_Data[[#This Row],[Current Price]]<=Analysis!$B$4, "Medium Price", "High Price" ) ) ) -> Medium Price | K5: =IF(Cleaned_Data[[#This Row],[Review]]="","Missing",IF(Cleaned_Data[[#This Row],[Review]]>=Engagement_Threshold,"Strong Engagement","Weak Engagement")) -> Weak Engagement | L5: =IF(OR(Cleaned_Data[[#This Row],[Discount]]="",Cleaned_Data[[#This Row],[Rating]]=""),"Missing",IF(AND(Cleaned_Data[[#This Row],[Discount Category]]="High Discount",Cleaned_Data[[#This Row],[Rating Category]]="Poor"),"Flag","OK")) -> OK | M5: =IF(OR(Cleaned_Data[[#This Row],[Discount]]="",Cleaned_Data[[#This Row],[Review]]=""),"Missing",IF(AND(Cleaned_Data[[#This Row],[Discount Category]]="High Discount",Cleaned_Data[[#This Row],[Engagement]]="Weak Engagement"),"Flag","OK")) -> OK | N5: =IF(OR(Cleaned_Data[[#This Row],[Review]]="",Cleaned_Data[[#This Row],[Rating]]=""),"Missing",IF(AND(Cleaned_Data[[#This Row],[Engagement]]="Strong Engagement",Cleaned_Data[[#This Row],[Rating Category]]="Average"),"Flag","OK")) -> OK | O5: =IF(OR(Cleaned_Data[[#This Row],[Review]]="",Cleaned_Data[[#This Row],[Rating]]=""),"Missing",IF(AND(Cleaned_Data[[#This Row],[Engagement]]="Strong Engagement",Cleaned_Data[[#This Row],[Rating Category]]="Excellent"),"Flag","OK")) -> OK | P5: =IF(Cleaned_Data[[#This Row],[Rating]]="","Missing Rating","Has Rating") -> Has Rating | Q5: =IFERROR( (Cleaned_Data[[#This Row],[Old Price]]-Cleaned_Data[[#This Row],[Current Price]])/Cleaned_Data[[#This Row],[Old Price]], "" ) -> 0.3677471 | R5: =IF( Cleaned_Data[[#This Row],[Discount]] - Cleaned_Data[[#This Row],[Calculated Discount]]>2%, "Check", "OK" ) -> OK | S5: =IF(OR(Cleaned_Data[[#This Row],[Rating]]<0,Cleaned_Data[[#This Row],[Rating]]>5),"Check rating","OK") -> OK | T5: =IF(OR(Cleaned_Data[[#This Row],[Discount]]<0,Cleaned_Data[[#This Row],[Discount]]>1),"Check discount","OK") -> OK | U5: =IF(Cleaned_Data[[#This Row],[Current Price]]>Cleaned_Data[[#This Row],[Old Price]],"Check prices","OK") -> OK
A6: Portable Home Small Air Humidifier 3-Speed Fan - Green | B6: 1740 | C6: 2356 | D6: 0.26 | E6: 5 | F6: 4.8 | G6: =Cleaned_Data[[#This Row],[Old Price]]-Cleaned_Data[[#This Row],[Current Price]] -> 616 | H6: =IF(Cleaned_Data[[#This Row],[Rating]]="","Missing",IF(Cleaned_Data[[#This Row],[Rating]]<3,"Poor",IF(Cleaned_Data[[#This Row],[Rating]]<=4.5,"Average","Excellent"))) -> Excellent | I6: =IF( Cleaned_Data[[#This Row],[Discount]]="", "Missing", IF( Cleaned_Data[[#This Row],[Discount]]<20%, "Low Discount", IF( Cleaned_Data[[#This Row],[Discount]]<=40%, "Medium Discount", "High Discount" ) ) ) -> Medium Discount | J6: =IF( Cleaned_Data[[#This Row],[Current Price]]="", "Missing", IF( Cleaned_Data[[#This Row],[Current Price]]<=Analysis!$B$3, "Low Price", IF( Cleaned_Data[[#This Row],[Current Price]]<=Analysis!$B$4, "Medium Price", "High Price" ) ) ) -> High Price | K6: =IF(Cleaned_Data[[#This Row],[Review]]="","Missing",IF(Cleaned_Data[[#This Row],[Review]]>=Engagement_Threshold,"Strong Engagement","Weak Engagement")) -> Weak Engagement | L6: =IF(OR(Cleaned_Data[[#This Row],[Discount]]="",Cleaned_Data[[#This Row],[Rating]]=""),"Missing",IF(AND(Cleaned_Data[[#This Row],[Discount Category]]="High Discount",Cleaned_Data[[#This Row],[Rating Category]]="Poor"),"Flag","OK")) -> OK | M6: =IF(OR(Cleaned_Data[[#This Row],[Discount]]="",Cleaned_Data[[#This Row],[Review]]=""),"Missing",IF(AND(Cleaned_Data[[#This Row],[Discount Category]]="High Discount",Cleaned_Data[[#This Row],[Engagement]]="Weak Engagement"),"Flag","OK")) -> OK | N6: =IF(OR(Cleaned_Data[[#This Row],[Review]]="",Cleaned_Data[[#This Row],[Rating]]=""),"Missing",IF(AND(Cleaned_Data[[#This Row],[Engagement]]="Strong Engagement",Cleaned_Data[[#This Row],[Rating Category]]="Average"),"Flag","OK")) -> OK | O6: =IF(OR(Cleaned_Data[[#This Row],[Review]]="",Cleaned_Data[[#This Row],[Rating]]=""),"Missing",IF(AND(Cleaned_Data[[#This Row],[Engagement]]="Strong Engagement",Cleaned_Data[[#This Row],[Rating Category]]="Excellent"),"Flag","OK")) -> OK | P6: =IF(Cleaned_Data[[#This Row],[Rating]]="","Missing Rating","Has Rating") -> Has Rating | Q6: =IFERROR( (Cleaned_Data[[#This Row],[Old Price]]-Cleaned_Data[[#This Row],[Current Price]])/Cleaned_Data[[#This Row],[Old Price]], "" ) -> 0.2614601 | R6: =IF( Cleaned_Data[[#This Row],[Discount]] - Cleaned_Data[[#This Row],[Calculated Discount]]>2%, "Check", "OK" ) -> OK | S6: =IF(OR(Cleaned_Data[[#This Row],[Rating]]<0,Cleaned_Data[[#This Row],[Rating]]>5),"Check rating","OK") -> OK | T6: =IF(OR(Cleaned_Data[[#This Row],[Discount]]<0,Cleaned_Data[[#This Row],[Discount]]>1),"Check discount","OK") -> OK | U6: =IF(Cleaned_Data[[#This Row],[Current Price]]>Cleaned_Data[[#This Row],[Old Price]],"Check prices","OK") -> OK
A7: 220V 60W Electric Soldering Iron Kits With Tools, Tips, And Multimeter | B7: 2999 | C7: 3290 | D7: 0.09 | E7: 15 | F7: 4 | G7: =Cleaned_Data[[#This Row],[Old Price]]-Cleaned_Data[[#This Row],[Current Price]] -> 291 | H7: =IF(Cleaned_Data[[#This Row],[Rating]]="","Missing",IF(Cleaned_Data[[#This Row],[Rating]]<3,"Poor",IF(Cleaned_Data[[#This Row],[Rating]]<=4.5,"Average","Excellent"))) -> Average | I7: =IF( Cleaned_Data[[#This Row],[Discount]]="", "Missing", IF( Cleaned_Data[[#This Row],[Discount]]<20%, "Low Discount", IF( Cleaned_Data[[#This Row],[Discount]]<=40%, "Medium Discount", "High Discount" ) ) ) -> Low Discount | J7: =IF( Cleaned_Data[[#This Row],[Current Price]]="", "Missing", IF( Cleaned_Data[[#This Row],[Current Price]]<=Analysis!$B$3, "Low Price", IF( Cleaned_Data[[#This Row],[Current Price]]<=Analysis!$B$4, "Medium Price", "High Price" ) ) ) -> High Price | K7: =IF(Cleaned_Data[[#This Row],[Review]]="","Missing",IF(Cleaned_Data[[#This Row],[Review]]>=Engagement_Threshold,"Strong Engagement","Weak Engagement")) -> Strong Engagement | L7: =IF(OR(Cleaned_Data[[#This Row],[Discount]]="",Cleaned_Data[[#This Row],[Rating]]=""),"Missing",IF(AND(Cleaned_Data[[#This Row],[Discount Category]]="High Discount",Cleaned_Data[[#This Row],[Rating Category]]="Poor"),"Flag","OK")) -> OK | M7: =IF(OR(Cleaned_Data[[#This Row],[Discount]]="",Cleaned_Data[[#This Row],[Review]]=""),"Missing",IF(AND(Cleaned_Data[[#This Row],[Discount Category]]="High Discount",Cleaned_Data[[#This Row],[Engagement]]="Weak Engagement"),"Flag","OK")) -> OK | N7: =IF(OR(Cleaned_Data[[#This Row],[Review]]="",Cleaned_Data[[#This Row],[Rating]]=""),"Missing",IF(AND(Cleaned_Data[[#This Row],[Engagement]]="Strong Engagement",Cleaned_Data[[#This Row],[Rating Category]]="Average"),"Flag","OK")) -> Flag | O7: =IF(OR(Cleaned_Data[[#This Row],[Review]]="",Cleaned_Data[[#This Row],[Rating]]=""),"Missing",IF(AND(Cleaned_Data[[#This Row],[Engagement]]="Strong Engagement",Cleaned_Data[[#This Row],[Rating Category]]="Excellent"),"Flag","OK")) -> OK | P7: =IF(Cleaned_Data[[#This Row],[Rating]]="","Missing Rating","Has Rating") -> Has Rating | Q7: =IFERROR( (Cleaned_Data[[#This Row],[Old Price]]-Cleaned_Data[[#This Row],[Current Price]])/Cleaned_Data[[#This Row],[Old Price]], "" ) -> 0.088449848 | R7: =IF( Cleaned_Data[[#This Row],[Discount]] - Cleaned_Data[[#This Row],[Calculated Discount]]>2%, "Check", "OK" ) -> OK | S7: =IF(OR(Cleaned_Data[[#This Row],[Rating]]<0,Cleaned_Data[[#This Row],[Rating]]>5),"Check rating","OK") -> OK | T7: =IF(OR(Cleaned_Data[[#This Row],[Discount]]<0,Cleaned_Data[[#This Row],[Discount]]>1),"Check discount","OK") -> OK | U7: =IF(Cleaned_Data[[#This Row],[Current Price]]>Cleaned_Data[[#This Row],[Old Price]],"Check prices","OK") -> OK
A8: 137 Pieces Cake Decorating Tool Set Baking Supplies | B8: 2319 | C8: 3032 | D8: 0.24 | E8: 55 | F8: 4.6 | G8: =Cleaned_Data[[#This Row],[Old Price]]-Cleaned_Data[[#This Row],[Current Price]] -> 713 | H8: =IF(Cleaned_Data[[#This Row],[Rating]]="","Missing",IF(Cleaned_Data[[#This Row],[Rating]]<3,"Poor",IF(Cleaned_Data[[#This Row],[Rating]]<=4.5,"Average","Excellent"))) -> Excellent | I8: =IF( Cleaned_Data[[#This Row],[Discount]]="", "Missing", IF( Cleaned_Data[[#This Row],[Discount]]<20%, "Low Discount", IF( Cleaned_Data[[#This Row],[Discount]]<=40%, "Medium Discount", "High Discount" ) ) ) -> Medium Discount | J8: =IF( Cleaned_Data[[#This Row],[Current Price]]="", "Missing", IF( Cleaned_Data[[#This Row],[Current Price]]<=Analysis!$B$3, "Low Price", IF( Cleaned_Data[[#This Row],[Current Price]]<=Analysis!$B$4, "Medium Price", "High Price" ) ) ) -> High Price | K8: =IF(Cleaned_Data[[#This Row],[Review]]="","Missing",IF(Cleaned_Data[[#This Row],[Review]]>=Engagement_Threshold,"Strong Engagement","Weak Engagement")) -> Strong Engagement | L8: =IF(OR(Cleaned_Data[[#This Row],[Discount]]="",Cleaned_Data[[#This Row],[Rating]]=""),"Missing",IF(AND(Cleaned_Data[[#This Row],[Discount Category]]="High Discount",Cleaned_Data[[#This Row],[Rating Category]]="Poor"),"Flag","OK")) -> OK | M8: =IF(OR(Cleaned_Data[[#This Row],[Discount]]="",Cleaned_Data[[#This Row],[Review]]=""),"Missing",IF(AND(Cleaned_Data[[#This Row],[Discount Category]]="High Discount",Cleaned_Data[[#This Row],[Engagement]]="Weak Engagement"),"Flag","OK")) -> OK | N8: =IF(OR(Cleaned_Data[[#This Row],[Review]]="",Cleaned_Data[[#This Row],[Rating]]=""),"Missing",IF(AND(Cleaned_Data[[#This Row],[Engagement]]="Strong Engagement",Cleaned_Data[[#This Row],[Rating Category]]="Average"),"Flag","OK")) -> OK | O8: =IF(OR(Cleaned_Data[[#This Row],[Review]]="",Cleaned_Data[[#This Row],[Rating]]=""),"Missing",IF(AND(Cleaned_Data[[#This Row],[Engagement]]="Strong Engagement",Cleaned_Data[[#This Row],[Rating Category]]="Excellent"),"Flag","OK")) -> Flag | P8: =IF(Cleaned_Data[[#This Row],[Rating]]="","Missing Rating","Has Rating") -> Has Rating | Q8: =IFERROR( (Cleaned_Data[[#This Row],[Old Price]]-Cleaned_Data[[#This Row],[Current Price]])/Cleaned_Data[[#This Row],[Old Price]], "" ) -> 0.23515831 | R8: =IF( Cleaned_Data[[#This Row],[Discount]] - Cleaned_Data[[#This Row],[Calculated Discount]]>2%, "Check", "OK" ) -> OK | S8: =IF(OR(Cleaned_Data[[#This Row],[Rating]]<0,Cleaned_Data[[#This Row],[Rating]]>5),"Check rating","OK") -> OK | T8: =IF(OR(Cleaned_Data[[#This Row],[Discount]]<0,Cleaned_Data[[#This Row],[Discount]]>1),"Check discount","OK") -> OK | U8: =IF(Cleaned_Data[[#This Row],[Current Price]]>Cleaned_Data[[#This Row],[Old Price]],"Check prices","OK") -> OK
A9: Desk Foldable Fan Adjustable Fan Strong Wind 3 Gear Usb | B9: 988 | C9: 1580 | D9: 0.37 | E9: 2 | F9: 4 | G9: =Cleaned_Data[[#This Row],[Old Price]]-Cleaned_Data[[#This Row],[Current Price]] -> 592 | H9: =IF(Cleaned_Data[[#This Row],[Rating]]="","Missing",IF(Cleaned_Data[[#This Row],[Rating]]<3,"Poor",IF(Cleaned_Data[[#This Row],[Rating]]<=4.5,"Average","Excellent"))) -> Average | I9: =IF( Cleaned_Data[[#This Row],[Discount]]="", "Missing", IF( Cleaned_Data[[#This Row],[Discount]]<20%, "Low Discount", IF( Cleaned_Data[[#This Row],[Discount]]<=40%, "Medium Discount", "High Discount" ) ) ) -> Medium Discount | J9: =IF( Cleaned_Data[[#This Row],[Current Price]]="", "Missing", IF( Cleaned_Data[[#This Row],[Current Price]]<=Analysis!$B$3, "Low Price", IF( Cleaned_Data[[#This Row],[Current Price]]<=Analysis!$B$4, "Medium Price", "High Price" ) ) ) -> Medium Price | K9: =IF(Cleaned_Data[[#This Row],[Review]]="","Missing",IF(Cleaned_Data[[#This Row],[Review]]>=Engagement_Threshold,"Strong Engagement","Weak Engagement")) -> Weak Engagement | L9: =IF(OR(Cleaned_Data[[#This Row],[Discount]]="",Cleaned_Data[[#This Row],[Rating]]=""),"Missing",IF(AND(Cleaned_Data[[#This Row],[Discount Category]]="High Discount",Cleaned_Data[[#This Row],[Rating Category]]="Poor"),"Flag","OK")) -> OK | M9: =IF(OR(Cleaned_Data[[#This Row],[Discount]]="",Cleaned_Data[[#This Row],[Review]]=""),"Missing",IF(AND(Cleaned_Data[[#This Row],[Discount Category]]="High Discount",Cleaned_Data[[#This Row],[Engagement]]="Weak Engagement"),"Flag","OK")) -> OK | N9: =IF(OR(Cleaned_Data[[#This Row],[Review]]="",Cleaned_Data[[#This Row],[Rating]]=""),"Missing",IF(AND(Cleaned_Data[[#This Row],[Engagement]]="Strong Engagement",Cleaned_Data[[#This Row],[Rating Category]]="Average"),"Flag","OK")) -> OK | O9: =IF(OR(Cleaned_Data[[#This Row],[Review]]="",Cleaned_Data[[#This Row],[Rating]]=""),"Missing",IF(AND(Cleaned_Data[[#This Row],[Engagement]]="Strong Engagement",Cleaned_Data[[#This Row],[Rating Category]]="Excellent"),"Flag","OK")) -> OK | P9: =IF(Cleaned_Data[[#This Row],[Rating]]="","Missing Rating","Has Rating") -> Has Rating | Q9: =IFERROR( (Cleaned_Data[[#This Row],[Old Price]]-Cleaned_Data[[#This Row],[Current Price]])/Cleaned_Data[[#This Row],[Old Price]], "" ) -> 0.37468354 | R9: =IF( Cleaned_Data[[#This Row],[Discount]] - Cleaned_Data[[#This Row],[Calculated Discount]]>2%, "Check", "OK" ) -> OK | S9: =IF(OR(Cleaned_Data[[#This Row],[Rating]]<0,Cleaned_Data[[#This Row],[Rating]]>5),"Check rating","OK") -> OK | T9: =IF(OR(Cleaned_Data[[#This Row],[Discount]]<0,Cleaned_Data[[#This Row],[Discount]]>1),"Check discount","OK") -> OK | U9: =IF(Cleaned_Data[[#This Row],[Current Price]]>Cleaned_Data[[#This Row],[Old Price]],"Check prices","OK") -> OK
A10: LASA FOLDING TABLE SERVING STAND | B10: 1274 | C10: 2800 | D10: 0.55 | E10: 5 | F10: 4.8 | G10: =Cleaned_Data[[#This Row],[Old Price]]-Cleaned_Data[[#This Row],[Current Price]] -> 1526 | H10: =IF(Cleaned_Data[[#This Row],[Rating]]="","Missing",IF(Cleaned_Data[[#This Row],[Rating]]<3,"Poor",IF(Cleaned_Data[[#This Row],[Rating]]<=4.5,"Average","Excellent"))) -> Excellent | I10: =IF( Cleaned_Data[[#This Row],[Discount]]="", "Missing", IF( Cleaned_Data[[#This Row],[Discount]]<20%, "Low Discount", IF( Cleaned_Data[[#This Row],[Discount]]<=40%, "Medium Discount", "High Discount" ) ) ) -> High Discount | J10: =IF( Cleaned_Data[[#This Row],[Current Price]]="", "Missing", IF( Cleaned_Data[[#This Row],[Current Price]]<=Analysis!$B$3, "Low Price", IF( Cleaned_Data[[#This Row],[Current Price]]<=Analysis!$B$4, "Medium Price", "High Price" ) ) ) -> Medium Price | K10: =IF(Cleaned_Data[[#This Row],[Review]]="","Missing",IF(Cleaned_Data[[#This Row],[Review]]>=Engagement_Threshold,"Strong Engagement","Weak Engagement")) -> Weak Engagement | L10: =IF(OR(Cleaned_Data[[#This Row],[Discount]]="",Cleaned_Data[[#This Row],[Rating]]=""),"Missing",IF(AND(Cleaned_Data[[#This Row],[Discount Category]]="High Discount",Cleaned_Data[[#This Row],[Rating Category]]="Poor"),"Flag","OK")) -> OK | M10: =IF(OR(Cleaned_Data[[#This Row],[Discount]]="",Cleaned_Data[[#This Row],[Review]]=""),"Missing",IF(AND(Cleaned_Data[[#This Row],[Discount Category]]="High Discount",Cleaned_Data[[#This Row],[Engagement]]="Weak Engagement"),"Flag","OK")) -> Flag | N10: =IF(OR(Cleaned_Data[[#This Row],[Review]]="",Cleaned_Data[[#This Row],[Rating]]=""),"Missing",IF(AND(Cleaned_Data[[#This Row],[Engagement]]="Strong Engagement",Cleaned_Data[[#This Row],[Rating Category]]="Average"),"Flag","OK")) -> OK | O10: =IF(OR(Cleaned_Data[[#This Row],[Review]]="",Cleaned_Data[[#This Row],[Rating]]=""),"Missing",IF(AND(Cleaned_Data[[#This Row],[Engagement]]="Strong Engagement",Cleaned_Data[[#This Row],[Rating Category]]="Excellent"),"Flag","OK")) -> OK | P10: =IF(Cleaned_Data[[#This Row],[Rating]]="","Missing Rating","Has Rating") -> Has Rating | Q10: =IFERROR( (Cleaned_Data[[#This Row],[Old Price]]-Cleaned_Data[[#This Row],[Current Price]])/Cleaned_Data[[#This Row],[Old Price]], "" ) -> 0.545 | R10: =IF( Cleaned_Data[[#This Row],[Discount]] - Cleaned_Data[[#This Row],[Calculated Discount]]>2%, "Check", "OK" ) -> OK | S10: =IF(OR(Cleaned_Data[[#This Row],[Rating]]<0,Cleaned_Data[[#This Row],[Rating]]>5),"Check rating","OK") -> OK | T10: =IF(OR(Cleaned_Data[[#This Row],[Discount]]<0,Cleaned_Data[[#This Row],[Discount]]>1),"Check discount","OK") -> OK | U10: =IF(Cleaned_Data[[#This Row],[Current Price]]>Cleaned_Data[[#This Row],[Old Price]],"Check prices","OK") -> OK
A11: 13 In 1 Home Repair Tools Box Kit Set | B11: 1600 | C11: 2929 | D11: 0.45 | E11: 5 | F11: 3.8 | G11: =Cleaned_Data[[#This Row],[Old Price]]-Cleaned_Data[[#This Row],[Current Price]] -> 1329 | H11: =IF(Cleaned_Data[[#This Row],[Rating]]="","Missing",IF(Cleaned_Data[[#This Row],[Rating]]<3,"Poor",IF(Cleaned_Data[[#This Row],[Rating]]<=4.5,"Average","Excellent"))) -> Average | I11: =IF( Cleaned_Data[[#This Row],[Discount]]="", "Missing", IF( Cleaned_Data[[#This Row],[Discount]]<20%, "Low Discount", IF( Cleaned_Data[[#This Row],[Discount]]<=40%, "Medium Discount", "High Discount" ) ) ) -> High Discount | J11: =IF( Cleaned_Data[[#This Row],[Current Price]]="", "Missing", IF( Cleaned_Data[[#This Row],[Current Price]]<=Analysis!$B$3, "Low Price", IF( Cleaned_Data[[#This Row],[Current Price]]<=Analysis!$B$4, "Medium Price", "High Price" ) ) ) -> Medium Price | K11: =IF(Cleaned_Data[[#This Row],[Review]]="","Missing",IF(Cleaned_Data[[#This Row],[Review]]>=Engagement_Threshold,"Strong Engagement","Weak Engagement")) -> Weak Engagement | L11: =IF(OR(Cleaned_Data[[#This Row],[Discount]]="",Cleaned_Data[[#This Row],[Rating]]=""),"Missing",IF(AND(Cleaned_Data[[#This Row],[Discount Category]]="High Discount",Cleaned_Data[[#This Row],[Rating Category]]="Poor"),"Flag","OK")) -> OK | M11: =IF(OR(Cleaned_Data[[#This Row],[Discount]]="",Cleaned_Data[[#This Row],[Review]]=""),"Missing",IF(AND(Cleaned_Data[[#This Row],[Discount Category]]="High Discount",Cleaned_Data[[#This Row],[Engagement]]="Weak Engagement"),"Flag","OK")) -> Flag | N11: =IF(OR(Cleaned_Data[[#This Row],[Review]]="",Cleaned_Data[[#This Row],[Rating]]=""),"Missing",IF(AND(Cleaned_Data[[#This Row],[Engagement]]="Strong Engagement",Cleaned_Data[[#This Row],[Rating Category]]="Average"),"Flag","OK")) -> OK | O11: =IF(OR(Cleaned_Data[[#This Row],[Review]]="",Cleaned_Data[[#This Row],[Rating]]=""),"Missing",IF(AND(Cleaned_Data[[#This Row],[Engagement]]="Strong Engagement",Cleaned_Data[[#This Row],[Rating Category]]="Excellent"),"Flag","OK")) -> OK | P11: =IF(Cleaned_Data[[#This Row],[Rating]]="","Missing Rating","Has Rating") -> Has Rating | Q11: =IFERROR( (Cleaned_Data[[#This Row],[Old Price]]-Cleaned_Data[[#This Row],[Current Price]])/Cleaned_Data[[#This Row],[Old Price]], "" ) -> 0.45373848 | R11: =IF( Cleaned_Data[[#This Row],[Discount]] - Cleaned_Data[[#This Row],[Calculated Discount]]>2%, "Check", "OK" ) -> OK | S11: =IF(OR(Cleaned_Data[[#This Row],[Rating]]<0,Cleaned_Data[[#This Row],[Rating]]>5),"Check rating","OK") -> OK | T11: =IF(OR(Cleaned_Data[[#This Row],[Discount]]<0,Cleaned_Data[[#This Row],[Discount]]>1),"Check discount","OK") -> OK | U11: =IF(Cleaned_Data[[#This Row],[Current Price]]>Cleaned_Data[[#This Row],[Old Price]],"Check prices","OK") -> OK
A12: Genebre 115 In 1 Screwdriver Repairing Tool Set For IPhone Cellphone Hand Tool | B12: 799 | C12: 999 | D12: 0.2 | E12: 12 | F12: 4.1 | G12: =Cleaned_Data[[#This Row],[Old Price]]-Cleaned_Data[[#This Row],[Current Price]] -> 200 | H12: =IF(Cleaned_Data[[#This Row],[Rating]]="","Missing",IF(Cleaned_Data[[#This Row],[Rating]]<3,"Poor",IF(Cleaned_Data[[#This Row],[Rating]]<=4.5,"Average","Excellent"))) -> Average | I12: =IF( Cleaned_Data[[#This Row],[Discount]]="", "Missing", IF( Cleaned_Data[[#This Row],[Discount]]<20%, "Low Discount", IF( Cleaned_Data[[#This Row],[Discount]]<=40%, "Medium Discount", "High Discount" ) ) ) -> Medium Discount | J12: =IF( Cleaned_Data[[#This Row],[Current Price]]="", "Missing", IF( Cleaned_Data[[#This Row],[Current Price]]<=Analysis!$B$3, "Low Price", IF( Cleaned_Data[[#This Row],[Current Price]]<=Analysis!$B$4, "Medium Price", "High Price" ) ) ) -> Medium Price | K12: =IF(Cleaned_Data[[#This Row],[Review]]="","Missing",IF(Cleaned_Data[[#This Row],[Review]]>=Engagement_Threshold,"Strong Engagement","Weak Engagement")) -> Weak Engagement | L12: =IF(OR(Cleaned_Data[[#This Row],[Discount]]="",Cleaned_Data[[#This Row],[Rating]]=""),"Missing",IF(AND(Cleaned_Data[[#This Row],[Discount Category]]="High Discount",Cleaned_Data[[#This Row],[Rating Category]]="Poor"),"Flag","OK")) -> OK | M12: =IF(OR(Cleaned_Data[[#This Row],[Discount]]="",Cleaned_Data[[#This Row],[Review]]=""),"Missing",IF(AND(Cleaned_Data[[#This Row],[Discount Category]]="High Discount",Cleaned_Data[[#This Row],[Engagement]]="Weak Engagement"),"Flag","OK")) -> OK | N12: =IF(OR(Cleaned_Data[[#This Row],[Review]]="",Cleaned_Data[[#This Row],[Rating]]=""),"Missing",IF(AND(Cleaned_Data[[#This Row],[Engagement]]="Strong Engagement",Cleaned_Data[[#This Row],[Rating Category]]="Average"),"Flag","OK")) -> OK | O12: =IF(OR(Cleaned_Data[[#This Row],[Review]]="",Cleaned_Data[[#This Row],[Rating]]=""),"Missing",IF(AND(Cleaned_Data[[#This Row],[Engagement]]="Strong Engagement",Cleaned_Data[[#This Row],[Rating Category]]="Excellent"),"Flag","OK")) -> OK | P12: =IF(Cleaned_Data[[#This Row],[Rating]]="","Missing Rating","Has Rating") -> Has Rating | Q12: =IFERROR( (Cleaned_Data[[#This Row],[Old Price]]-Cleaned_Data[[#This Row],[Current Price]])/Cleaned_Data[[#This Row],[Old Price]], "" ) -> 0.2002002 | R12: =IF( Cleaned_Data[[#This Row],[Discount]] - Cleaned_Data[[#This Row],[Calculated Discount]]>2%, "Check", "OK" ) -> OK | S12: =IF(OR(Cleaned_Data[[#This Row],[Rating]]<0,Cleaned_Data[[#This Row],[Rating]]>5),"Check rating","OK") -> OK | T12: =IF(OR(Cleaned_Data[[#This Row],[Discount]]<0,Cleaned_Data[[#This Row],[Discount]]>1),"Check discount","OK") -> OK | U12: =IF(Cleaned_Data[[#This Row],[Current Price]]>Cleaned_Data[[#This Row],[Old Price]],"Check prices","OK") -> OK
A13: 100 Pcs Crochet Hook Tool Set Knitting Hook Set With Box | B13: 990 | C13: 1500 | D13: 0.34 | E13: 39 | F13: 4.7 | G13: =Cleaned_Data[[#This Row],[Old Price]]-Cleaned_Data[[#This Row],[Current Price]] -> 510 | H13: =IF(Cleaned_Data[[#This Row],[Rating]]="","Missing",IF(Cleaned_Data[[#This Row],[Rating]]<3,"Poor",IF(Cleaned_Data[[#This Row],[Rating]]<=4.5,"Average","Excellent"))) -> Excellent | I13: =IF( Cleaned_Data[[#This Row],[Discount]]="", "Missing", IF( Cleaned_Data[[#This Row],[Discount]]<20%, "Low Discount", IF( Cleaned_Data[[#This Row],[Discount]]<=40%, "Medium Discount", "High Discount" ) ) ) -> Medium Discount | J13: =IF( Cleaned_Data[[#This Row],[Current Price]]="", "Missing", IF( Cleaned_Data[[#This Row],[Current Price]]<=Analysis!$B$3, "Low Price", IF( Cleaned_Data[[#This Row],[Current Price]]<=Analysis!$B$4, "Medium Price", "High Price" ) ) ) -> Medium Price | K13: =IF(Cleaned_Data[[#This Row],[Review]]="","Missing",IF(Cleaned_Data[[#This Row],[Review]]>=Engagement_Threshold,"Strong Engagement","Weak Engagement")) -> Strong Engagement | L13: =IF(OR(Cleaned_Data[[#This Row],[Discount]]="",Cleaned_Data[[#This Row],[Rating]]=""),"Missing",IF(AND(Cleaned_Data[[#This Row],[Discount Category]]="High Discount",Cleaned_Data[[#This Row],[Rating Category]]="Poor"),"Flag","OK")) -> OK | M13: =IF(OR(Cleaned_Data[[#This Row],[Discount]]="",Cleaned_Data[[#This Row],[Review]]=""),"Missing",IF(AND(Cleaned_Data[[#This Row],[Discount Category]]="High Discount",Cleaned_Data[[#This Row],[Engagement]]="Weak Engagement"),"Flag","OK")) -> OK | N13: =IF(OR(Cleaned_Data[[#This Row],[Review]]="",Cleaned_Data[[#This Row],[Rating]]=""),"Missing",IF(AND(Cleaned_Data[[#This Row],[Engagement]]="Strong Engagement",Cleaned_Data[[#This Row],[Rating Category]]="Average"),"Flag","OK")) -> OK | O13: =IF(OR(Cleaned_Data[[#This Row],[Review]]="",Cleaned_Data[[#This Row],[Rating]]=""),"Missing",IF(AND(Cleaned_Data[[#This Row],[Engagement]]="Strong Engagement",Cleaned_Data[[#This Row],[Rating Category]]="Excellent"),"Flag","OK")) -> Flag | P13: =IF(Cleaned_Data[[#This Row],[Rating]]="","Missing Rating","Has Rating") -> Has Rating | Q13: =IFERROR( (Cleaned_Data[[#This Row],[Old Price]]-Cleaned_Data[[#This Row],[Current Price]])/Cleaned_Data[[#This Row],[Old Price]], "" ) -> 0.34 | R13: =IF( Cleaned_Data[[#This Row],[Discount]] - Cleaned_Data[[#This Row],[Calculated Discount]]>2%, "Check", "OK" ) -> OK | S13: =IF(OR(Cleaned_Data[[#This Row],[Rating]]<0,Cleaned_Data[[#This Row],[Rating]]>5),"Check rating","OK") -> OK | T13: =IF(OR(Cleaned_Data[[#This Row],[Discount]]<0,Cleaned_Data[[#This Row],[Discount]]>1),"Check discount","OK") -> OK | U13: =IF(Cleaned_Data[[#This Row],[Current Price]]>Cleaned_Data[[#This Row],[Old Price]],"Check prices","OK") -> OK
... A22: 3PCS Single Head Knitting Crochet Sweater Needle Set | B22: 38 | C22: 80 | D22: 0.53 | E22: 13 | F22: 3.3 | G22: =Cleaned_Data[[#This Row],[Old Price]]-Cleaned_Data[[#This Row],[Current Price]] -> 42 | H22: =IF(Cleaned_Data[[#This Row],[Rating]]="","Missing",IF(Cleaned_Data[[#This Row],[Rating]]<3,"Poor",IF(Cleaned_Data[[#This Row],[Rating]]<=4.5,"Average","Excellent"))) -> Average | I22: =IF( Cleaned_Data[[#This Row],[Discount]]="", "Missing", IF( Cleaned_Data[[#This Row],[Discount]]<20%, "Low Discount", IF( Cleaned_Data[[#This Row],[Discount]]<=40%, "Medium Discount", "High Discount" ) ) ) -> High Discount | J22: =IF( Cleaned_Data[[#This Row],[Current Price]]="", "Missing", IF( Cleaned_Data[[#This Row],[Current Price]]<=Analysis!$B$3, "Low Price", IF( Cleaned_Data[[#This Row],[Current Price]]<=Analysis!$B$4, "Medium Price", "High Price" ) ) ) -> Low Price | K22: =IF(Cleaned_Data[[#This Row],[Review]]="","Missing",IF(Cleaned_Data[[#This Row],[Review]]>=Engagement_Threshold,"Strong Engagement","Weak Engagement")) -> Weak Engagement | L22: =IF(OR(Cleaned_Data[[#This Row],[Discount]]="",Cleaned_Data[[#This Row],[Rating]]=""),"Missing",IF(AND(Cleaned_Data[[#This Row],[Discount Category]]="High Discount",Cleaned_Data[[#This Row],[Rating Category]]="Poor"),"Flag","OK")) -> OK | M22: =IF(OR(Cleaned_Data[[#This Row],[Discount]]="",Cleaned_Data[[#This Row],[Review]]=""),"Missing",IF(AND(Cleaned_Data[[#This Row],[Discount Category]]="High Discount",Cleaned_Data[[#This Row],[Engagement]]="Weak Engagement"),"Flag","OK")) -> Flag | N22: =IF(OR(Cleaned_Data[[#This Row],[Review]]="",Cleaned_Data[[#This Row],[Rating]]=""),"Missing",IF(AND(Cleaned_Data[[#This Row],[Engagement]]="Strong Engagement",Cleaned_Data[[#This Row],[Rating Category]]="Average"),"Flag","OK")) -> OK | O22: =IF(OR(Cleaned_Data[[#This Row],[Review]]="",Cleaned_Data[[#This Row],[Rating]]=""),"Missing",IF(AND(Cleaned_Data[[#This Row],[Engagement]]="Strong Engagement",Cleaned_Data[[#This Row],[Rating Category]]="Excellent"),"Flag","OK")) -> OK | P22: =IF(Cleaned_Data[[#This Row],[Rating]]="","Missing Rating","Has Rating") -> Has Rating | Q22: =IFERROR( (Cleaned_Data[[#This Row],[Old Price]]-Cleaned_Data[[#This Row],[Current Price]])/Cleaned_Data[[#This Row],[Old Price]], "" ) -> 0.525 | R22: =IF( Cleaned_Data[[#This Row],[Discount]] - Cleaned_Data[[#This Row],[Calculated Discount]]>2%, "Check", "OK" ) -> OK | S22: =IF(OR(Cleaned_Data[[#This Row],[Rating]]<0,Cleaned_Data[[#This Row],[Rating]]>5),"Check rating","OK") -> OK | T22: =IF(OR(Cleaned_Data[[#This Row],[Discount]]<0,Cleaned_Data[[#This Row],[Discount]]>1),"Check discount","OK") -> OK | U22: =IF(Cleaned_Data[[#This Row],[Current Price]]>Cleaned_Data[[#This Row],[Old Price]],"Check prices","OK") -> OK
A23: 4pcs Bathroom/Kitchen Towel Rack,Roll Paper Holder,Towel Bars,Hook | B23: 1860 | C23: 3220 | D23: 0.42 | G23: =Cleaned_Data[[#This Row],[Old Price]]-Cleaned_Data[[#This Row],[Current Price]] -> 1360 | H23: =IF(Cleaned_Data[[#This Row],[Rating]]="","Missing",IF(Cleaned_Data[[#This Row],[Rating]]<3,"Poor",IF(Cleaned_Data[[#This Row],[Rating]]<=4.5,"Average","Excellent"))) -> Missing | I23: =IF( Cleaned_Data[[#This Row],[Discount]]="", "Missing", IF( Cleaned_Data[[#This Row],[Discount]]<20%, "Low Discount", IF( Cleaned_Data[[#This Row],[Discount]]<=40%, "Medium Discount", "High Discount" ) ) ) -> High Discount | J23: =IF( Cleaned_Data[[#This Row],[Current Price]]="", "Missing", IF( Cleaned_Data[[#This Row],[Current Price]]<=Analysis!$B$3, "Low Price", IF( Cleaned_Data[[#This Row],[Current Price]]<=Analysis!$B$4, "Medium Price", "High Price" ) ) ) -> High Price | K23: =IF(Cleaned_Data[[#This Row],[Review]]="","Missing",IF(Cleaned_Data[[#This Row],[Review]]>=Engagement_Threshold,"Strong Engagement","Weak Engagement")) -> Missing | L23: =IF(OR(Cleaned_Data[[#This Row],[Discount]]="",Cleaned_Data[[#This Row],[Rating]]=""),"Missing",IF(AND(Cleaned_Data[[#This Row],[Discount Category]]="High Discount",Cleaned_Data[[#This Row],[Rating Category]]="Poor"),"Flag","OK")) -> Missing | M23: =IF(OR(Cleaned_Data[[#This Row],[Discount]]="",Cleaned_Data[[#This Row],[Review]]=""),"Missing",IF(AND(Cleaned_Data[[#This Row],[Discount Category]]="High Discount",Cleaned_Data[[#This Row],[Engagement]]="Weak Engagement"),"Flag","OK")) -> Missing | N23: =IF(OR(Cleaned_Data[[#This Row],[Review]]="",Cleaned_Data[[#This Row],[Rating]]=""),"Missing",IF(AND(Cleaned_Data[[#This Row],[Engagement]]="Strong Engagement",Cleaned_Data[[#This Row],[Rating Category]]="Average"),"Flag","OK")) -> Missing | O23: =IF(OR(Cleaned_Data[[#This Row],[Review]]="",Cleaned_Data[[#This Row],[Rating]]=""),"Missing",IF(AND(Cleaned_Data[[#This Row],[Engagement]]="Strong Engagement",Cleaned_Data[[#This Row],[Rating Category]]="Excellent"),"Flag","OK")) -> Missing | P23: =IF(Cleaned_Data[[#This Row],[Rating]]="","Missing Rating","Has Rating") -> Missing Rating | Q23: =IFERROR( (Cleaned_Data[[#This Row],[Old Price]]-Cleaned_Data[[#This Row],[Current Price]])/Cleaned_Data[[#This Row],[Old Price]], "" ) -> 0.42236025 | R23: =IF( Cleaned_Data[[#This Row],[Discount]] - Cleaned_Data[[#This Row],[Calculated Discount]]>2%, "Check", "OK" ) -> OK | S23: =IF(OR(Cleaned_Data[[#This Row],[Rating]]<0,Cleaned_Data[[#This Row],[Rating]]>5),"Check rating","OK") -> OK | T23: =IF(OR(Cleaned_Data[[#This Row],[Discount]]<0,Cleaned_Data[[#This Row],[Discount]]>1),"Check discount","OK") -> OK | U23: =IF(Cleaned_Data[[#This Row],[Current Price]]>Cleaned_Data[[#This Row],[Old Price]],"Check prices","OK") -> OK
A24: LED Romantic Spaceship Starry Sky Projector,Children's Bedroom Night Light-Blue | B24: 880 | C24: 1350 | D24: 0.35 | E24: 6 | F24: 4 | G24: =Cleaned_Data[[#This Row],[Old Price]]-Cleaned_Data[[#This Row],[Current Price]] -> 470 | H24: =IF(Cleaned_Data[[#This Row],[Rating]]="","Missing",IF(Cleaned_Data[[#This Row],[Rating]]<3,"Poor",IF(Cleaned_Data[[#This Row],[Rating]]<=4.5,"Average","Excellent"))) -> Average | I24: =IF( Cleaned_Data[[#This Row],[Discount]]="", "Missing", IF( Cleaned_Data[[#This Row],[Discount]]<20%, "Low Discount", IF( Cleaned_Data[[#This Row],[Discount]]<=40%, "Medium Discount", "High Discount" ) ) ) -> Medium Discount | J24: =IF( Cleaned_Data[[#This Row],[Current Price]]="", "Missing", IF( Cleaned_Data[[#This Row],[Current Price]]<=Analysis!$B$3, "Low Price", IF( Cleaned_Data[[#This Row],[Current Price]]<=Analysis!$B$4, "Medium Price", "High Price" ) ) ) -> Medium Price | K24: =IF(Cleaned_Data[[#This Row],[Review]]="","Missing",IF(Cleaned_Data[[#This Row],[Review]]>=Engagement_Threshold,"Strong Engagement","Weak Engagement")) -> Weak Engagement | L24: =IF(OR(Cleaned_Data[[#This Row],[Discount]]="",Cleaned_Data[[#This Row],[Rating]]=""),"Missing",IF(AND(Cleaned_Data[[#This Row],[Discount Category]]="High Discount",Cleaned_Data[[#This Row],[Rating Category]]="Poor"),"Flag","OK")) -> OK | M24: =IF(OR(Cleaned_Data[[#This Row],[Discount]]="",Cleaned_Data[[#This Row],[Review]]=""),"Missing",IF(AND(Cleaned_Data[[#This Row],[Discount Category]]="High Discount",Cleaned_Data[[#This Row],[Engagement]]="Weak Engagement"),"Flag","OK")) -> OK | N24: =IF(OR(Cleaned_Data[[#This Row],[Review]]="",Cleaned_Data[[#This Row],[Rating]]=""),"Missing",IF(AND(Cleaned_Data[[#This Row],[Engagement]]="Strong Engagement",Cleaned_Data[[#This Row],[Rating Category]]="Average"),"Flag","OK")) -> OK | O24: =IF(OR(Cleaned_Data[[#This Row],[Review]]="",Cleaned_Data[[#This Row],[Rating]]=""),"Missing",IF(AND(Cleaned_Data[[#This Row],[Engagement]]="Strong Engagement",Cleaned_Data[[#This Row],[Rating Category]]="Excellent"),"Flag","OK")) -> OK | P24: =IF(Cleaned_Data[[#This Row],[Rating]]="","Missing Rating","Has Rating") -> Has Rating | Q24: =IFERROR( (Cleaned_Data[[#This Row],[Old Price]]-Cleaned_Data[[#This Row],[Current Price]])/Cleaned_Data[[#This Row],[Old Price]], "" ) -> 0.34814815 | R24: =IF( Cleaned_Data[[#This Row],[Discount]] - Cleaned_Data[[#This Row],[Calculated Discount]]>2%, "Check", "OK" ) -> OK | S24: =IF(OR(Cleaned_Data[[#This Row],[Rating]]<0,Cleaned_Data[[#This Row],[Rating]]>5),"Check rating","OK") -> OK | T24: =IF(OR(Cleaned_Data[[#This Row],[Discount]]<0,Cleaned_Data[[#This Row],[Discount]]>1),"Check discount","OK") -> OK | U24: =IF(Cleaned_Data[[#This Row],[Current Price]]>Cleaned_Data[[#This Row],[Old Price]],"Check prices","OK") -> OK
A25: Foldable Overbed Table/Desk | B25: 1650 | C25: 2150 | D25: 0.23 | E25: 14 | F25: 4.4 | G25: =Cleaned_Data[[#This Row],[Old Price]]-Cleaned_Data[[#This Row],[Current Price]] -> 500 | H25: =IF(Cleaned_Data[[#This Row],[Rating]]="","Missing",IF(Cleaned_Data[[#This Row],[Rating]]<3,"Poor",IF(Cleaned_Data[[#This Row],[Rating]]<=4.5,"Average","Excellent"))) -> Average | I25: =IF( Cleaned_Data[[#This Row],[Discount]]="", "Missing", IF( Cleaned_Data[[#This Row],[Discount]]<20%, "Low Discount", IF( Cleaned_Data[[#This Row],[Discount]]<=40%, "Medium Discount", "High Discount" ) ) ) -> Medium Discount | J25: =IF( Cleaned_Data[[#This Row],[Current Price]]="", "Missing", IF( Cleaned_Data[[#This Row],[Current Price]]<=Analysis!$B$3, "Low Price", IF( Cleaned_Data[[#This Row],[Current Price]]<=Analysis!$B$4, "Medium Price", "High Price" ) ) ) -> Medium Price | K25: =IF(Cleaned_Data[[#This Row],[Review]]="","Missing",IF(Cleaned_Data[[#This Row],[Review]]>=Engagement_Threshold,"Strong Engagement","Weak Engagement")) -> Strong Engagement | L25: =IF(OR(Cleaned_Data[[#This Row],[Discount]]="",Cleaned_Data[[#This Row],[Rating]]=""),"Missing",IF(AND(Cleaned_Data[[#This Row],[Discount Category]]="High Discount",Cleaned_Data[[#This Row],[Rating Category]]="Poor"),"Flag","OK")) -> OK | M25: =IF(OR(Cleaned_Data[[#This Row],[Discount]]="",Cleaned_Data[[#This Row],[Review]]=""),"Missing",IF(AND(Cleaned_Data[[#This Row],[Discount Category]]="High Discount",Cleaned_Data[[#This Row],[Engagement]]="Weak Engagement"),"Flag","OK")) -> OK | N25: =IF(OR(Cleaned_Data[[#This Row],[Review]]="",Cleaned_Data[[#This Row],[Rating]]=""),"Missing",IF(AND(Cleaned_Data[[#This Row],[Engagement]]="Strong Engagement",Cleaned_Data[[#This Row],[Rating Category]]="Average"),"Flag","OK")) -> Flag | O25: =IF(OR(Cleaned_Data[[#This Row],[Review]]="",Cleaned_Data[[#This Row],[Rating]]=""),"Missing",IF(AND(Cleaned_Data[[#This Row],[Engagement]]="Strong Engagement",Cleaned_Data[[#This Row],[Rating Category]]="Excellent"),"Flag","OK")) -> OK | P25: =IF(Cleaned_Data[[#This Row],[Rating]]="","Missing Rating","Has Rating") -> Has Rating | Q25: =IFERROR( (Cleaned_Data[[#This Row],[Old Price]]-Cleaned_Data[[#This Row],[Current Price]])/Cleaned_Data[[#This Row],[Old Price]], "" ) -> 0.23255814 | R25: =IF( Cleaned_Data[[#This Row],[Discount]] - Cleaned_Data[[#This Row],[Calculated Discount]]>2%, "Check", "OK" ) -> OK | S25: =IF(OR(Cleaned_Data[[#This Row],[Rating]]<0,Cleaned_Data[[#This Row],[Rating]]>5),"Check rating","OK") -> OK | T25: =IF(OR(Cleaned_Data[[#This Row],[Discount]]<0,Cleaned_Data[[#This Row],[Discount]]>1),"Check discount","OK") -> OK | U25: =IF(Cleaned_Data[[#This Row],[Current Price]]>Cleaned_Data[[#This Row],[Old Price]],"Check prices","OK") -> OK
A26: LASA 3 Tier Bamboo Shoe Bench Storage Shelf | B26: 2048 | C26: 4500 | D26: 0.54 | E26: 7 | F26: 4.3 | G26: =Cleaned_Data[[#This Row],[Old Price]]-Cleaned_Data[[#This Row],[Current Price]] -> 2452 | H26: =IF(Cleaned_Data[[#This Row],[Rating]]="","Missing",IF(Cleaned_Data[[#This Row],[Rating]]<3,"Poor",IF(Cleaned_Data[[#This Row],[Rating]]<=4.5,"Average","Excellent"))) -> Average | I26: =IF( Cleaned_Data[[#This Row],[Discount]]="", "Missing", IF( Cleaned_Data[[#This Row],[Discount]]<20%, "Low Discount", IF( Cleaned_Data[[#This Row],[Discount]]<=40%, "Medium Discount", "High Discount" ) ) ) -> High Discount | J26: =IF( Cleaned_Data[[#This Row],[Current Price]]="", "Missing", IF( Cleaned_Data[[#This Row],[Current Price]]<=Analysis!$B$3, "Low Price", IF( Cleaned_Data[[#This Row],[Current Price]]<=Analysis!$B$4, "Medium Price", "High Price" ) ) ) -> High Price | K26: =IF(Cleaned_Data[[#This Row],[Review]]="","Missing",IF(Cleaned_Data[[#This Row],[Review]]>=Engagement_Threshold,"Strong Engagement","Weak Engagement")) -> Weak Engagement | L26: =IF(OR(Cleaned_Data[[#This Row],[Discount]]="",Cleaned_Data[[#This Row],[Rating]]=""),"Missing",IF(AND(Cleaned_Data[[#This Row],[Discount Category]]="High Discount",Cleaned_Data[[#This Row],[Rating Category]]="Poor"),"Flag","OK")) -> OK | M26: =IF(OR(Cleaned_Data[[#This Row],[Discount]]="",Cleaned_Data[[#This Row],[Review]]=""),"Missing",IF(AND(Cleaned_Data[[#This Row],[Discount Category]]="High Discount",Cleaned_Data[[#This Row],[Engagement]]="Weak Engagement"),"Flag","OK")) -> Flag | N26: =IF(OR(Cleaned_Data[[#This Row],[Review]]="",Cleaned_Data[[#This Row],[Rating]]=""),"Missing",IF(AND(Cleaned_Data[[#This Row],[Engagement]]="Strong Engagement",Cleaned_Data[[#This Row],[Rating Category]]="Average"),"Flag","OK")) -> OK | O26: =IF(OR(Cleaned_Data[[#This Row],[Review]]="",Cleaned_Data[[#This Row],[Rating]]=""),"Missing",IF(AND(Cleaned_Data[[#This Row],[Engagement]]="Strong Engagement",Cleaned_Data[[#This Row],[Rating Category]]="Excellent"),"Flag","OK")) -> OK | P26: =IF(Cleaned_Data[[#This Row],[Rating]]="","Missing Rating","Has Rating") -> Has Rating | Q26: =IFERROR( (Cleaned_Data[[#This Row],[Old Price]]-Cleaned_Data[[#This Row],[Current Price]])/Cleaned_Data[[#This Row],[Old Price]], "" ) -> 0.54488889 | R26: =IF( Cleaned_Data[[#This Row],[Discount]] - Cleaned_Data[[#This Row],[Calculated Discount]]>2%, "Check", "OK" ) -> OK | S26: =IF(OR(Cleaned_Data[[#This Row],[Rating]]<0,Cleaned_Data[[#This Row],[Rating]]>5),"Check rating","OK") -> OK | T26: =IF(OR(Cleaned_Data[[#This Row],[Discount]]<0,Cleaned_Data[[#This Row],[Discount]]>1),"Check discount","OK") -> OK | U26: =IF(Cleaned_Data[[#This Row],[Current Price]]>Cleaned_Data[[#This Row],[Old Price]],"Check prices","OK") -> OK
A27: Electronic Digital Display Vernier Caliper | B27: 420 | C27: 647 | D27: 0.35 | E27: 49 | F27: 4.6 | G27: =Cleaned_Data[[#This Row],[Old Price]]-Cleaned_Data[[#This Row],[Current Price]] -> 227 | H27: =IF(Cleaned_Data[[#This Row],[Rating]]="","Missing",IF(Cleaned_Data[[#This Row],[Rating]]<3,"Poor",IF(Cleaned_Data[[#This Row],[Rating]]<=4.5,"Average","Excellent"))) -> Excellent | I27: =IF( Cleaned_Data[[#This Row],[Discount]]="", "Missing", IF( Cleaned_Data[[#This Row],[Discount]]<20%, "Low Discount", IF( Cleaned_Data[[#This Row],[Discount]]<=40%, "Medium Discount", "High Discount" ) ) ) -> Medium Discount | J27: =IF( Cleaned_Data[[#This Row],[Current Price]]="", "Missing", IF( Cleaned_Data[[#This Row],[Current Price]]<=Analysis!$B$3, "Low Price", IF( Cleaned_Data[[#This Row],[Current Price]]<=Analysis!$B$4, "Medium Price", "High Price" ) ) ) -> Low Price | K27: =IF(Cleaned_Data[[#This Row],[Review]]="","Missing",IF(Cleaned_Data[[#This Row],[Review]]>=Engagement_Threshold,"Strong Engagement","Weak Engagement")) -> Strong Engagement | L27: =IF(OR(Cleaned_Data[[#This Row],[Discount]]="",Cleaned_Data[[#This Row],[Rating]]=""),"Missing",IF(AND(Cleaned_Data[[#This Row],[Discount Category]]="High Discount",Cleaned_Data[[#This Row],[Rating Category]]="Poor"),"Flag","OK")) -> OK | M27: =IF(OR(Cleaned_Data[[#This Row],[Discount]]="",Cleaned_Data[[#This Row],[Review]]=""),"Missing",IF(AND(Cleaned_Data[[#This Row],[Discount Category]]="High Discount",Cleaned_Data[[#This Row],[Engagement]]="Weak Engagement"),"Flag","OK")) -> OK | N27: =IF(OR(Cleaned_Data[[#This Row],[Review]]="",Cleaned_Data[[#This Row],[Rating]]=""),"Missing",IF(AND(Cleaned_Data[[#This Row],[Engagement]]="Strong Engagement",Cleaned_Data[[#This Row],[Rating Category]]="Average"),"Flag","OK")) -> OK | O27: =IF(OR(Cleaned_Data[[#This Row],[Review]]="",Cleaned_Data[[#This Row],[Rating]]=""),"Missing",IF(AND(Cleaned_Data[[#This Row],[Engagement]]="Strong Engagement",Cleaned_Data[[#This Row],[Rating Category]]="Excellent"),"Flag","OK")) -> Flag | P27: =IF(Cleaned_Data[[#This Row],[Rating]]="","Missing Rating","Has Rating") -> Has Rating | Q27: =IFERROR( (Cleaned_Data[[#This Row],[Old Price]]-Cleaned_Data[[#This Row],[Current Price]])/Cleaned_Data[[#This Row],[Old Price]], "" ) -> 0.35085008 | R27: =IF( Cleaned_Data[[#This Row],[Discount]] - Cleaned_Data[[#This Row],[Calculated Discount]]>2%, "Check", "OK" ) -> OK | S27: =IF(OR(Cleaned_Data[[#This Row],[Rating]]<0,Cleaned_Data[[#This Row],[Rating]]>5),"Check rating","OK") -> OK | T27: =IF(OR(Cleaned_Data[[#This Row],[Discount]]<0,Cleaned_Data[[#This Row],[Discount]]>1),"Check discount","OK") -> OK | U27: =IF(Cleaned_Data[[#This Row],[Current Price]]>Cleaned_Data[[#This Row],[Old Price]],"Check prices","OK") -> OK
A28: Portable Wardrobe Nonwoven With 3 Hanging Rods And 6 Storage Shelves | B28: 2880 | C28: 3520 | D28: 0.18 | E28: 12 | F28: 3.8 | G28: =Cleaned_Data[[#This Row],[Old Price]]-Cleaned_Data[[#This Row],[Current Price]] -> 640 | H28: =IF(Cleaned_Data[[#This Row],[Rating]]="","Missing",IF(Cleaned_Data[[#This Row],[Rating]]<3,"Poor",IF(Cleaned_Data[[#This Row],[Rating]]<=4.5,"Average","Excellent"))) -> Average | I28: =IF( Cleaned_Data[[#This Row],[Discount]]="", "Missing", IF( Cleaned_Data[[#This Row],[Discount]]<20%, "Low Discount", IF( Cleaned_Data[[#This Row],[Discount]]<=40%, "Medium Discount", "High Discount" ) ) ) -> Low Discount | J28: =IF( Cleaned_Data[[#This Row],[Current Price]]="", "Missing", IF( Cleaned_Data[[#This Row],[Current Price]]<=Analysis!$B$3, "Low Price", IF( Cleaned_Data[[#This Row],[Current Price]]<=Analysis!$B$4, "Medium Price", "High Price" ) ) ) -> High Price | K28: =IF(Cleaned_Data[[#This Row],[Review]]="","Missing",IF(Cleaned_Data[[#This Row],[Review]]>=Engagement_Threshold,"Strong Engagement","Weak Engagement")) -> Weak Engagement | L28: =IF(OR(Cleaned_Data[[#This Row],[Discount]]="",Cleaned_Data[[#This Row],[Rating]]=""),"Missing",IF(AND(Cleaned_Data[[#This Row],[Discount Category]]="High Discount",Cleaned_Data[[#This Row],[Rating Category]]="Poor"),"Flag","OK")) -> OK | M28: =IF(OR(Cleaned_Data[[#This Row],[Discount]]="",Cleaned_Data[[#This Row],[Review]]=""),"Missing",IF(AND(Cleaned_Data[[#This Row],[Discount Category]]="High Discount",Cleaned_Data[[#This Row],[Engagement]]="Weak Engagement"),"Flag","OK")) -> OK | N28: =IF(OR(Cleaned_Data[[#This Row],[Review]]="",Cleaned_Data[[#This Row],[Rating]]=""),"Missing",IF(AND(Cleaned_Data[[#This Row],[Engagement]]="Strong Engagement",Cleaned_Data[[#This Row],[Rating Category]]="Average"),"Flag","OK")) -> OK | O28: =IF(OR(Cleaned_Data[[#This Row],[Review]]="",Cleaned_Data[[#This Row],[Rating]]=""),"Missing",IF(AND(Cleaned_Data[[#This Row],[Engagement]]="Strong Engagement",Cleaned_Data[[#This Row],[Rating Category]]="Excellent"),"Flag","OK")) -> OK | P28: =IF(Cleaned_Data[[#This Row],[Rating]]="","Missing Rating","Has Rating") -> Has Rating | Q28: =IFERROR( (Cleaned_Data[[#This Row],[Old Price]]-Cleaned_Data[[#This Row],[Current Price]])/Cleaned_Data[[#This Row],[Old Price]], "" ) -> 0.18181818 | R28: =IF( Cleaned_Data[[#This Row],[Discount]] - Cleaned_Data[[#This Row],[Calculated Discount]]>2%, "Check", "OK" ) -> OK | S28: =IF(OR(Cleaned_Data[[#This Row],[Rating]]<0,Cleaned_Data[[#This Row],[Rating]]>5),"Check rating","OK") -> OK | T28: =IF(OR(Cleaned_Data[[#This Row],[Discount]]<0,Cleaned_Data[[#This Row],[Discount]]>1),"Check discount","OK") -> OK | U28: =IF(Cleaned_Data[[#This Row],[Current Price]]>Cleaned_Data[[#This Row],[Old Price]],"Check prices","OK") -> OK
A29: 12 Litre Black Insulated Lunch Box | B29: 1350 | C29: 1990 | D29: 0.32 | E29: 13 | F29: 3.8 | G29: =Cleaned_Data[[#This Row],[Old Price]]-Cleaned_Data[[#This Row],[Current Price]] -> 640 | H29: =IF(Cleaned_Data[[#This Row],[Rating]]="","Missing",IF(Cleaned_Data[[#This Row],[Rating]]<3,"Poor",IF(Cleaned_Data[[#This Row],[Rating]]<=4.5,"Average","Excellent"))) -> Average | I29: =IF( Cleaned_Data[[#This Row],[Discount]]="", "Missing", IF( Cleaned_Data[[#This Row],[Discount]]<20%, "Low Discount", IF( Cleaned_Data[[#This Row],[Discount]]<=40%, "Medium Discount", "High Discount" ) ) ) -> Medium Discount | J29: =IF( Cleaned_Data[[#This Row],[Current Price]]="", "Missing", IF( Cleaned_Data[[#This Row],[Current Price]]<=Analysis!$B$3, "Low Price", IF( Cleaned_Data[[#This Row],[Current Price]]<=Analysis!$B$4, "Medium Price", "High Price" ) ) ) -> Medium Price | K29: =IF(Cleaned_Data[[#This Row],[Review]]="","Missing",IF(Cleaned_Data[[#This Row],[Review]]>=Engagement_Threshold,"Strong Engagement","Weak Engagement")) -> Weak Engagement | L29: =IF(OR(Cleaned_Data[[#This Row],[Discount]]="",Cleaned_Data[[#This Row],[Rating]]=""),"Missing",IF(AND(Cleaned_Data[[#This Row],[Discount Category]]="High Discount",Cleaned_Data[[#This Row],[Rating Category]]="Poor"),"Flag","OK")) -> OK | M29: =IF(OR(Cleaned_Data[[#This Row],[Discount]]="",Cleaned_Data[[#This Row],[Review]]=""),"Missing",IF(AND(Cleaned_Data[[#This Row],[Discount Category]]="High Discount",Cleaned_Data[[#This Row],[Engagement]]="Weak Engagement"),"Flag","OK")) -> OK | N29: =IF(OR(Cleaned_Data[[#This Row],[Review]]="",Cleaned_Data[[#This Row],[Rating]]=""),"Missing",IF(AND(Cleaned_Data[[#This Row],[Engagement]]="Strong Engagement",Cleaned_Data[[#This Row],[Rating Category]]="Average"),"Flag","OK")) -> OK | O29: =IF(OR(Cleaned_Data[[#This Row],[Review]]="",Cleaned_Data[[#This Row],[Rating]]=""),"Missing",IF(AND(Cleaned_Data[[#This Row],[Engagement]]="Strong Engagement",Cleaned_Data[[#This Row],[Rating Category]]="Excellent"),"Flag","OK")) -> OK | P29: =IF(Cleaned_Data[[#This Row],[Rating]]="","Missing Rating","Has Rating") -> Has Rating | Q29: =IFERROR( (Cleaned_Data[[#This Row],[Old Price]]-Cleaned_Data[[#This Row],[Current Price]])/Cleaned_Data[[#This Row],[Old Price]], "" ) -> 0.32160804 | R29: =IF( Cleaned_Data[[#This Row],[Discount]] - Cleaned_Data[[#This Row],[Calculated Discount]]>2%, "Check", "OK" ) -> OK | S29: =IF(OR(Cleaned_Data[[#This Row],[Rating]]<0,Cleaned_Data[[#This Row],[Rating]]>5),"Check rating","OK") -> OK | T29: =IF(OR(Cleaned_Data[[#This Row],[Discount]]<0,Cleaned_Data[[#This Row],[Discount]]>1),"Check discount","OK") -> OK | U29: =IF(Cleaned_Data[[#This Row],[Current Price]]>Cleaned_Data[[#This Row],[Old Price]],"Check prices","OK") -> OK
A30: 52 Pieces Cake Decorating Tool Set Gift Kit Baking Supplies | B30: 1758 | C30: 2499 | D30: 0.3 | E30: 20 | F30: 4.1 | G30: =Cleaned_Data[[#This Row],[Old Price]]-Cleaned_Data[[#This Row],[Current Price]] -> 741 | H30: =IF(Cleaned_Data[[#This Row],[Rating]]="","Missing",IF(Cleaned_Data[[#This Row],[Rating]]<3,"Poor",IF(Cleaned_Data[[#This Row],[Rating]]<=4.5,"Average","Excellent"))) -> Average | I30: =IF( Cleaned_Data[[#This Row],[Discount]]="", "Missing", IF( Cleaned_Data[[#This Row],[Discount]]<20%, "Low Discount", IF( Cleaned_Data[[#This Row],[Discount]]<=40%, "Medium Discount", "High Discount" ) ) ) -> Medium Discount | J30: =IF( Cleaned_Data[[#This Row],[Current Price]]="", "Missing", IF( Cleaned_Data[[#This Row],[Current Price]]<=Analysis!$B$3, "Low Price", IF( Cleaned_Data[[#This Row],[Current Price]]<=Analysis!$B$4, "Medium Price", "High Price" ) ) ) -> High Price | K30: =IF(Cleaned_Data[[#This Row],[Review]]="","Missing",IF(Cleaned_Data[[#This Row],[Review]]>=Engagement_Threshold,"Strong Engagement","Weak Engagement")) -> Strong Engagement | L30: =IF(OR(Cleaned_Data[[#This Row],[Discount]]="",Cleaned_Data[[#This Row],[Rating]]=""),"Missing",IF(AND(Cleaned_Data[[#This Row],[Discount Category]]="High Discount",Cleaned_Data[[#This Row],[Rating Category]]="Poor"),"Flag","OK")) -> OK | M30: =IF(OR(Cleaned_Data[[#This Row],[Discount]]="",Cleaned_Data[[#This Row],[Review]]=""),"Missing",IF(AND(Cleaned_Data[[#This Row],[Discount Category]]="High Discount",Cleaned_Data[[#This Row],[Engagement]]="Weak Engagement"),"Flag","OK")) -> OK | N30: =IF(OR(Cleaned_Data[[#This Row],[Review]]="",Cleaned_Data[[#This Row],[Rating]]=""),"Missing",IF(AND(Cleaned_Data[[#This Row],[Engagement]]="Strong Engagement",Cleaned_Data[[#This Row],[Rating Category]]="Average"),"Flag","OK")) -> Flag | O30: =IF(OR(Cleaned_Data[[#This Row],[Review]]="",Cleaned_Data[[#This Row],[Rating]]=""),"Missing",IF(AND(Cleaned_Data[[#This Row],[Engagement]]="Strong Engagement",Cleaned_Data[[#This Row],[Rating Category]]="Excellent"),"Flag","OK")) -> OK | P30: =IF(Cleaned_Data[[#This Row],[Rating]]="","Missing Rating","Has Rating") -> Has Rating | Q30: =IFERROR( (Cleaned_Data[[#This Row],[Old Price]]-Cleaned_Data[[#This Row],[Current Price]])/Cleaned_Data[[#This Row],[Old Price]], "" ) -> 0.29651861 | R30: =IF( Cleaned_Data[[#This Row],[Discount]] - Cleaned_Data[[#This Row],[Calculated Discount]]>2%, "Check", "OK" ) -> OK | S30: =IF(OR(Cleaned_Data[[#This Row],[Rating]]<0,Cleaned_Data[[#This Row],[Rating]]>5),"Check rating","OK") -> OK | T30: =IF(OR(Cleaned_Data[[#This Row],[Discount]]<0,Cleaned_Data[[#This Row],[Discount]]>1),"Check discount","OK") -> OK | U30: =IF(Cleaned_Data[[#This Row],[Current Price]]>Cleaned_Data[[#This Row],[Old Price]],"Check prices","OK") -> OK
A31: MultiFunctional Storage Rack Multi-layer Bookshelf | B31: 2200 | C31: 4080 | D31: 0.46 | G31: =Cleaned_Data[[#This Row],[Old Price]]-Cleaned_Data[[#This Row],[Current Price]] -> 1880 | H31: =IF(Cleaned_Data[[#This Row],[Rating]]="","Missing",IF(Cleaned_Data[[#This Row],[Rating]]<3,"Poor",IF(Cleaned_Data[[#This Row],[Rating]]<=4.5,"Average","Excellent"))) -> Missing | I31: =IF( Cleaned_Data[[#This Row],[Discount]]="", "Missing", IF( Cleaned_Data[[#This Row],[Discount]]<20%, "Low Discount", IF( Cleaned_Data[[#This Row],[Discount]]<=40%, "Medium Discount", "High Discount" ) ) ) -> High Discount | J31: =IF( Cleaned_Data[[#This Row],[Current Price]]="", "Missing", IF( Cleaned_Data[[#This Row],[Current Price]]<=Analysis!$B$3, "Low Price", IF( Cleaned_Data[[#This Row],[Current Price]]<=Analysis!$B$4, "Medium Price", "High Price" ) ) ) -> High Price | K31: =IF(Cleaned_Data[[#This Row],[Review]]="","Missing",IF(Cleaned_Data[[#This Row],[Review]]>=Engagement_Threshold,"Strong Engagement","Weak Engagement")) -> Missing | L31: =IF(OR(Cleaned_Data[[#This Row],[Discount]]="",Cleaned_Data[[#This Row],[Rating]]=""),"Missing",IF(AND(Cleaned_Data[[#This Row],[Discount Category]]="High Discount",Cleaned_Data[[#This Row],[Rating Category]]="Poor"),"Flag","OK")) -> Missing | M31: =IF(OR(Cleaned_Data[[#This Row],[Discount]]="",Cleaned_Data[[#This Row],[Review]]=""),"Missing",IF(AND(Cleaned_Data[[#This Row],[Discount Category]]="High Discount",Cleaned_Data[[#This Row],[Engagement]]="Weak Engagement"),"Flag","OK")) -> Missing | N31: =IF(OR(Cleaned_Data[[#This Row],[Review]]="",Cleaned_Data[[#This Row],[Rating]]=""),"Missing",IF(AND(Cleaned_Data[[#This Row],[Engagement]]="Strong Engagement",Cleaned_Data[[#This Row],[Rating Category]]="Average"),"Flag","OK")) -> Missing | O31: =IF(OR(Cleaned_Data[[#This Row],[Review]]="",Cleaned_Data[[#This Row],[Rating]]=""),"Missing",IF(AND(Cleaned_Data[[#This Row],[Engagement]]="Strong Engagement",Cleaned_Data[[#This Row],[Rating Category]]="Excellent"),"Flag","OK")) -> Missing | P31: =IF(Cleaned_Data[[#This Row],[Rating]]="","Missing Rating","Has Rating") -> Missing Rating | Q31: =IFERROR( (Cleaned_Data[[#This Row],[Old Price]]-Cleaned_Data[[#This Row],[Current Price]])/Cleaned_Data[[#This Row],[Old Price]], "" ) -> 0.46078431 | R31: =IF( Cleaned_Data[[#This Row],[Discount]] - Cleaned_Data[[#This Row],[Calculated Discount]]>2%, "Check", "OK" ) -> OK | S31: =IF(OR(Cleaned_Data[[#This Row],[Rating]]<0,Cleaned_Data[[#This Row],[Rating]]>5),"Check rating","OK") -> OK | T31: =IF(OR(Cleaned_Data[[#This Row],[Discount]]<0,Cleaned_Data[[#This Row],[Discount]]>1),"Check discount","OK") -> OK | U31: =IF(Cleaned_Data[[#This Row],[Current Price]]>Cleaned_Data[[#This Row],[Old Price]],"Check prices","OK") -> OK
A32: Exfoliate And Exfoliate Face Towel - Black | B32: 185 | C32: 382 | D32: 0.52 | E32: 9 | F32: 4.3 | G32: =Cleaned_Data[[#This Row],[Old Price]]-Cleaned_Data[[#This Row],[Current Price]] -> 197 | H32: =IF(Cleaned_Data[[#This Row],[Rating]]="","Missing",IF(Cleaned_Data[[#This Row],[Rating]]<3,"Poor",IF(Cleaned_Data[[#This Row],[Rating]]<=4.5,"Average","Excellent"))) -> Average | I32: =IF( Cleaned_Data[[#This Row],[Discount]]="", "Missing", IF( Cleaned_Data[[#This Row],[Discount]]<20%, "Low Discount", IF( Cleaned_Data[[#This Row],[Discount]]<=40%, "Medium Discount", "High Discount" ) ) ) -> High Discount | J32: =IF( Cleaned_Data[[#This Row],[Current Price]]="", "Missing", IF( Cleaned_Data[[#This Row],[Current Price]]<=Analysis!$B$3, "Low Price", IF( Cleaned_Data[[#This Row],[Current Price]]<=Analysis!$B$4, "Medium Price", "High Price" ) ) ) -> Low Price | K32: =IF(Cleaned_Data[[#This Row],[Review]]="","Missing",IF(Cleaned_Data[[#This Row],[Review]]>=Engagement_Threshold,"Strong Engagement","Weak Engagement")) -> Weak Engagement | L32: =IF(OR(Cleaned_Data[[#This Row],[Discount]]="",Cleaned_Data[[#This Row],[Rating]]=""),"Missing",IF(AND(Cleaned_Data[[#This Row],[Discount Category]]="High Discount",Cleaned_Data[[#This Row],[Rating Category]]="Poor"),"Flag","OK")) -> OK | M32: =IF(OR(Cleaned_Data[[#This Row],[Discount]]="",Cleaned_Data[[#This Row],[Review]]=""),"Missing",IF(AND(Cleaned_Data[[#This Row],[Discount Category]]="High Discount",Cleaned_Data[[#This Row],[Engagement]]="Weak Engagement"),"Flag","OK")) -> Flag | N32: =IF(OR(Cleaned_Data[[#This Row],[Review]]="",Cleaned_Data[[#This Row],[Rating]]=""),"Missing",IF(AND(Cleaned_Data[[#This Row],[Engagement]]="Strong Engagement",Cleaned_Data[[#This Row],[Rating Category]]="Average"),"Flag","OK")) -> OK | O32: =IF(OR(Cleaned_Data[[#This Row],[Review]]="",Cleaned_Data[[#This Row],[Rating]]=""),"Missing",IF(AND(Cleaned_Data[[#This Row],[Engagement]]="Strong Engagement",Cleaned_Data[[#This Row],[Rating Category]]="Excellent"),"Flag","OK")) -> OK | P32: =IF(Cleaned_Data[[#This Row],[Rating]]="","Missing Rating","Has Rating") -> Has Rating | Q32: =IFERROR( (Cleaned_Data[[#This Row],[Old Price]]-Cleaned_Data[[#This Row],[Current Price]])/Cleaned_Data[[#This Row],[Old Price]], "" ) -> 0.51570681 | R32: =IF( Cleaned_Data[[#This Row],[Discount]] - Cleaned_Data[[#This Row],[Calculated Discount]]>2%, "Check", "OK" ) -> OK | S32: =IF(OR(Cleaned_Data[[#This Row],[Rating]]<0,Cleaned_Data[[#This Row],[Rating]]>5),"Check rating","OK") -> OK | T32: =IF(OR(Cleaned_Data[[#This Row],[Discount]]<0,Cleaned_Data[[#This Row],[Discount]]>1),"Check discount","OK") -> OK | U32: =IF(Cleaned_Data[[#This Row],[Current Price]]>Cleaned_Data[[#This Row],[Old Price]],"Check prices","OK") -> OK
A33: 12 Litre Insulated Lunch Box Grey | B33: 980 | C33: 1490 | D33: 0.34 | E33: 12 | F33: 4.7 | G33: =Cleaned_Data[[#This Row],[Old Price]]-Cleaned_Data[[#This Row],[Current Price]] -> 510 | H33: =IF(Cleaned_Data[[#This Row],[Rating]]="","Missing",IF(Cleaned_Data[[#This Row],[Rating]]<3,"Poor",IF(Cleaned_Data[[#This Row],[Rating]]<=4.5,"Average","Excellent"))) -> Excellent | I33: =IF( Cleaned_Data[[#This Row],[Discount]]="", "Missing", IF( Cleaned_Data[[#This Row],[Discount]]<20%, "Low Discount", IF( Cleaned_Data[[#This Row],[Discount]]<=40%, "Medium Discount", "High Discount" ) ) ) -> Medium Discount | J33: =IF( Cleaned_Data[[#This Row],[Current Price]]="", "Missing", IF( Cleaned_Data[[#This Row],[Current Price]]<=Analysis!$B$3, "Low Price", IF( Cleaned_Data[[#This Row],[Current Price]]<=Analysis!$B$4, "Medium Price", "High Price" ) ) ) -> Medium Price | K33: =IF(Cleaned_Data[[#This Row],[Review]]="","Missing",IF(Cleaned_Data[[#This Row],[Review]]>=Engagement_Threshold,"Strong Engagement","Weak Engagement")) -> Weak Engagement | L33: =IF(OR(Cleaned_Data[[#This Row],[Discount]]="",Cleaned_Data[[#This Row],[Rating]]=""),"Missing",IF(AND(Cleaned_Data[[#This Row],[Discount Category]]="High Discount",Cleaned_Data[[#This Row],[Rating Category]]="Poor"),"Flag","OK")) -> OK | M33: =IF(OR(Cleaned_Data[[#This Row],[Discount]]="",Cleaned_Data[[#This Row],[Review]]=""),"Missing",IF(AND(Cleaned_Data[[#This Row],[Discount Category]]="High Discount",Cleaned_Data[[#This Row],[Engagement]]="Weak Engagement"),"Flag","OK")) -> OK | N33: =IF(OR(Cleaned_Data[[#This Row],[Review]]="",Cleaned_Data[[#This Row],[Rating]]=""),"Missing",IF(AND(Cleaned_Data[[#This Row],[Engagement]]="Strong Engagement",Cleaned_Data[[#This Row],[Rating Category]]="Average"),"Flag","OK")) -> OK | O33: =IF(OR(Cleaned_Data[[#This Row],[Review]]="",Cleaned_Data[[#This Row],[Rating]]=""),"Missing",IF(AND(Cleaned_Data[[#This Row],[Engagement]]="Strong Engagement",Cleaned_Data[[#This Row],[Rating Category]]="Excellent"),"Flag","OK")) -> OK | P33: =IF(Cleaned_Data[[#This Row],[Rating]]="","Missing Rating","Has Rating") -> Has Rating | Q33: =IFERROR( (Cleaned_Data[[#This Row],[Old Price]]-Cleaned_Data[[#This Row],[Current Price]])/Cleaned_Data[[#This Row],[Old Price]], "" ) -> 0.34228188 | R33: =IF( Cleaned_Data[[#This Row],[Discount]] - Cleaned_Data[[#This Row],[Calculated Discount]]>2%, "Check", "OK" ) -> OK | S33: =IF(OR(Cleaned_Data[[#This Row],[Rating]]<0,Cleaned_Data[[#This Row],[Rating]]>5),"Check rating","OK") -> OK | T33: =IF(OR(Cleaned_Data[[#This Row],[Discount]]<0,Cleaned_Data[[#This Row],[Discount]]>1),"Check discount","OK") -> OK | U33: =IF(Cleaned_Data[[#This Row],[Current Price]]>Cleaned_Data[[#This Row],[Old Price]],"Check prices","OK") -> OK
A34: LED Eye Protection Desk Lamp , Study, Reading, USB Fan - Double Pen Holder | B34: 1820 | C34: 3490 | D34: 0.48 | E34: 9 | F34: 4.3 | G34: =Cleaned_Data[[#This Row],[Old Price]]-Cleaned_Data[[#This Row],[Current Price]] -> 1670 | H34: =IF(Cleaned_Data[[#This Row],[Rating]]="","Missing",IF(Cleaned_Data[[#This Row],[Rating]]<3,"Poor",IF(Cleaned_Data[[#This Row],[Rating]]<=4.5,"Average","Excellent"))) -> Average | I34: =IF( Cleaned_Data[[#This Row],[Discount]]="", "Missing", IF( Cleaned_Data[[#This Row],[Discount]]<20%, "Low Discount", IF( Cleaned_Data[[#This Row],[Discount]]<=40%, "Medium Discount", "High Discount" ) ) ) -> High Discount | J34: =IF( Cleaned_Data[[#This Row],[Current Price]]="", "Missing", IF( Cleaned_Data[[#This Row],[Current Price]]<=Analysis!$B$3, "Low Price", IF( Cleaned_Data[[#This Row],[Current Price]]<=Analysis!$B$4, "Medium Price", "High Price" ) ) ) -> High Price | K34: =IF(Cleaned_Data[[#This Row],[Review]]="","Missing",IF(Cleaned_Data[[#This Row],[Review]]>=Engagement_Threshold,"Strong Engagement","Weak Engagement")) -> Weak Engagement | L34: =IF(OR(Cleaned_Data[[#This Row],[Discount]]="",Cleaned_Data[[#This Row],[Rating]]=""),"Missing",IF(AND(Cleaned_Data[[#This Row],[Discount Category]]="High Discount",Cleaned_Data[[#This Row],[Rating Category]]="Poor"),"Flag","OK")) -> OK | M34: =IF(OR(Cleaned_Data[[#This Row],[Discount]]="",Cleaned_Data[[#This Row],[Review]]=""),"Missing",IF(AND(Cleaned_Data[[#This Row],[Discount Category]]="High Discount",Cleaned_Data[[#This Row],[Engagement]]="Weak Engagement"),"Flag","OK")) -> Flag | N34: =IF(OR(Cleaned_Data[[#This Row],[Review]]="",Cleaned_Data[[#This Row],[Rating]]=""),"Missing",IF(AND(Cleaned_Data[[#This Row],[Engagement]]="Strong Engagement",Cleaned_Data[[#This Row],[Rating Category]]="Average"),"Flag","OK")) -> OK | O34: =IF(OR(Cleaned_Data[[#This Row],[Review]]="",Cleaned_Data[[#This Row],[Rating]]=""),"Missing",IF(AND(Cleaned_Data[[#This Row],[Engagement]]="Strong Engagement",Cleaned_Data[[#This Row],[Rating Category]]="Excellent"),"Flag","OK")) -> OK | P34: =IF(Cleaned_Data[[#This Row],[Rating]]="","Missing Rating","Has Rating") -> Has Rating | Q34: =IFERROR( (Cleaned_Data[[#This Row],[Old Price]]-Cleaned_Data[[#This Row],[Current Price]])/Cleaned_Data[[#This Row],[Old Price]], "" ) -> 0.47851003 | R34: =IF( Cleaned_Data[[#This Row],[Discount]] - Cleaned_Data[[#This Row],[Calculated Discount]]>2%, "Check", "OK" ) -> OK | S34: =IF(OR(Cleaned_Data[[#This Row],[Rating]]<0,Cleaned_Data[[#This Row],[Rating]]>5),"Check rating","OK") -> OK | T34: =IF(OR(Cleaned_Data[[#This Row],[Discount]]<0,Cleaned_Data[[#This Row],[Discount]]>1),"Check discount","OK") -> OK | U34: =IF(Cleaned_Data[[#This Row],[Current Price]]>Cleaned_Data[[#This Row],[Old Price]],"Check prices","OK") -> OK
A35: 53Pcs/Set Yarn Knitting Crochet Hooks With Bag - Fortune Cat | B35: 1940 | C35: 2650 | D35: 0.27 | E35: 20 | F35: 4.7 | G35: =Cleaned_Data[[#This Row],[Old Price]]-Cleaned_Data[[#This Row],[Current Price]] -> 710 | H35: =IF(Cleaned_Data[[#This Row],[Rating]]="","Missing",IF(Cleaned_Data[[#This Row],[Rating]]<3,"Poor",IF(Cleaned_Data[[#This Row],[Rating]]<=4.5,"Average","Excellent"))) -> Excellent | I35: =IF( Cleaned_Data[[#This Row],[Discount]]="", "Missing", IF( Cleaned_Data[[#This Row],[Discount]]<20%, "Low Discount", IF( Cleaned_Data[[#This Row],[Discount]]<=40%, "Medium Discount", "High Discount" ) ) ) -> Medium Discount | J35: =IF( Cleaned_Data[[#This Row],[Current Price]]="", "Missing", IF( Cleaned_Data[[#This Row],[Current Price]]<=Analysis!$B$3, "Low Price", IF( Cleaned_Data[[#This Row],[Current Price]]<=Analysis!$B$4, "Medium Price", "High Price" ) ) ) -> High Price | K35: =IF(Cleaned_Data[[#This Row],[Review]]="","Missing",IF(Cleaned_Data[[#This Row],[Review]]>=Engagement_Threshold,"Strong Engagement","Weak Engagement")) -> Strong Engagement | L35: =IF(OR(Cleaned_Data[[#This Row],[Discount]]="",Cleaned_Data[[#This Row],[Rating]]=""),"Missing",IF(AND(Cleaned_Data[[#This Row],[Discount Category]]="High Discount",Cleaned_Data[[#This Row],[Rating Category]]="Poor"),"Flag","OK")) -> OK | M35: =IF(OR(Cleaned_Data[[#This Row],[Discount]]="",Cleaned_Data[[#This Row],[Review]]=""),"Missing",IF(AND(Cleaned_Data[[#This Row],[Discount Category]]="High Discount",Cleaned_Data[[#This Row],[Engagement]]="Weak Engagement"),"Flag","OK")) -> OK | N35: =IF(OR(Cleaned_Data[[#This Row],[Review]]="",Cleaned_Data[[#This Row],[Rating]]=""),"Missing",IF(AND(Cleaned_Data[[#This Row],[Engagement]]="Strong Engagement",Cleaned_Data[[#This Row],[Rating Category]]="Average"),"Flag","OK")) -> OK | O35: =IF(OR(Cleaned_Data[[#This Row],[Review]]="",Cleaned_Data[[#This Row],[Rating]]=""),"Missing",IF(AND(Cleaned_Data[[#This Row],[Engagement]]="Strong Engagement",Cleaned_Data[[#This Row],[Rating Category]]="Excellent"),"Flag","OK")) -> Flag | P35: =IF(Cleaned_Data[[#This Row],[Rating]]="","Missing Rating","Has Rating") -> Has Rating | Q35: =IFERROR( (Cleaned_Data[[#This Row],[Old Price]]-Cleaned_Data[[#This Row],[Current Price]])/Cleaned_Data[[#This Row],[Old Price]], "" ) -> 0.26792453 | R35: =IF( Cleaned_Data[[#This Row],[Discount]] - Cleaned_Data[[#This Row],[Calculated Discount]]>2%, "Check", "OK" ) -> OK | S35: =IF(OR(Cleaned_Data[[#This Row],[Rating]]<0,Cleaned_Data[[#This Row],[Rating]]>5),"Check rating","OK") -> OK | T35: =IF(OR(Cleaned_Data[[#This Row],[Discount]]<0,Cleaned_Data[[#This Row],[Discount]]>1),"Check discount","OK") -> OK | U35: =IF(Cleaned_Data[[#This Row],[Current Price]]>Cleaned_Data[[#This Row],[Old Price]],"Check prices","OK") -> OK
A36: 53 Pieces/Set Yarn Knitting Crochet Hooks With Bag - Pansies | B36: 1980 | C36: 2699 | D36: 0.27 | E36: 32 | F36: 4.5 | G36: =Cleaned_Data[[#This Row],[Old Price]]-Cleaned_Data[[#This Row],[Current Price]] -> 719 | H36: =IF(Cleaned_Data[[#This Row],[Rating]]="","Missing",IF(Cleaned_Data[[#This Row],[Rating]]<3,"Poor",IF(Cleaned_Data[[#This Row],[Rating]]<=4.5,"Average","Excellent"))) -> Average | I36: =IF( Cleaned_Data[[#This Row],[Discount]]="", "Missing", IF( Cleaned_Data[[#This Row],[Discount]]<20%, "Low Discount", IF( Cleaned_Data[[#This Row],[Discount]]<=40%, "Medium Discount", "High Discount" ) ) ) -> Medium Discount | J36: =IF( Cleaned_Data[[#This Row],[Current Price]]="", "Missing", IF( Cleaned_Data[[#This Row],[Current Price]]<=Analysis!$B$3, "Low Price", IF( Cleaned_Data[[#This Row],[Current Price]]<=Analysis!$B$4, "Medium Price", "High Price" ) ) ) -> High Price | K36: =IF(Cleaned_Data[[#This Row],[Review]]="","Missing",IF(Cleaned_Data[[#This Row],[Review]]>=Engagement_Threshold,"Strong Engagement","Weak Engagement")) -> Strong Engagement | L36: =IF(OR(Cleaned_Data[[#This Row],[Discount]]="",Cleaned_Data[[#This Row],[Rating]]=""),"Missing",IF(AND(Cleaned_Data[[#This Row],[Discount Category]]="High Discount",Cleaned_Data[[#This Row],[Rating Category]]="Poor"),"Flag","OK")) -> OK | M36: =IF(OR(Cleaned_Data[[#This Row],[Discount]]="",Cleaned_Data[[#This Row],[Review]]=""),"Missing",IF(AND(Cleaned_Data[[#This Row],[Discount Category]]="High Discount",Cleaned_Data[[#This Row],[Engagement]]="Weak Engagement"),"Flag","OK")) -> OK | N36: =IF(OR(Cleaned_Data[[#This Row],[Review]]="",Cleaned_Data[[#This Row],[Rating]]=""),"Missing",IF(AND(Cleaned_Data[[#This Row],[Engagement]]="Strong Engagement",Cleaned_Data[[#This Row],[Rating Category]]="Average"),"Flag","OK")) -> Flag | O36: =IF(OR(Cleaned_Data[[#This Row],[Review]]="",Cleaned_Data[[#This Row],[Rating]]=""),"Missing",IF(AND(Cleaned_Data[[#This Row],[Engagement]]="Strong Engagement",Cleaned_Data[[#This Row],[Rating Category]]="Excellent"),"Flag","OK")) -> OK | P36: =IF(Cleaned_Data[[#This Row],[Rating]]="","Missing Rating","Has Rating") -> Has Rating | Q36: =IFERROR( (Cleaned_Data[[#This Row],[Old Price]]-Cleaned_Data[[#This Row],[Current Price]])/Cleaned_Data[[#This Row],[Old Price]], "" ) -> 0.26639496 | R36: =IF( Cleaned_Data[[#This Row],[Discount]] - Cleaned_Data[[#This Row],[Calculated Discount]]>2%, "Check", "OK" ) -> OK | S36: =IF(OR(Cleaned_Data[[#This Row],[Rating]]<0,Cleaned_Data[[#This Row],[Rating]]>5),"Check rating","OK") -> OK | T36: =IF(OR(Cleaned_Data[[#This Row],[Discount]]<0,Cleaned_Data[[#This Row],[Discount]]>1),"Check discount","OK") -> OK | U36: =IF(Cleaned_Data[[#This Row],[Current Price]]>Cleaned_Data[[#This Row],[Old Price]],"Check prices","OK") -> OK
A37: DIY File Folder, Office Drawer File Holder, Pen Holder, Desktop Storage Rack | B37: 1620 | C37: 2690 | D37: 0.4 | E37: 1 | F37: 5 | G37: =Cleaned_Data[[#This Row],[Old Price]]-Cleaned_Data[[#This Row],[Current Price]] -> 1070 | H37: =IF(Cleaned_Data[[#This Row],[Rating]]="","Missing",IF(Cleaned_Data[[#This Row],[Rating]]<3,"Poor",IF(Cleaned_Data[[#This Row],[Rating]]<=4.5,"Average","Excellent"))) -> Excellent | I37: =IF( Cleaned_Data[[#This Row],[Discount]]="", "Missing", IF( Cleaned_Data[[#This Row],[Discount]]<20%, "Low Discount", IF( Cleaned_Data[[#This Row],[Discount]]<=40%, "Medium Discount", "High Discount" ) ) ) -> Medium Discount | J37: =IF( Cleaned_Data[[#This Row],[Current Price]]="", "Missing", IF( Cleaned_Data[[#This Row],[Current Price]]<=Analysis!$B$3, "Low Price", IF( Cleaned_Data[[#This Row],[Current Price]]<=Analysis!$B$4, "Medium Price", "High Price" ) ) ) -> Medium Price | K37: =IF(Cleaned_Data[[#This Row],[Review]]="","Missing",IF(Cleaned_Data[[#This Row],[Review]]>=Engagement_Threshold,"Strong Engagement","Weak Engagement")) -> Weak Engagement | L37: =IF(OR(Cleaned_Data[[#This Row],[Discount]]="",Cleaned_Data[[#This Row],[Rating]]=""),"Missing",IF(AND(Cleaned_Data[[#This Row],[Discount Category]]="High Discount",Cleaned_Data[[#This Row],[Rating Category]]="Poor"),"Flag","OK")) -> OK | M37: =IF(OR(Cleaned_Data[[#This Row],[Discount]]="",Cleaned_Data[[#This Row],[Review]]=""),"Missing",IF(AND(Cleaned_Data[[#This Row],[Discount Category]]="High Discount",Cleaned_Data[[#This Row],[Engagement]]="Weak Engagement"),"Flag","OK")) -> OK | N37: =IF(OR(Cleaned_Data[[#This Row],[Review]]="",Cleaned_Data[[#This Row],[Rating]]=""),"Missing",IF(AND(Cleaned_Data[[#This Row],[Engagement]]="Strong Engagement",Cleaned_Data[[#This Row],[Rating Category]]="Average"),"Flag","OK")) -> OK | O37: =IF(OR(Cleaned_Data[[#This Row],[Review]]="",Cleaned_Data[[#This Row],[Rating]]=""),"Missing",IF(AND(Cleaned_Data[[#This Row],[Engagement]]="Strong Engagement",Cleaned_Data[[#This Row],[Rating Category]]="Excellent"),"Flag","OK")) -> OK | P37: =IF(Cleaned_Data[[#This Row],[Rating]]="","Missing Rating","Has Rating") -> Has Rating | Q37: =IFERROR( (Cleaned_Data[[#This Row],[Old Price]]-Cleaned_Data[[#This Row],[Current Price]])/Cleaned_Data[[#This Row],[Old Price]], "" ) -> 0.39776952 | R37: =IF( Cleaned_Data[[#This Row],[Discount]] - Cleaned_Data[[#This Row],[Calculated Discount]]>2%, "Check", "OK" ) -> OK | S37: =IF(OR(Cleaned_Data[[#This Row],[Rating]]<0,Cleaned_Data[[#This Row],[Rating]]>5),"Check rating","OK") -> OK | T37: =IF(OR(Cleaned_Data[[#This Row],[Discount]]<0,Cleaned_Data[[#This Row],[Discount]]>1),"Check discount","OK") -> OK | U37: =IF(Cleaned_Data[[#This Row],[Current Price]]>Cleaned_Data[[#This Row],[Old Price]],"Check prices","OK") -> OK
A38: Classic Black Cat Cotton Hemp Pillow Case For Home Car | B38: 171 | C38: 360 | D38: 0.53 | E38: 2 | F38: 5 | G38: =Cleaned_Data[[#This Row],[Old Price]]-Cleaned_Data[[#This Row],[Current Price]] -> 189 | H38: =IF(Cleaned_Data[[#This Row],[Rating]]="","Missing",IF(Cleaned_Data[[#This Row],[Rating]]<3,"Poor",IF(Cleaned_Data[[#This Row],[Rating]]<=4.5,"Average","Excellent"))) -> Excellent | I38: =IF( Cleaned_Data[[#This Row],[Discount]]="", "Missing", IF( Cleaned_Data[[#This Row],[Discount]]<20%, "Low Discount", IF( Cleaned_Data[[#This Row],[Discount]]<=40%, "Medium Discount", "High Discount" ) ) ) -> High Discount | J38: =IF( Cleaned_Data[[#This Row],[Current Price]]="", "Missing", IF( Cleaned_Data[[#This Row],[Current Price]]<=Analysis!$B$3, "Low Price", IF( Cleaned_Data[[#This Row],[Current Price]]<=Analysis!$B$4, "Medium Price", "High Price" ) ) ) -> Low Price | K38: =IF(Cleaned_Data[[#This Row],[Review]]="","Missing",IF(Cleaned_Data[[#This Row],[Review]]>=Engagement_Threshold,"Strong Engagement","Weak Engagement")) -> Weak Engagement | L38: =IF(OR(Cleaned_Data[[#This Row],[Discount]]="",Cleaned_Data[[#This Row],[Rating]]=""),"Missing",IF(AND(Cleaned_Data[[#This Row],[Discount Category]]="High Discount",Cleaned_Data[[#This Row],[Rating Category]]="Poor"),"Flag","OK")) -> OK | M38: =IF(OR(Cleaned_Data[[#This Row],[Discount]]="",Cleaned_Data[[#This Row],[Review]]=""),"Missing",IF(AND(Cleaned_Data[[#This Row],[Discount Category]]="High Discount",Cleaned_Data[[#This Row],[Engagement]]="Weak Engagement"),"Flag","OK")) -> Flag | N38: =IF(OR(Cleaned_Data[[#This Row],[Review]]="",Cleaned_Data[[#This Row],[Rating]]=""),"Missing",IF(AND(Cleaned_Data[[#This Row],[Engagement]]="Strong Engagement",Cleaned_Data[[#This Row],[Rating Category]]="Average"),"Flag","OK")) -> OK | O38: =IF(OR(Cleaned_Data[[#This Row],[Review]]="",Cleaned_Data[[#This Row],[Rating]]=""),"Missing",IF(AND(Cleaned_Data[[#This Row],[Engagement]]="Strong Engagement",Cleaned_Data[[#This Row],[Rating Category]]="Excellent"),"Flag","OK")) -> OK | P38: =IF(Cleaned_Data[[#This Row],[Rating]]="","Missing Rating","Has Rating") -> Has Rating | Q38: =IFERROR( (Cleaned_Data[[#This Row],[Old Price]]-Cleaned_Data[[#This Row],[Current Price]])/Cleaned_Data[[#This Row],[Old Price]], "" ) -> 0.525 | R38: =IF( Cleaned_Data[[#This Row],[Discount]] - Cleaned_Data[[#This Row],[Calculated Discount]]>2%, "Check", "OK" ) -> OK | S38: =IF(OR(Cleaned_Data[[#This Row],[Rating]]<0,Cleaned_Data[[#This Row],[Rating]]>5),"Check rating","OK") -> OK | T38: =IF(OR(Cleaned_Data[[#This Row],[Discount]]<0,Cleaned_Data[[#This Row],[Discount]]>1),"Check discount","OK") -> OK | U38: =IF(Cleaned_Data[[#This Row],[Current Price]]>Cleaned_Data[[#This Row],[Old Price]],"Check prices","OK") -> OK
A39: Punch-free Great Load Bearing Bathroom Storage Rack Wall Shelf-White | B39: 389 | C39: 656 | D39: 0.41 | E39: 36 | F39: 4.3 | G39: =Cleaned_Data[[#This Row],[Old Price]]-Cleaned_Data[[#This Row],[Current Price]] -> 267 | H39: =IF(Cleaned_Data[[#This Row],[Rating]]="","Missing",IF(Cleaned_Data[[#This Row],[Rating]]<3,"Poor",IF(Cleaned_Data[[#This Row],[Rating]]<=4.5,"Average","Excellent"))) -> Average | I39: =IF( Cleaned_Data[[#This Row],[Discount]]="", "Missing", IF( Cleaned_Data[[#This Row],[Discount]]<20%, "Low Discount", IF( Cleaned_Data[[#This Row],[Discount]]<=40%, "Medium Discount", "High Discount" ) ) ) -> High Discount | J39: =IF( Cleaned_Data[[#This Row],[Current Price]]="", "Missing", IF( Cleaned_Data[[#This Row],[Current Price]]<=Analysis!$B$3, "Low Price", IF( Cleaned_Data[[#This Row],[Current Price]]<=Analysis!$B$4, "Medium Price", "High Price" ) ) ) -> Low Price | K39: =IF(Cleaned_Data[[#This Row],[Review]]="","Missing",IF(Cleaned_Data[[#This Row],[Review]]>=Engagement_Threshold,"Strong Engagement","Weak Engagement")) -> Strong Engagement | L39: =IF(OR(Cleaned_Data[[#This Row],[Discount]]="",Cleaned_Data[[#This Row],[Rating]]=""),"Missing",IF(AND(Cleaned_Data[[#This Row],[Discount Category]]="High Discount",Cleaned_Data[[#This Row],[Rating Category]]="Poor"),"Flag","OK")) -> OK | M39: =IF(OR(Cleaned_Data[[#This Row],[Discount]]="",Cleaned_Data[[#This Row],[Review]]=""),"Missing",IF(AND(Cleaned_Data[[#This Row],[Discount Category]]="High Discount",Cleaned_Data[[#This Row],[Engagement]]="Weak Engagement"),"Flag","OK")) -> OK | N39: =IF(OR(Cleaned_Data[[#This Row],[Review]]="",Cleaned_Data[[#This Row],[Rating]]=""),"Missing",IF(AND(Cleaned_Data[[#This Row],[Engagement]]="Strong Engagement",Cleaned_Data[[#This Row],[Rating Category]]="Average"),"Flag","OK")) -> Flag | O39: =IF(OR(Cleaned_Data[[#This Row],[Review]]="",Cleaned_Data[[#This Row],[Rating]]=""),"Missing",IF(AND(Cleaned_Data[[#This Row],[Engagement]]="Strong Engagement",Cleaned_Data[[#This Row],[Rating Category]]="Excellent"),"Flag","OK")) -> OK | P39: =IF(Cleaned_Data[[#This Row],[Rating]]="","Missing Rating","Has Rating") -> Has Rating | Q39: =IFERROR( (Cleaned_Data[[#This Row],[Old Price]]-Cleaned_Data[[#This Row],[Current Price]])/Cleaned_Data[[#This Row],[Old Price]], "" ) -> 0.4070122 | R39: =IF( Cleaned_Data[[#This Row],[Discount]] - Cleaned_Data[[#This Row],[Calculated Discount]]>2%, "Check", "OK" ) -> OK | S39: =IF(OR(Cleaned_Data[[#This Row],[Rating]]<0,Cleaned_Data[[#This Row],[Rating]]>5),"Check rating","OK") -> OK | T39: =IF(OR(Cleaned_Data[[#This Row],[Discount]]<0,Cleaned_Data[[#This Row],[Discount]]>1),"Check discount","OK") -> OK | U39: =IF(Cleaned_Data[[#This Row],[Current Price]]>Cleaned_Data[[#This Row],[Old Price]],"Check prices","OK") -> OK
A40: 1/2/3 Seater Elastic Sofa Cover,Living Room/Home Decor Chair Cover-Grey | B40: 1800 | C40: 2700 | D40: 0.38 | E40: 2 | F40: 4.5 | G40: =Cleaned_Data[[#This Row],[Old Price]]-Cleaned_Data[[#This Row],[Current Price]] -> 900 | H40: =IF(Cleaned_Data[[#This Row],[Rating]]="","Missing",IF(Cleaned_Data[[#This Row],[Rating]]<3,"Poor",IF(Cleaned_Data[[#This Row],[Rating]]<=4.5,"Average","Excellent"))) -> Average | I40: =IF( Cleaned_Data[[#This Row],[Discount]]="", "Missing", IF( Cleaned_Data[[#This Row],[Discount]]<20%, "Low Discount", IF( Cleaned_Data[[#This Row],[Discount]]<=40%, "Medium Discount", "High Discount" ) ) ) -> Medium Discount | J40: =IF( Cleaned_Data[[#This Row],[Current Price]]="", "Missing", IF( Cleaned_Data[[#This Row],[Current Price]]<=Analysis!$B$3, "Low Price", IF( Cleaned_Data[[#This Row],[Current Price]]<=Analysis!$B$4, "Medium Price", "High Price" ) ) ) -> High Price | K40: =IF(Cleaned_Data[[#This Row],[Review]]="","Missing",IF(Cleaned_Data[[#This Row],[Review]]>=Engagement_Threshold,"Strong Engagement","Weak Engagement")) -> Weak Engagement | L40: =IF(OR(Cleaned_Data[[#This Row],[Discount]]="",Cleaned_Data[[#This Row],[Rating]]=""),"Missing",IF(AND(Cleaned_Data[[#This Row],[Discount Category]]="High Discount",Cleaned_Data[[#This Row],[Rating Category]]="Poor"),"Flag","OK")) -> OK | M40: =IF(OR(Cleaned_Data[[#This Row],[Discount]]="",Cleaned_Data[[#This Row],[Review]]=""),"Missing",IF(AND(Cleaned_Data[[#This Row],[Discount Category]]="High Discount",Cleaned_Data[[#This Row],[Engagement]]="Weak Engagement"),"Flag","OK")) -> OK | N40: =IF(OR(Cleaned_Data[[#This Row],[Review]]="",Cleaned_Data[[#This Row],[Rating]]=""),"Missing",IF(AND(Cleaned_Data[[#This Row],[Engagement]]="Strong Engagement",Cleaned_Data[[#This Row],[Rating Category]]="Average"),"Flag","OK")) -> OK | O40: =IF(OR(Cleaned_Data[[#This Row],[Review]]="",Cleaned_Data[[#This Row],[Rating]]=""),"Missing",IF(AND(Cleaned_Data[[#This Row],[Engagement]]="Strong Engagement",Cleaned_Data[[#This Row],[Rating Category]]="Excellent"),"Flag","OK")) -> OK | P40: =IF(Cleaned_Data[[#This Row],[Rating]]="","Missing Rating","Has Rating") -> Has Rating | Q40: =IFERROR( (Cleaned_Data[[#This Row],[Old Price]]-Cleaned_Data[[#This Row],[Current Price]])/Cleaned_Data[[#This Row],[Old Price]], "" ) -> 0.33333333 | R40: =IF( Cleaned_Data[[#This Row],[Discount]] - Cleaned_Data[[#This Row],[Calculated Discount]]>2%, "Check", "OK" ) -> Check | S40: =IF(OR(Cleaned_Data[[#This Row],[Rating]]<0,Cleaned_Data[[#This Row],[Rating]]>5),"Check rating","OK") -> OK | T40: =IF(OR(Cleaned_Data[[#This Row],[Discount]]<0,Cleaned_Data[[#This Row],[Discount]]>1),"Check discount","OK") -> OK | U40: =IF(Cleaned_Data[[#This Row],[Current Price]]>Cleaned_Data[[#This Row],[Old Price]],"Check prices","OK") -> OK
A41: LASA Stainless Steel Double Wall Mount Soap Dispenser - 500ml | B41: 2750 | C41: 4471 | D41: 0.38 | G41: =Cleaned_Data[[#This Row],[Old Price]]-Cleaned_Data[[#This Row],[Current Price]] -> 1721 | H41: =IF(Cleaned_Data[[#This Row],[Rating]]="","Missing",IF(Cleaned_Data[[#This Row],[Rating]]<3,"Poor",IF(Cleaned_Data[[#This Row],[Rating]]<=4.5,"Average","Excellent"))) -> Missing | I41: =IF( Cleaned_Data[[#This Row],[Discount]]="", "Missing", IF( Cleaned_Data[[#This Row],[Discount]]<20%, "Low Discount", IF( Cleaned_Data[[#This Row],[Discount]]<=40%, "Medium Discount", "High Discount" ) ) ) -> Medium Discount | J41: =IF( Cleaned_Data[[#This Row],[Current Price]]="", "Missing", IF( Cleaned_Data[[#This Row],[Current Price]]<=Analysis!$B$3, "Low Price", IF( Cleaned_Data[[#This Row],[Current Price]]<=Analysis!$B$4, "Medium Price", "High Price" ) ) ) -> High Price | K41: =IF(Cleaned_Data[[#This Row],[Review]]="","Missing",IF(Cleaned_Data[[#This Row],[Review]]>=Engagement_Threshold,"Strong Engagement","Weak Engagement")) -> Missing | L41: =IF(OR(Cleaned_Data[[#This Row],[Discount]]="",Cleaned_Data[[#This Row],[Rating]]=""),"Missing",IF(AND(Cleaned_Data[[#This Row],[Discount Category]]="High Discount",Cleaned_Data[[#This Row],[Rating Category]]="Poor"),"Flag","OK")) -> Missing | M41: =IF(OR(Cleaned_Data[[#This Row],[Discount]]="",Cleaned_Data[[#This Row],[Review]]=""),"Missing",IF(AND(Cleaned_Data[[#This Row],[Discount Category]]="High Discount",Cleaned_Data[[#This Row],[Engagement]]="Weak Engagement"),"Flag","OK")) -> Missing | N41: =IF(OR(Cleaned_Data[[#This Row],[Review]]="",Cleaned_Data[[#This Row],[Rating]]=""),"Missing",IF(AND(Cleaned_Data[[#This Row],[Engagement]]="Strong Engagement",Cleaned_Data[[#This Row],[Rating Category]]="Average"),"Flag","OK")) -> Missing | O41: =IF(OR(Cleaned_Data[[#This Row],[Review]]="",Cleaned_Data[[#This Row],[Rating]]=""),"Missing",IF(AND(Cleaned_Data[[#This Row],[Engagement]]="Strong Engagement",Cleaned_Data[[#This Row],[Rating Category]]="Excellent"),"Flag","OK")) -> Missing | P41: =IF(Cleaned_Data[[#This Row],[Rating]]="","Missing Rating","Has Rating") -> Missing Rating | Q41: =IFERROR( (Cleaned_Data[[#This Row],[Old Price]]-Cleaned_Data[[#This Row],[Current Price]])/Cleaned_Data[[#This Row],[Old Price]], "" ) -> 0.38492507 | R41: =IF( Cleaned_Data[[#This Row],[Discount]] - Cleaned_Data[[#This Row],[Calculated Discount]]>2%, "Check", "OK" ) -> OK | S41: =IF(OR(Cleaned_Data[[#This Row],[Rating]]<0,Cleaned_Data[[#This Row],[Rating]]>5),"Check rating","OK") -> OK | T41: =IF(OR(Cleaned_Data[[#This Row],[Discount]]<0,Cleaned_Data[[#This Row],[Discount]]>1),"Check discount","OK") -> OK | U41: =IF(Cleaned_Data[[#This Row],[Current Price]]>Cleaned_Data[[#This Row],[Old Price]],"Check prices","OK") -> OK
A42: 4M Float Switch Water Level Controller -Water Tank | B42: 475 | C42: 931 | D42: 0.49 | G42: =Cleaned_Data[[#This Row],[Old Price]]-Cleaned_Data[[#This Row],[Current Price]] -> 456 | H42: =IF(Cleaned_Data[[#This Row],[Rating]]="","Missing",IF(Cleaned_Data[[#This Row],[Rating]]<3,"Poor",IF(Cleaned_Data[[#This Row],[Rating]]<=4.5,"Average","Excellent"))) -> Missing | I42: =IF( Cleaned_Data[[#This Row],[Discount]]="", "Missing", IF( Cleaned_Data[[#This Row],[Discount]]<20%, "Low Discount", IF( Cleaned_Data[[#This Row],[Discount]]<=40%, "Medium Discount", "High Discount" ) ) ) -> High Discount | J42: =IF( Cleaned_Data[[#This Row],[Current Price]]="", "Missing", IF( Cleaned_Data[[#This Row],[Current Price]]<=Analysis!$B$3, "Low Price", IF( Cleaned_Data[[#This Row],[Current Price]]<=Analysis!$B$4, "Medium Price", "High Price" ) ) ) -> Low Price | K42: =IF(Cleaned_Data[[#This Row],[Review]]="","Missing",IF(Cleaned_Data[[#This Row],[Review]]>=Engagement_Threshold,"Strong Engagement","Weak Engagement")) -> Missing | L42: =IF(OR(Cleaned_Data[[#This Row],[Discount]]="",Cleaned_Data[[#This Row],[Rating]]=""),"Missing",IF(AND(Cleaned_Data[[#This Row],[Discount Category]]="High Discount",Cleaned_Data[[#This Row],[Rating Category]]="Poor"),"Flag","OK")) -> Missing | M42: =IF(OR(Cleaned_Data[[#This Row],[Discount]]="",Cleaned_Data[[#This Row],[Review]]=""),"Missing",IF(AND(Cleaned_Data[[#This Row],[Discount Category]]="High Discount",Cleaned_Data[[#This Row],[Engagement]]="Weak Engagement"),"Flag","OK")) -> Missing | N42: =IF(OR(Cleaned_Data[[#This Row],[Review]]="",Cleaned_Data[[#This Row],[Rating]]=""),"Missing",IF(AND(Cleaned_Data[[#This Row],[Engagement]]="Strong Engagement",Cleaned_Data[[#This Row],[Rating Category]]="Average"),"Flag","OK")) -> Missing | O42: =IF(OR(Cleaned_Data[[#This Row],[Review]]="",Cleaned_Data[[#This Row],[Rating]]=""),"Missing",IF(AND(Cleaned_Data[[#This Row],[Engagement]]="Strong Engagement",Cleaned_Data[[#This Row],[Rating Category]]="Excellent"),"Flag","OK")) -> Missing | P42: =IF(Cleaned_Data[[#This Row],[Rating]]="","Missing Rating","Has Rating") -> Missing Rating | Q42: =IFERROR( (Cleaned_Data[[#This Row],[Old Price]]-Cleaned_Data[[#This Row],[Current Price]])/Cleaned_Data[[#This Row],[Old Price]], "" ) -> 0.48979592 | R42: =IF( Cleaned_Data[[#This Row],[Discount]] - Cleaned_Data[[#This Row],[Calculated Discount]]>2%, "Check", "OK" ) -> OK | S42: =IF(OR(Cleaned_Data[[#This Row],[Rating]]<0,Cleaned_Data[[#This Row],[Rating]]>5),"Check rating","OK") -> OK | T42: =IF(OR(Cleaned_Data[[#This Row],[Discount]]<0,Cleaned_Data[[#This Row],[Discount]]>1),"Check discount","OK") -> OK | U42: =IF(Cleaned_Data[[#This Row],[Current Price]]>Cleaned_Data[[#This Row],[Old Price]],"Check prices","OK") -> OK
A43: Modern Sofa Throw Pillow Cover-45x45cm-Blue&Red | B43: 238 | C43: 476 | D43: 0.5 | G43: =Cleaned_Data[[#This Row],[Old Price]]-Cleaned_Data[[#This Row],[Current Price]] -> 238 | H43: =IF(Cleaned_Data[[#This Row],[Rating]]="","Missing",IF(Cleaned_Data[[#This Row],[Rating]]<3,"Poor",IF(Cleaned_Data[[#This Row],[Rating]]<=4.5,"Average","Excellent"))) -> Missing | I43: =IF( Cleaned_Data[[#This Row],[Discount]]="", "Missing", IF( Cleaned_Data[[#This Row],[Discount]]<20%, "Low Discount", IF( Cleaned_Data[[#This Row],[Discount]]<=40%, "Medium Discount", "High Discount" ) ) ) -> High Discount | J43: =IF( Cleaned_Data[[#This Row],[Current Price]]="", "Missing", IF( Cleaned_Data[[#This Row],[Current Price]]<=Analysis!$B$3, "Low Price", IF( Cleaned_Data[[#This Row],[Current Price]]<=Analysis!$B$4, "Medium Price", "High Price" ) ) ) -> Low Price | K43: =IF(Cleaned_Data[[#This Row],[Review]]="","Missing",IF(Cleaned_Data[[#This Row],[Review]]>=Engagement_Threshold,"Strong Engagement","Weak Engagement")) -> Missing | L43: =IF(OR(Cleaned_Data[[#This Row],[Discount]]="",Cleaned_Data[[#This Row],[Rating]]=""),"Missing",IF(AND(Cleaned_Data[[#This Row],[Discount Category]]="High Discount",Cleaned_Data[[#This Row],[Rating Category]]="Poor"),"Flag","OK")) -> Missing | M43: =IF(OR(Cleaned_Data[[#This Row],[Discount]]="",Cleaned_Data[[#This Row],[Review]]=""),"Missing",IF(AND(Cleaned_Data[[#This Row],[Discount Category]]="High Discount",Cleaned_Data[[#This Row],[Engagement]]="Weak Engagement"),"Flag","OK")) -> Missing | N43: =IF(OR(Cleaned_Data[[#This Row],[Review]]="",Cleaned_Data[[#This Row],[Rating]]=""),"Missing",IF(AND(Cleaned_Data[[#This Row],[Engagement]]="Strong Engagement",Cleaned_Data[[#This Row],[Rating Category]]="Average"),"Flag","OK")) -> Missing | O43: =IF(OR(Cleaned_Data[[#This Row],[Review]]="",Cleaned_Data[[#This Row],[Rating]]=""),"Missing",IF(AND(Cleaned_Data[[#This Row],[Engagement]]="Strong Engagement",Cleaned_Data[[#This Row],[Rating Category]]="Excellent"),"Flag","OK")) -> Missing | P43: =IF(Cleaned_Data[[#This Row],[Rating]]="","Missing Rating","Has Rating") -> Missing Rating | Q43: =IFERROR( (Cleaned_Data[[#This Row],[Old Price]]-Cleaned_Data[[#This Row],[Current Price]])/Cleaned_Data[[#This Row],[Old Price]], "" ) -> 0.5 | R43: =IF( Cleaned_Data[[#This Row],[Discount]] - Cleaned_Data[[#This Row],[Calculated Discount]]>2%, "Check", "OK" ) -> OK | S43: =IF(OR(Cleaned_Data[[#This Row],[Rating]]<0,Cleaned_Data[[#This Row],[Rating]]>5),"Check rating","OK") -> OK | T43: =IF(OR(Cleaned_Data[[#This Row],[Discount]]<0,Cleaned_Data[[#This Row],[Discount]]>1),"Check discount","OK") -> OK | U43: =IF(Cleaned_Data[[#This Row],[Current Price]]>Cleaned_Data[[#This Row],[Old Price]],"Check prices","OK") -> OK
A44: Balloon Insert, Birthday Party Balloon Set, PU Leather | B44: 610 | C44: 1060 | D44: 0.42 | G44: =Cleaned_Data[[#This Row],[Old Price]]-Cleaned_Data[[#This Row],[Current Price]] -> 450 | H44: =IF(Cleaned_Data[[#This Row],[Rating]]="","Missing",IF(Cleaned_Data[[#This Row],[Rating]]<3,"Poor",IF(Cleaned_Data[[#This Row],[Rating]]<=4.5,"Average","Excellent"))) -> Missing | I44: =IF( Cleaned_Data[[#This Row],[Discount]]="", "Missing", IF( Cleaned_Data[[#This Row],[Discount]]<20%, "Low Discount", IF( Cleaned_Data[[#This Row],[Discount]]<=40%, "Medium Discount", "High Discount" ) ) ) -> High Discount | J44: =IF( Cleaned_Data[[#This Row],[Current Price]]="", "Missing", IF( Cleaned_Data[[#This Row],[Current Price]]<=Analysis!$B$3, "Low Price", IF( Cleaned_Data[[#This Row],[Current Price]]<=Analysis!$B$4, "Medium Price", "High Price" ) ) ) -> Medium Price | K44: =IF(Cleaned_Data[[#This Row],[Review]]="","Missing",IF(Cleaned_Data[[#This Row],[Review]]>=Engagement_Threshold,"Strong Engagement","Weak Engagement")) -> Missing | L44: =IF(OR(Cleaned_Data[[#This Row],[Discount]]="",Cleaned_Data[[#This Row],[Rating]]=""),"Missing",IF(AND(Cleaned_Data[[#This Row],[Discount Category]]="High Discount",Cleaned_Data[[#This Row],[Rating Category]]="Poor"),"Flag","OK")) -> Missing | M44: =IF(OR(Cleaned_Data[[#This Row],[Discount]]="",Cleaned_Data[[#This Row],[Review]]=""),"Missing",IF(AND(Cleaned_Data[[#This Row],[Discount Category]]="High Discount",Cleaned_Data[[#This Row],[Engagement]]="Weak Engagement"),"Flag","OK")) -> Missing | N44: =IF(OR(Cleaned_Data[[#This Row],[Review]]="",Cleaned_Data[[#This Row],[Rating]]=""),"Missing",IF(AND(Cleaned_Data[[#This Row],[Engagement]]="Strong Engagement",Cleaned_Data[[#This Row],[Rating Category]]="Average"),"Flag","OK")) -> Missing | O44: =IF(OR(Cleaned_Data[[#This Row],[Review]]="",Cleaned_Data[[#This Row],[Rating]]=""),"Missing",IF(AND(Cleaned_Data[[#This Row],[Engagement]]="Strong Engagement",Cleaned_Data[[#This Row],[Rating Category]]="Excellent"),"Flag","OK")) -> Missing | P44: =IF(Cleaned_Data[[#This Row],[Rating]]="","Missing Rating","Has Rating") -> Missing Rating | Q44: =IFERROR( (Cleaned_Data[[#This Row],[Old Price]]-Cleaned_Data[[#This Row],[Current Price]])/Cleaned_Data[[#This Row],[Old Price]], "" ) -> 0.4245283 | R44: =IF( Cleaned_Data[[#This Row],[Discount]] - Cleaned_Data[[#This Row],[Calculated Discount]]>2%, "Check", "OK" ) -> OK | S44: =IF(OR(Cleaned_Data[[#This Row],[Rating]]<0,Cleaned_Data[[#This Row],[Rating]]>5),"Check rating","OK") -> OK | T44: =IF(OR(Cleaned_Data[[#This Row],[Discount]]<0,Cleaned_Data[[#This Row],[Discount]]>1),"Check discount","OK") -> OK | U44: =IF(Cleaned_Data[[#This Row],[Current Price]]>Cleaned_Data[[#This Row],[Old Price]],"Check prices","OK") -> OK
A45: Shower Cap Wide Elastic Band Cover Reusable Bashroom Cap | B45: 2132 | C45: 2169 | D45: 0.02 | G45: =Cleaned_Data[[#This Row],[Old Price]]-Cleaned_Data[[#This Row],[Current Price]] -> 37 | H45: =IF(Cleaned_Data[[#This Row],[Rating]]="","Missing",IF(Cleaned_Data[[#This Row],[Rating]]<3,"Poor",IF(Cleaned_Data[[#This Row],[Rating]]<=4.5,"Average","Excellent"))) -> Missing | I45: =IF( Cleaned_Data[[#This Row],[Discount]]="", "Missing", IF( Cleaned_Data[[#This Row],[Discount]]<20%, "Low Discount", IF( Cleaned_Data[[#This Row],[Discount]]<=40%, "Medium Discount", "High Discount" ) ) ) -> Low Discount | J45: =IF( Cleaned_Data[[#This Row],[Current Price]]="", "Missing", IF( Cleaned_Data[[#This Row],[Current Price]]<=Analysis!$B$3, "Low Price", IF( Cleaned_Data[[#This Row],[Current Price]]<=Analysis!$B$4, "Medium Price", "High Price" ) ) ) -> High Price | K45: =IF(Cleaned_Data[[#This Row],[Review]]="","Missing",IF(Cleaned_Data[[#This Row],[Review]]>=Engagement_Threshold,"Strong Engagement","Weak Engagement")) -> Missing | L45: =IF(OR(Cleaned_Data[[#This Row],[Discount]]="",Cleaned_Data[[#This Row],[Rating]]=""),"Missing",IF(AND(Cleaned_Data[[#This Row],[Discount Category]]="High Discount",Cleaned_Data[[#This Row],[Rating Category]]="Poor"),"Flag","OK")) -> Missing | M45: =IF(OR(Cleaned_Data[[#This Row],[Discount]]="",Cleaned_Data[[#This Row],[Review]]=""),"Missing",IF(AND(Cleaned_Data[[#This Row],[Discount Category]]="High Discount",Cleaned_Data[[#This Row],[Engagement]]="Weak Engagement"),"Flag","OK")) -> Missing | N45: =IF(OR(Cleaned_Data[[#This Row],[Review]]="",Cleaned_Data[[#This Row],[Rating]]=""),"Missing",IF(AND(Cleaned_Data[[#This Row],[Engagement]]="Strong Engagement",Cleaned_Data[[#This Row],[Rating Category]]="Average"),"Flag","OK")) -> Missing | O45: =IF(OR(Cleaned_Data[[#This Row],[Review]]="",Cleaned_Data[[#This Row],[Rating]]=""),"Missing",IF(AND(Cleaned_Data[[#This Row],[Engagement]]="Strong Engagement",Cleaned_Data[[#This Row],[Rating Category]]="Excellent"),"Flag","OK")) -> Missing | P45: =IF(Cleaned_Data[[#This Row],[Rating]]="","Missing Rating","Has Rating") -> Missing Rating | Q45: =IFERROR( (Cleaned_Data[[#This Row],[Old Price]]-Cleaned_Data[[#This Row],[Current Price]])/Cleaned_Data[[#This Row],[Old Price]], "" ) -> 0.017058552 | R45: =IF( Cleaned_Data[[#This Row],[Discount]] - Cleaned_Data[[#This Row],[Calculated Discount]]>2%, "Check", "OK" ) -> OK | S45: =IF(OR(Cleaned_Data[[#This Row],[Rating]]<0,Cleaned_Data[[#This Row],[Rating]]>5),"Check rating","OK") -> OK | T45: =IF(OR(Cleaned_Data[[#This Row],[Discount]]<0,Cleaned_Data[[#This Row],[Discount]]>1),"Check discount","OK") -> OK | U45: =IF(Cleaned_Data[[#This Row],[Current Price]]>Cleaned_Data[[#This Row],[Old Price]],"Check prices","OK") -> OK
A46: Christmas Elk Fence Yard Lawn Decorations Cute For Holidays | B46: 999 | C46: 2000 | D46: 0.5 | G46: =Cleaned_Data[[#This Row],[Old Price]]-Cleaned_Data[[#This Row],[Current Price]] -> 1001 | H46: =IF(Cleaned_Data[[#This Row],[Rating]]="","Missing",IF(Cleaned_Data[[#This Row],[Rating]]<3,"Poor",IF(Cleaned_Data[[#This Row],[Rating]]<=4.5,"Average","Excellent"))) -> Missing | I46: =IF( Cleaned_Data[[#This Row],[Discount]]="", "Missing", IF( Cleaned_Data[[#This Row],[Discount]]<20%, "Low Discount", IF( Cleaned_Data[[#This Row],[Discount]]<=40%, "Medium Discount", "High Discount" ) ) ) -> High Discount | J46: =IF( Cleaned_Data[[#This Row],[Current Price]]="", "Missing", IF( Cleaned_Data[[#This Row],[Current Price]]<=Analysis!$B$3, "Low Price", IF( Cleaned_Data[[#This Row],[Current Price]]<=Analysis!$B$4, "Medium Price", "High Price" ) ) ) -> Medium Price | K46: =IF(Cleaned_Data[[#This Row],[Review]]="","Missing",IF(Cleaned_Data[[#This Row],[Review]]>=Engagement_Threshold,"Strong Engagement","Weak Engagement")) -> Missing | L46: =IF(OR(Cleaned_Data[[#This Row],[Discount]]="",Cleaned_Data[[#This Row],[Rating]]=""),"Missing",IF(AND(Cleaned_Data[[#This Row],[Discount Category]]="High Discount",Cleaned_Data[[#This Row],[Rating Category]]="Poor"),"Flag","OK")) -> Missing | M46: =IF(OR(Cleaned_Data[[#This Row],[Discount]]="",Cleaned_Data[[#This Row],[Review]]=""),"Missing",IF(AND(Cleaned_Data[[#This Row],[Discount Category]]="High Discount",Cleaned_Data[[#This Row],[Engagement]]="Weak Engagement"),"Flag","OK")) -> Missing | N46: =IF(OR(Cleaned_Data[[#This Row],[Review]]="",Cleaned_Data[[#This Row],[Rating]]=""),"Missing",IF(AND(Cleaned_Data[[#This Row],[Engagement]]="Strong Engagement",Cleaned_Data[[#This Row],[Rating Category]]="Average"),"Flag","OK")) -> Missing | O46: =IF(OR(Cleaned_Data[[#This Row],[Review]]="",Cleaned_Data[[#This Row],[Rating]]=""),"Missing",IF(AND(Cleaned_Data[[#This Row],[Engagement]]="Strong Engagement",Cleaned_Data[[#This Row],[Rating Category]]="Excellent"),"Flag","OK")) -> Missing | P46: =IF(Cleaned_Data[[#This Row],[Rating]]="","Missing Rating","Has Rating") -> Missing Rating | Q46: =IFERROR( (Cleaned_Data[[#This Row],[Old Price]]-Cleaned_Data[[#This Row],[Current Price]])/Cleaned_Data[[#This Row],[Old Price]], "" ) -> 0.5005 | R46: =IF( Cleaned_Data[[#This Row],[Discount]] - Cleaned_Data[[#This Row],[Calculated Discount]]>2%, "Check", "OK" ) -> OK | S46: =IF(OR(Cleaned_Data[[#This Row],[Rating]]<0,Cleaned_Data[[#This Row],[Rating]]>5),"Check rating","OK") -> OK | T46: =IF(OR(Cleaned_Data[[#This Row],[Discount]]<0,Cleaned_Data[[#This Row],[Discount]]>1),"Check discount","OK") -> OK | U46: =IF(Cleaned_Data[[#This Row],[Current Price]]>Cleaned_Data[[#This Row],[Old Price]],"Check prices","OK") -> OK
A47: 60W Hot Melt Glue Sprayer - Efficient And Stable Glue Dispensing | B47: 1190 | C47: 1785 | D47: 0.33 | G47: =Cleaned_Data[[#This Row],[Old Price]]-Cleaned_Data[[#This Row],[Current Price]] -> 595 | H47: =IF(Cleaned_Data[[#This Row],[Rating]]="","Missing",IF(Cleaned_Data[[#This Row],[Rating]]<3,"Poor",IF(Cleaned_Data[[#This Row],[Rating]]<=4.5,"Average","Excellent"))) -> Missing | I47: =IF( Cleaned_Data[[#This Row],[Discount]]="", "Missing", IF( Cleaned_Data[[#This Row],[Discount]]<20%, "Low Discount", IF( Cleaned_Data[[#This Row],[Discount]]<=40%, "Medium Discount", "High Discount" ) ) ) -> Medium Discount | J47: =IF( Cleaned_Data[[#This Row],[Current Price]]="", "Missing", IF( Cleaned_Data[[#This Row],[Current Price]]<=Analysis!$B$3, "Low Price", IF( Cleaned_Data[[#This Row],[Current Price]]<=Analysis!$B$4, "Medium Price", "High Price" ) ) ) -> Medium Price | K47: =IF(Cleaned_Data[[#This Row],[Review]]="","Missing",IF(Cleaned_Data[[#This Row],[Review]]>=Engagement_Threshold,"Strong Engagement","Weak Engagement")) -> Missing | L47: =IF(OR(Cleaned_Data[[#This Row],[Discount]]="",Cleaned_Data[[#This Row],[Rating]]=""),"Missing",IF(AND(Cleaned_Data[[#This Row],[Discount Category]]="High Discount",Cleaned_Data[[#This Row],[Rating Category]]="Poor"),"Flag","OK")) -> Missing | M47: =IF(OR(Cleaned_Data[[#This Row],[Discount]]="",Cleaned_Data[[#This Row],[Review]]=""),"Missing",IF(AND(Cleaned_Data[[#This Row],[Discount Category]]="High Discount",Cleaned_Data[[#This Row],[Engagement]]="Weak Engagement"),"Flag","OK")) -> Missing | N47: =IF(OR(Cleaned_Data[[#This Row],[Review]]="",Cleaned_Data[[#This Row],[Rating]]=""),"Missing",IF(AND(Cleaned_Data[[#This Row],[Engagement]]="Strong Engagement",Cleaned_Data[[#This Row],[Rating Category]]="Average"),"Flag","OK")) -> Missing | O47: =IF(OR(Cleaned_Data[[#This Row],[Review]]="",Cleaned_Data[[#This Row],[Rating]]=""),"Missing",IF(AND(Cleaned_Data[[#This Row],[Engagement]]="Strong Engagement",Cleaned_Data[[#This Row],[Rating Category]]="Excellent"),"Flag","OK")) -> Missing | P47: =IF(Cleaned_Data[[#This Row],[Rating]]="","Missing Rating","Has Rating") -> Missing Rating | Q47: =IFERROR( (Cleaned_Data[[#This Row],[Old Price]]-Cleaned_Data[[#This Row],[Current Price]])/Cleaned_Data[[#This Row],[Old Price]], "" ) -> 0.33333333 | R47: =IF( Cleaned_Data[[#This Row],[Discount]] - Cleaned_Data[[#This Row],[Calculated Discount]]>2%, "Check", "OK" ) -> OK | S47: =IF(OR(Cleaned_Data[[#This Row],[Rating]]<0,Cleaned_Data[[#This Row],[Rating]]>5),"Check rating","OK") -> OK | T47: =IF(OR(Cleaned_Data[[#This Row],[Discount]]<0,Cleaned_Data[[#This Row],[Discount]]>1),"Check discount","OK") -> OK | U47: =IF(Cleaned_Data[[#This Row],[Current Price]]>Cleaned_Data[[#This Row],[Old Price]],"Check prices","OK") -> OK
A48: Car Phone Charging Stand | B48: 671 | C48: 1316 | D48: 0.49 | G48: =Cleaned_Data[[#This Row],[Old Price]]-Cleaned_Data[[#This Row],[Current Price]] -> 645 | H48: =IF(Cleaned_Data[[#This Row],[Rating]]="","Missing",IF(Cleaned_Data[[#This Row],[Rating]]<3,"Poor",IF(Cleaned_Data[[#This Row],[Rating]]<=4.5,"Average","Excellent"))) -> Missing | I48: =IF( Cleaned_Data[[#This Row],[Discount]]="", "Missing", IF( Cleaned_Data[[#This Row],[Discount]]<20%, "Low Discount", IF( Cleaned_Data[[#This Row],[Discount]]<=40%, "Medium Discount", "High Discount" ) ) ) -> High Discount | J48: =IF( Cleaned_Data[[#This Row],[Current Price]]="", "Missing", IF( Cleaned_Data[[#This Row],[Current Price]]<=Analysis!$B$3, "Low Price", IF( Cleaned_Data[[#This Row],[Current Price]]<=Analysis!$B$4, "Medium Price", "High Price" ) ) ) -> Medium Price | K48: =IF(Cleaned_Data[[#This Row],[Review]]="","Missing",IF(Cleaned_Data[[#This Row],[Review]]>=Engagement_Threshold,"Strong Engagement","Weak Engagement")) -> Missing | L48: =IF(OR(Cleaned_Data[[#This Row],[Discount]]="",Cleaned_Data[[#This Row],[Rating]]=""),"Missing",IF(AND(Cleaned_Data[[#This Row],[Discount Category]]="High Discount",Cleaned_Data[[#This Row],[Rating Category]]="Poor"),"Flag","OK")) -> Missing | M48: =IF(OR(Cleaned_Data[[#This Row],[Discount]]="",Cleaned_Data[[#This Row],[Review]]=""),"Missing",IF(AND(Cleaned_Data[[#This Row],[Discount Category]]="High Discount",Cleaned_Data[[#This Row],[Engagement]]="Weak Engagement"),"Flag","OK")) -> Missing | N48: =IF(OR(Cleaned_Data[[#This Row],[Review]]="",Cleaned_Data[[#This Row],[Rating]]=""),"Missing",IF(AND(Cleaned_Data[[#This Row],[Engagement]]="Strong Engagement",Cleaned_Data[[#This Row],[Rating Category]]="Average"),"Flag","OK")) -> Missing | O48: =IF(OR(Cleaned_Data[[#This Row],[Review]]="",Cleaned_Data[[#This Row],[Rating]]=""),"Missing",IF(AND(Cleaned_Data[[#This Row],[Engagement]]="Strong Engagement",Cleaned_Data[[#This Row],[Rating Category]]="Excellent"),"Flag","OK")) -> Missing | P48: =IF(Cleaned_Data[[#This Row],[Rating]]="","Missing Rating","Has Rating") -> Missing Rating | Q48: =IFERROR( (Cleaned_Data[[#This Row],[Old Price]]-Cleaned_Data[[#This Row],[Current Price]])/Cleaned_Data[[#This Row],[Old Price]], "" ) -> 0.49012158 | R48: =IF( Cleaned_Data[[#This Row],[Discount]] - Cleaned_Data[[#This Row],[Calculated Discount]]>2%, "Check", "OK" ) -> OK | S48: =IF(OR(Cleaned_Data[[#This Row],[Rating]]<0,Cleaned_Data[[#This Row],[Rating]]>5),"Check rating","OK") -> OK | T48: =IF(OR(Cleaned_Data[[#This Row],[Discount]]<0,Cleaned_Data[[#This Row],[Discount]]>1),"Check discount","OK") -> OK | U48: =IF(Cleaned_Data[[#This Row],[Current Price]]>Cleaned_Data[[#This Row],[Old Price]],"Check prices","OK") -> OK
A49: 2pcs Solar Street Light Flood Light Outdoor | B49: 1200 | C49: 1950 | D49: 0.38 | G49: =Cleaned_Data[[#This Row],[Old Price]]-Cleaned_Data[[#This Row],[Current Price]] -> 750 | H49: =IF(Cleaned_Data[[#This Row],[Rating]]="","Missing",IF(Cleaned_Data[[#This Row],[Rating]]<3,"Poor",IF(Cleaned_Data[[#This Row],[Rating]]<=4.5,"Average","Excellent"))) -> Missing | I49: =IF( Cleaned_Data[[#This Row],[Discount]]="", "Missing", IF( Cleaned_Data[[#This Row],[Discount]]<20%, "Low Discount", IF( Cleaned_Data[[#This Row],[Discount]]<=40%, "Medium Discount", "High Discount" ) ) ) -> Medium Discount | J49: =IF( Cleaned_Data[[#This Row],[Current Price]]="", "Missing", IF( Cleaned_Data[[#This Row],[Current Price]]<=Analysis!$B$3, "Low Price", IF( Cleaned_Data[[#This Row],[Current Price]]<=Analysis!$B$4, "Medium Price", "High Price" ) ) ) -> Medium Price | K49: =IF(Cleaned_Data[[#This Row],[Review]]="","Missing",IF(Cleaned_Data[[#This Row],[Review]]>=Engagement_Threshold,"Strong Engagement","Weak Engagement")) -> Missing | L49: =IF(OR(Cleaned_Data[[#This Row],[Discount]]="",Cleaned_Data[[#This Row],[Rating]]=""),"Missing",IF(AND(Cleaned_Data[[#This Row],[Discount Category]]="High Discount",Cleaned_Data[[#This Row],[Rating Category]]="Poor"),"Flag","OK")) -> Missing | M49: =IF(OR(Cleaned_Data[[#This Row],[Discount]]="",Cleaned_Data[[#This Row],[Review]]=""),"Missing",IF(AND(Cleaned_Data[[#This Row],[Discount Category]]="High Discount",Cleaned_Data[[#This Row],[Engagement]]="Weak Engagement"),"Flag","OK")) -> Missing | N49: =IF(OR(Cleaned_Data[[#This Row],[Review]]="",Cleaned_Data[[#This Row],[Rating]]=""),"Missing",IF(AND(Cleaned_Data[[#This Row],[Engagement]]="Strong Engagement",Cleaned_Data[[#This Row],[Rating Category]]="Average"),"Flag","OK")) -> Missing | O49: =IF(OR(Cleaned_Data[[#This Row],[Review]]="",Cleaned_Data[[#This Row],[Rating]]=""),"Missing",IF(AND(Cleaned_Data[[#This Row],[Engagement]]="Strong Engagement",Cleaned_Data[[#This Row],[Rating Category]]="Excellent"),"Flag","OK")) -> Missing | P49: =IF(Cleaned_Data[[#This Row],[Rating]]="","Missing Rating","Has Rating") -> Missing Rating | Q49: =IFERROR( (Cleaned_Data[[#This Row],[Old Price]]-Cleaned_Data[[#This Row],[Current Price]])/Cleaned_Data[[#This Row],[Old Price]], "" ) -> 0.38461538 | R49: =IF( Cleaned_Data[[#This Row],[Discount]] - Cleaned_Data[[#This Row],[Calculated Discount]]>2%, "Check", "OK" ) -> OK | S49: =IF(OR(Cleaned_Data[[#This Row],[Rating]]<0,Cleaned_Data[[#This Row],[Rating]]>5),"Check rating","OK") -> OK | T49: =IF(OR(Cleaned_Data[[#This Row],[Discount]]<0,Cleaned_Data[[#This Row],[Discount]]>1),"Check discount","OK") -> OK | U49: =IF(Cleaned_Data[[#This Row],[Current Price]]>Cleaned_Data[[#This Row],[Old Price]],"Check prices","OK") -> OK
A50: Creative Owl Shape Keychain Black | B50: 199 | C50: 504 | D50: 0.61 | G50: =Cleaned_Data[[#This Row],[Old Price]]-Cleaned_Data[[#This Row],[Current Price]] -> 305 | H50: =IF(Cleaned_Data[[#This Row],[Rating]]="","Missing",IF(Cleaned_Data[[#This Row],[Rating]]<3,"Poor",IF(Cleaned_Data[[#This Row],[Rating]]<=4.5,"Average","Excellent"))) -> Missing | I50: =IF( Cleaned_Data[[#This Row],[Discount]]="", "Missing", IF( Cleaned_Data[[#This Row],[Discount]]<20%, "Low Discount", IF( Cleaned_Data[[#This Row],[Discount]]<=40%, "Medium Discount", "High Discount" ) ) ) -> High Discount | J50: =IF( Cleaned_Data[[#This Row],[Current Price]]="", "Missing", IF( Cleaned_Data[[#This Row],[Current Price]]<=Analysis!$B$3, "Low Price", IF( Cleaned_Data[[#This Row],[Current Price]]<=Analysis!$B$4, "Medium Price", "High Price" ) ) ) -> Low Price | K50: =IF(Cleaned_Data[[#This Row],[Review]]="","Missing",IF(Cleaned_Data[[#This Row],[Review]]>=Engagement_Threshold,"Strong Engagement","Weak Engagement")) -> Missing | L50: =IF(OR(Cleaned_Data[[#This Row],[Discount]]="",Cleaned_Data[[#This Row],[Rating]]=""),"Missing",IF(AND(Cleaned_Data[[#This Row],[Discount Category]]="High Discount",Cleaned_Data[[#This Row],[Rating Category]]="Poor"),"Flag","OK")) -> Missing | M50: =IF(OR(Cleaned_Data[[#This Row],[Discount]]="",Cleaned_Data[[#This Row],[Review]]=""),"Missing",IF(AND(Cleaned_Data[[#This Row],[Discount Category]]="High Discount",Cleaned_Data[[#This Row],[Engagement]]="Weak Engagement"),"Flag","OK")) -> Missing | N50: =IF(OR(Cleaned_Data[[#This Row],[Review]]="",Cleaned_Data[[#This Row],[Rating]]=""),"Missing",IF(AND(Cleaned_Data[[#This Row],[Engagement]]="Strong Engagement",Cleaned_Data[[#This Row],[Rating Category]]="Average"),"Flag","OK")) -> Missing | O50: =IF(OR(Cleaned_Data[[#This Row],[Review]]="",Cleaned_Data[[#This Row],[Rating]]=""),"Missing",IF(AND(Cleaned_Data[[#This Row],[Engagement]]="Strong Engagement",Cleaned_Data[[#This Row],[Rating Category]]="Excellent"),"Flag","OK")) -> Missing | P50: =IF(Cleaned_Data[[#This Row],[Rating]]="","Missing Rating","Has Rating") -> Missing Rating | Q50: =IFERROR( (Cleaned_Data[[#This Row],[Old Price]]-Cleaned_Data[[#This Row],[Current Price]])/Cleaned_Data[[#This Row],[Old Price]], "" ) -> 0.60515873 | R50: =IF( Cleaned_Data[[#This Row],[Discount]] - Cleaned_Data[[#This Row],[Calculated Discount]]>2%, "Check", "OK" ) -> OK | S50: =IF(OR(Cleaned_Data[[#This Row],[Rating]]<0,Cleaned_Data[[#This Row],[Rating]]>5),"Check rating","OK") -> OK | T50: =IF(OR(Cleaned_Data[[#This Row],[Discount]]<0,Cleaned_Data[[#This Row],[Discount]]>1),"Check discount","OK") -> OK | U50: =IF(Cleaned_Data[[#This Row],[Current Price]]>Cleaned_Data[[#This Row],[Old Price]],"Check prices","OK") -> OK
A51: Brush & Paintbrush Cleaning Tool Pink | B51: 299 | C51: 600 | D51: 0.5 | G51: =Cleaned_Data[[#This Row],[Old Price]]-Cleaned_Data[[#This Row],[Current Price]] -> 301 | H51: =IF(Cleaned_Data[[#This Row],[Rating]]="","Missing",IF(Cleaned_Data[[#This Row],[Rating]]<3,"Poor",IF(Cleaned_Data[[#This Row],[Rating]]<=4.5,"Average","Excellent"))) -> Missing | I51: =IF( Cleaned_Data[[#This Row],[Discount]]="", "Missing", IF( Cleaned_Data[[#This Row],[Discount]]<20%, "Low Discount", IF( Cleaned_Data[[#This Row],[Discount]]<=40%, "Medium Discount", "High Discount" ) ) ) -> High Discount | J51: =IF( Cleaned_Data[[#This Row],[Current Price]]="", "Missing", IF( Cleaned_Data[[#This Row],[Current Price]]<=Analysis!$B$3, "Low Price", IF( Cleaned_Data[[#This Row],[Current Price]]<=Analysis!$B$4, "Medium Price", "High Price" ) ) ) -> Low Price | K51: =IF(Cleaned_Data[[#This Row],[Review]]="","Missing",IF(Cleaned_Data[[#This Row],[Review]]>=Engagement_Threshold,"Strong Engagement","Weak Engagement")) -> Missing | L51: =IF(OR(Cleaned_Data[[#This Row],[Discount]]="",Cleaned_Data[[#This Row],[Rating]]=""),"Missing",IF(AND(Cleaned_Data[[#This Row],[Discount Category]]="High Discount",Cleaned_Data[[#This Row],[Rating Category]]="Poor"),"Flag","OK")) -> Missing | M51: =IF(OR(Cleaned_Data[[#This Row],[Discount]]="",Cleaned_Data[[#This Row],[Review]]=""),"Missing",IF(AND(Cleaned_Data[[#This Row],[Discount Category]]="High Discount",Cleaned_Data[[#This Row],[Engagement]]="Weak Engagement"),"Flag","OK")) -> Missing | N51: =IF(OR(Cleaned_Data[[#This Row],[Review]]="",Cleaned_Data[[#This Row],[Rating]]=""),"Missing",IF(AND(Cleaned_Data[[#This Row],[Engagement]]="Strong Engagement",Cleaned_Data[[#This Row],[Rating Category]]="Average"),"Flag","OK")) -> Missing | O51: =IF(OR(Cleaned_Data[[#This Row],[Review]]="",Cleaned_Data[[#This Row],[Rating]]=""),"Missing",IF(AND(Cleaned_Data[[#This Row],[Engagement]]="Strong Engagement",Cleaned_Data[[#This Row],[Rating Category]]="Excellent"),"Flag","OK")) -> Missing | P51: =IF(Cleaned_Data[[#This Row],[Rating]]="","Missing Rating","Has Rating") -> Missing Rating | Q51: =IFERROR( (Cleaned_Data[[#This Row],[Old Price]]-Cleaned_Data[[#This Row],[Current Price]])/Cleaned_Data[[#This Row],[Old Price]], "" ) -> 0.50166667 | R51: =IF( Cleaned_Data[[#This Row],[Discount]] - Cleaned_Data[[#This Row],[Calculated Discount]]>2%, "Check", "OK" ) -> OK | S51: =IF(OR(Cleaned_Data[[#This Row],[Rating]]<0,Cleaned_Data[[#This Row],[Rating]]>5),"Check rating","OK") -> OK | T51: =IF(OR(Cleaned_Data[[#This Row],[Discount]]<0,Cleaned_Data[[#This Row],[Discount]]>1),"Check discount","OK") -> OK | U51: =IF(Cleaned_Data[[#This Row],[Current Price]]>Cleaned_Data[[#This Row],[Old Price]],"Check prices","OK") -> OK
A52: Pen Grips For Kids Pen Grip Posture Correction Tool For Kids | B52: 1660 | C52: 1699 | D52: 0.02 | G52: =Cleaned_Data[[#This Row],[Old Price]]-Cleaned_Data[[#This Row],[Current Price]] -> 39 | H52: =IF(Cleaned_Data[[#This Row],[Rating]]="","Missing",IF(Cleaned_Data[[#This Row],[Rating]]<3,"Poor",IF(Cleaned_Data[[#This Row],[Rating]]<=4.5,"Average","Excellent"))) -> Missing | I52: =IF( Cleaned_Data[[#This Row],[Discount]]="", "Missing", IF( Cleaned_Data[[#This Row],[Discount]]<20%, "Low Discount", IF( Cleaned_Data[[#This Row],[Discount]]<=40%, "Medium Discount", "High Discount" ) ) ) -> Low Discount | J52: =IF( Cleaned_Data[[#This Row],[Current Price]]="", "Missing", IF( Cleaned_Data[[#This Row],[Current Price]]<=Analysis!$B$3, "Low Price", IF( Cleaned_Data[[#This Row],[Current Price]]<=Analysis!$B$4, "Medium Price", "High Price" ) ) ) -> Medium Price | K52: =IF(Cleaned_Data[[#This Row],[Review]]="","Missing",IF(Cleaned_Data[[#This Row],[Review]]>=Engagement_Threshold,"Strong Engagement","Weak Engagement")) -> Missing | L52: =IF(OR(Cleaned_Data[[#This Row],[Discount]]="",Cleaned_Data[[#This Row],[Rating]]=""),"Missing",IF(AND(Cleaned_Data[[#This Row],[Discount Category]]="High Discount",Cleaned_Data[[#This Row],[Rating Category]]="Poor"),"Flag","OK")) -> Missing | M52: =IF(OR(Cleaned_Data[[#This Row],[Discount]]="",Cleaned_Data[[#This Row],[Review]]=""),"Missing",IF(AND(Cleaned_Data[[#This Row],[Discount Category]]="High Discount",Cleaned_Data[[#This Row],[Engagement]]="Weak Engagement"),"Flag","OK")) -> Missing | N52: =IF(OR(Cleaned_Data[[#This Row],[Review]]="",Cleaned_Data[[#This Row],[Rating]]=""),"Missing",IF(AND(Cleaned_Data[[#This Row],[Engagement]]="Strong Engagement",Cleaned_Data[[#This Row],[Rating Category]]="Average"),"Flag","OK")) -> Missing | O52: =IF(OR(Cleaned_Data[[#This Row],[Review]]="",Cleaned_Data[[#This Row],[Rating]]=""),"Missing",IF(AND(Cleaned_Data[[#This Row],[Engagement]]="Strong Engagement",Cleaned_Data[[#This Row],[Rating Category]]="Excellent"),"Flag","OK")) -> Missing | P52: =IF(Cleaned_Data[[#This Row],[Rating]]="","Missing Rating","Has Rating") -> Missing Rating | Q52: =IFERROR( (Cleaned_Data[[#This Row],[Old Price]]-Cleaned_Data[[#This Row],[Current Price]])/Cleaned_Data[[#This Row],[Old Price]], "" ) -> 0.022954679 | R52: =IF( Cleaned_Data[[#This Row],[Discount]] - Cleaned_Data[[#This Row],[Calculated Discount]]>2%, "Check", "OK" ) -> OK | S52: =IF(OR(Cleaned_Data[[#This Row],[Rating]]<0,Cleaned_Data[[#This Row],[Rating]]>5),"Check rating","OK") -> OK | T52: =IF(OR(Cleaned_Data[[#This Row],[Discount]]<0,Cleaned_Data[[#This Row],[Discount]]>1),"Check discount","OK") -> OK | U52: =IF(Cleaned_Data[[#This Row],[Current Price]]>Cleaned_Data[[#This Row],[Old Price]],"Check prices","OK") -> OK
... A60: Simple Metal Dog Art Sculpture Decoration For Home Office | B60: 399 | C60: 896 | D60: 0.55 | G60: =Cleaned_Data[[#This Row],[Old Price]]-Cleaned_Data[[#This Row],[Current Price]] -> 497 | H60: =IF(Cleaned_Data[[#This Row],[Rating]]="","Missing",IF(Cleaned_Data[[#This Row],[Rating]]<3,"Poor",IF(Cleaned_Data[[#This Row],[Rating]]<=4.5,"Average","Excellent"))) -> Missing | I60: =IF( Cleaned_Data[[#This Row],[Discount]]="", "Missing", IF( Cleaned_Data[[#This Row],[Discount]]<20%, "Low Discount", IF( Cleaned_Data[[#This Row],[Discount]]<=40%, "Medium Discount", "High Discount" ) ) ) -> High Discount | J60: =IF( Cleaned_Data[[#This Row],[Current Price]]="", "Missing", IF( Cleaned_Data[[#This Row],[Current Price]]<=Analysis!$B$3, "Low Price", IF( Cleaned_Data[[#This Row],[Current Price]]<=Analysis!$B$4, "Medium Price", "High Price" ) ) ) -> Low Price | K60: =IF(Cleaned_Data[[#This Row],[Review]]="","Missing",IF(Cleaned_Data[[#This Row],[Review]]>=Engagement_Threshold,"Strong Engagement","Weak Engagement")) -> Missing | L60: =IF(OR(Cleaned_Data[[#This Row],[Discount]]="",Cleaned_Data[[#This Row],[Rating]]=""),"Missing",IF(AND(Cleaned_Data[[#This Row],[Discount Category]]="High Discount",Cleaned_Data[[#This Row],[Rating Category]]="Poor"),"Flag","OK")) -> Missing | M60: =IF(OR(Cleaned_Data[[#This Row],[Discount]]="",Cleaned_Data[[#This Row],[Review]]=""),"Missing",IF(AND(Cleaned_Data[[#This Row],[Discount Category]]="High Discount",Cleaned_Data[[#This Row],[Engagement]]="Weak Engagement"),"Flag","OK")) -> Missing | N60: =IF(OR(Cleaned_Data[[#This Row],[Review]]="",Cleaned_Data[[#This Row],[Rating]]=""),"Missing",IF(AND(Cleaned_Data[[#This Row],[Engagement]]="Strong Engagement",Cleaned_Data[[#This Row],[Rating Category]]="Average"),"Flag","OK")) -> Missing | O60: =IF(OR(Cleaned_Data[[#This Row],[Review]]="",Cleaned_Data[[#This Row],[Rating]]=""),"Missing",IF(AND(Cleaned_Data[[#This Row],[Engagement]]="Strong Engagement",Cleaned_Data[[#This Row],[Rating Category]]="Excellent"),"Flag","OK")) -> Missing | P60: =IF(Cleaned_Data[[#This Row],[Rating]]="","Missing Rating","Has Rating") -> Missing Rating | Q60: =IFERROR( (Cleaned_Data[[#This Row],[Old Price]]-Cleaned_Data[[#This Row],[Current Price]])/Cleaned_Data[[#This Row],[Old Price]], "" ) -> 0.5546875 | R60: =IF( Cleaned_Data[[#This Row],[Discount]] - Cleaned_Data[[#This Row],[Calculated Discount]]>2%, "Check", "OK" ) -> OK | S60: =IF(OR(Cleaned_Data[[#This Row],[Rating]]<0,Cleaned_Data[[#This Row],[Rating]]>5),"Check rating","OK") -> OK | T60: =IF(OR(Cleaned_Data[[#This Row],[Discount]]<0,Cleaned_Data[[#This Row],[Discount]]>1),"Check discount","OK") -> OK | U60: =IF(Cleaned_Data[[#This Row],[Current Price]]>Cleaned_Data[[#This Row],[Old Price]],"Check prices","OK") -> OK
A61: 5 Pieces/set Of Stainless Steel Induction Cooker Pots | B61: 2170 | C61: 2500 | D61: 0.13 | E61: 6 | F61: 2.5 | G61: =Cleaned_Data[[#This Row],[Old Price]]-Cleaned_Data[[#This Row],[Current Price]] -> 330 | H61: =IF(Cleaned_Data[[#This Row],[Rating]]="","Missing",IF(Cleaned_Data[[#This Row],[Rating]]<3,"Poor",IF(Cleaned_Data[[#This Row],[Rating]]<=4.5,"Average","Excellent"))) -> Poor | I61: =IF( Cleaned_Data[[#This Row],[Discount]]="", "Missing", IF( Cleaned_Data[[#This Row],[Discount]]<20%, "Low Discount", IF( Cleaned_Data[[#This Row],[Discount]]<=40%, "Medium Discount", "High Discount" ) ) ) -> Low Discount | J61: =IF( Cleaned_Data[[#This Row],[Current Price]]="", "Missing", IF( Cleaned_Data[[#This Row],[Current Price]]<=Analysis!$B$3, "Low Price", IF( Cleaned_Data[[#This Row],[Current Price]]<=Analysis!$B$4, "Medium Price", "High Price" ) ) ) -> High Price | K61: =IF(Cleaned_Data[[#This Row],[Review]]="","Missing",IF(Cleaned_Data[[#This Row],[Review]]>=Engagement_Threshold,"Strong Engagement","Weak Engagement")) -> Weak Engagement | L61: =IF(OR(Cleaned_Data[[#This Row],[Discount]]="",Cleaned_Data[[#This Row],[Rating]]=""),"Missing",IF(AND(Cleaned_Data[[#This Row],[Discount Category]]="High Discount",Cleaned_Data[[#This Row],[Rating Category]]="Poor"),"Flag","OK")) -> OK | M61: =IF(OR(Cleaned_Data[[#This Row],[Discount]]="",Cleaned_Data[[#This Row],[Review]]=""),"Missing",IF(AND(Cleaned_Data[[#This Row],[Discount Category]]="High Discount",Cleaned_Data[[#This Row],[Engagement]]="Weak Engagement"),"Flag","OK")) -> OK | N61: =IF(OR(Cleaned_Data[[#This Row],[Review]]="",Cleaned_Data[[#This Row],[Rating]]=""),"Missing",IF(AND(Cleaned_Data[[#This Row],[Engagement]]="Strong Engagement",Cleaned_Data[[#This Row],[Rating Category]]="Average"),"Flag","OK")) -> OK | O61: =IF(OR(Cleaned_Data[[#This Row],[Review]]="",Cleaned_Data[[#This Row],[Rating]]=""),"Missing",IF(AND(Cleaned_Data[[#This Row],[Engagement]]="Strong Engagement",Cleaned_Data[[#This Row],[Rating Category]]="Excellent"),"Flag","OK")) -> OK | P61: =IF(Cleaned_Data[[#This Row],[Rating]]="","Missing Rating","Has Rating") -> Has Rating | Q61: =IFERROR( (Cleaned_Data[[#This Row],[Old Price]]-Cleaned_Data[[#This Row],[Current Price]])/Cleaned_Data[[#This Row],[Old Price]], "" ) -> 0.132 | R61: =IF( Cleaned_Data[[#This Row],[Discount]] - Cleaned_Data[[#This Row],[Calculated Discount]]>2%, "Check", "OK" ) -> OK | S61: =IF(OR(Cleaned_Data[[#This Row],[Rating]]<0,Cleaned_Data[[#This Row],[Rating]]>5),"Check rating","OK") -> OK | T61: =IF(OR(Cleaned_Data[[#This Row],[Discount]]<0,Cleaned_Data[[#This Row],[Discount]]>1),"Check discount","OK") -> OK | U61: =IF(Cleaned_Data[[#This Row],[Current Price]]>Cleaned_Data[[#This Row],[Old Price]],"Check prices","OK") -> OK
A62: Mythco 120COB Solar Wall Ligt With Motion Sensor And Remote Control 3 Modes | B62: 458 | C62: 986 | D62: 0.54 | E62: 10 | F62: 3 | G62: =Cleaned_Data[[#This Row],[Old Price]]-Cleaned_Data[[#This Row],[Current Price]] -> 528 | H62: =IF(Cleaned_Data[[#This Row],[Rating]]="","Missing",IF(Cleaned_Data[[#This Row],[Rating]]<3,"Poor",IF(Cleaned_Data[[#This Row],[Rating]]<=4.5,"Average","Excellent"))) -> Average | I62: =IF( Cleaned_Data[[#This Row],[Discount]]="", "Missing", IF( Cleaned_Data[[#This Row],[Discount]]<20%, "Low Discount", IF( Cleaned_Data[[#This Row],[Discount]]<=40%, "Medium Discount", "High Discount" ) ) ) -> High Discount | J62: =IF( Cleaned_Data[[#This Row],[Current Price]]="", "Missing", IF( Cleaned_Data[[#This Row],[Current Price]]<=Analysis!$B$3, "Low Price", IF( Cleaned_Data[[#This Row],[Current Price]]<=Analysis!$B$4, "Medium Price", "High Price" ) ) ) -> Low Price | K62: =IF(Cleaned_Data[[#This Row],[Review]]="","Missing",IF(Cleaned_Data[[#This Row],[Review]]>=Engagement_Threshold,"Strong Engagement","Weak Engagement")) -> Weak Engagement | L62: =IF(OR(Cleaned_Data[[#This Row],[Discount]]="",Cleaned_Data[[#This Row],[Rating]]=""),"Missing",IF(AND(Cleaned_Data[[#This Row],[Discount Category]]="High Discount",Cleaned_Data[[#This Row],[Rating Category]]="Poor"),"Flag","OK")) -> OK | M62: =IF(OR(Cleaned_Data[[#This Row],[Discount]]="",Cleaned_Data[[#This Row],[Review]]=""),"Missing",IF(AND(Cleaned_Data[[#This Row],[Discount Category]]="High Discount",Cleaned_Data[[#This Row],[Engagement]]="Weak Engagement"),"Flag","OK")) -> Flag | N62: =IF(OR(Cleaned_Data[[#This Row],[Review]]="",Cleaned_Data[[#This Row],[Rating]]=""),"Missing",IF(AND(Cleaned_Data[[#This Row],[Engagement]]="Strong Engagement",Cleaned_Data[[#This Row],[Rating Category]]="Average"),"Flag","OK")) -> OK | O62: =IF(OR(Cleaned_Data[[#This Row],[Review]]="",Cleaned_Data[[#This Row],[Rating]]=""),"Missing",IF(AND(Cleaned_Data[[#This Row],[Engagement]]="Strong Engagement",Cleaned_Data[[#This Row],[Rating Category]]="Excellent"),"Flag","OK")) -> OK | P62: =IF(Cleaned_Data[[#This Row],[Rating]]="","Missing Rating","Has Rating") -> Has Rating | Q62: =IFERROR( (Cleaned_Data[[#This Row],[Old Price]]-Cleaned_Data[[#This Row],[Current Price]])/Cleaned_Data[[#This Row],[Old Price]], "" ) -> 0.53549696 | R62: =IF( Cleaned_Data[[#This Row],[Discount]] - Cleaned_Data[[#This Row],[Calculated Discount]]>2%, "Check", "OK" ) -> OK | S62: =IF(OR(Cleaned_Data[[#This Row],[Rating]]<0,Cleaned_Data[[#This Row],[Rating]]>5),"Check rating","OK") -> OK | T62: =IF(OR(Cleaned_Data[[#This Row],[Discount]]<0,Cleaned_Data[[#This Row],[Discount]]>1),"Check discount","OK") -> OK | U62: =IF(Cleaned_Data[[#This Row],[Current Price]]>Cleaned_Data[[#This Row],[Old Price]],"Check prices","OK") -> OK
A63: 5-PCS Stainless Steel Cooking Pot Set With Steamed Slices | B63: 2115 | C63: 4700 | D63: 0.55 | E63: 13 | F63: 2.1 | G63: =Cleaned_Data[[#This Row],[Old Price]]-Cleaned_Data[[#This Row],[Current Price]] -> 2585 | H63: =IF(Cleaned_Data[[#This Row],[Rating]]="","Missing",IF(Cleaned_Data[[#This Row],[Rating]]<3,"Poor",IF(Cleaned_Data[[#This Row],[Rating]]<=4.5,"Average","Excellent"))) -> Poor | I63: =IF( Cleaned_Data[[#This Row],[Discount]]="", "Missing", IF( Cleaned_Data[[#This Row],[Discount]]<20%, "Low Discount", IF( Cleaned_Data[[#This Row],[Discount]]<=40%, "Medium Discount", "High Discount" ) ) ) -> High Discount | J63: =IF( Cleaned_Data[[#This Row],[Current Price]]="", "Missing", IF( Cleaned_Data[[#This Row],[Current Price]]<=Analysis!$B$3, "Low Price", IF( Cleaned_Data[[#This Row],[Current Price]]<=Analysis!$B$4, "Medium Price", "High Price" ) ) ) -> High Price | K63: =IF(Cleaned_Data[[#This Row],[Review]]="","Missing",IF(Cleaned_Data[[#This Row],[Review]]>=Engagement_Threshold,"Strong Engagement","Weak Engagement")) -> Weak Engagement | L63: =IF(OR(Cleaned_Data[[#This Row],[Discount]]="",Cleaned_Data[[#This Row],[Rating]]=""),"Missing",IF(AND(Cleaned_Data[[#This Row],[Discount Category]]="High Discount",Cleaned_Data[[#This Row],[Rating Category]]="Poor"),"Flag","OK")) -> Flag | M63: =IF(OR(Cleaned_Data[[#This Row],[Discount]]="",Cleaned_Data[[#This Row],[Review]]=""),"Missing",IF(AND(Cleaned_Data[[#This Row],[Discount Category]]="High Discount",Cleaned_Data[[#This Row],[Engagement]]="Weak Engagement"),"Flag","OK")) -> Flag | N63: =IF(OR(Cleaned_Data[[#This Row],[Review]]="",Cleaned_Data[[#This Row],[Rating]]=""),"Missing",IF(AND(Cleaned_Data[[#This Row],[Engagement]]="Strong Engagement",Cleaned_Data[[#This Row],[Rating Category]]="Average"),"Flag","OK")) -> OK | O63: =IF(OR(Cleaned_Data[[#This Row],[Review]]="",Cleaned_Data[[#This Row],[Rating]]=""),"Missing",IF(AND(Cleaned_Data[[#This Row],[Engagement]]="Strong Engagement",Cleaned_Data[[#This Row],[Rating Category]]="Excellent"),"Flag","OK")) -> OK | P63: =IF(Cleaned_Data[[#This Row],[Rating]]="","Missing Rating","Has Rating") -> Has Rating | Q63: =IFERROR( (Cleaned_Data[[#This Row],[Old Price]]-Cleaned_Data[[#This Row],[Current Price]])/Cleaned_Data[[#This Row],[Old Price]], "" ) -> 0.55 | R63: =IF( Cleaned_Data[[#This Row],[Discount]] - Cleaned_Data[[#This Row],[Calculated Discount]]>2%, "Check", "OK" ) -> OK | S63: =IF(OR(Cleaned_Data[[#This Row],[Rating]]<0,Cleaned_Data[[#This Row],[Rating]]>5),"Check rating","OK") -> OK | T63: =IF(OR(Cleaned_Data[[#This Row],[Discount]]<0,Cleaned_Data[[#This Row],[Discount]]>1),"Check discount","OK") -> OK | U63: =IF(Cleaned_Data[[#This Row],[Current Price]]>Cleaned_Data[[#This Row],[Old Price]],"Check prices","OK") -> OK
A64: 120W Cordless Vacuum Cleaners Handheld Electric Vacuum Cleaner | B64: 445 | C64: 873 | D64: 0.49 | E64: 69 | F64: 2.8 | G64: =Cleaned_Data[[#This Row],[Old Price]]-Cleaned_Data[[#This Row],[Current Price]] -> 428 | H64: =IF(Cleaned_Data[[#This Row],[Rating]]="","Missing",IF(Cleaned_Data[[#This Row],[Rating]]<3,"Poor",IF(Cleaned_Data[[#This Row],[Rating]]<=4.5,"Average","Excellent"))) -> Poor | I64: =IF( Cleaned_Data[[#This Row],[Discount]]="", "Missing", IF( Cleaned_Data[[#This Row],[Discount]]<20%, "Low Discount", IF( Cleaned_Data[[#This Row],[Discount]]<=40%, "Medium Discount", "High Discount" ) ) ) -> High Discount | J64: =IF( Cleaned_Data[[#This Row],[Current Price]]="", "Missing", IF( Cleaned_Data[[#This Row],[Current Price]]<=Analysis!$B$3, "Low Price", IF( Cleaned_Data[[#This Row],[Current Price]]<=Analysis!$B$4, "Medium Price", "High Price" ) ) ) -> Low Price | K64: =IF(Cleaned_Data[[#This Row],[Review]]="","Missing",IF(Cleaned_Data[[#This Row],[Review]]>=Engagement_Threshold,"Strong Engagement","Weak Engagement")) -> Strong Engagement | L64: =IF(OR(Cleaned_Data[[#This Row],[Discount]]="",Cleaned_Data[[#This Row],[Rating]]=""),"Missing",IF(AND(Cleaned_Data[[#This Row],[Discount Category]]="High Discount",Cleaned_Data[[#This Row],[Rating Category]]="Poor"),"Flag","OK")) -> Flag | M64: =IF(OR(Cleaned_Data[[#This Row],[Discount]]="",Cleaned_Data[[#This Row],[Review]]=""),"Missing",IF(AND(Cleaned_Data[[#This Row],[Discount Category]]="High Discount",Cleaned_Data[[#This Row],[Engagement]]="Weak Engagement"),"Flag","OK")) -> OK | N64: =IF(OR(Cleaned_Data[[#This Row],[Review]]="",Cleaned_Data[[#This Row],[Rating]]=""),"Missing",IF(AND(Cleaned_Data[[#This Row],[Engagement]]="Strong Engagement",Cleaned_Data[[#This Row],[Rating Category]]="Average"),"Flag","OK")) -> OK | O64: =IF(OR(Cleaned_Data[[#This Row],[Review]]="",Cleaned_Data[[#This Row],[Rating]]=""),"Missing",IF(AND(Cleaned_Data[[#This Row],[Engagement]]="Strong Engagement",Cleaned_Data[[#This Row],[Rating Category]]="Excellent"),"Flag","OK")) -> OK | P64: =IF(Cleaned_Data[[#This Row],[Rating]]="","Missing Rating","Has Rating") -> Has Rating | Q64: =IFERROR( (Cleaned_Data[[#This Row],[Old Price]]-Cleaned_Data[[#This Row],[Current Price]])/Cleaned_Data[[#This Row],[Old Price]], "" ) -> 0.49026346 | R64: =IF( Cleaned_Data[[#This Row],[Discount]] - Cleaned_Data[[#This Row],[Calculated Discount]]>2%, "Check", "OK" ) -> OK | S64: =IF(OR(Cleaned_Data[[#This Row],[Rating]]<0,Cleaned_Data[[#This Row],[Rating]]>5),"Check rating","OK") -> OK | T64: =IF(OR(Cleaned_Data[[#This Row],[Discount]]<0,Cleaned_Data[[#This Row],[Discount]]>1),"Check discount","OK") -> OK | U64: =IF(Cleaned_Data[[#This Row],[Current Price]]>Cleaned_Data[[#This Row],[Old Price]],"Check prices","OK") -> OK
A65: Intelligent LED Body Sensor Wireless Lighting Night Light USB | B65: 325 | C65: 680 | D65: 0.52 | E65: 15 | F65: 2.7 | G65: =Cleaned_Data[[#This Row],[Old Price]]-Cleaned_Data[[#This Row],[Current Price]] -> 355 | H65: =IF(Cleaned_Data[[#This Row],[Rating]]="","Missing",IF(Cleaned_Data[[#This Row],[Rating]]<3,"Poor",IF(Cleaned_Data[[#This Row],[Rating]]<=4.5,"Average","Excellent"))) -> Poor | I65: =IF( Cleaned_Data[[#This Row],[Discount]]="", "Missing", IF( Cleaned_Data[[#This Row],[Discount]]<20%, "Low Discount", IF( Cleaned_Data[[#This Row],[Discount]]<=40%, "Medium Discount", "High Discount" ) ) ) -> High Discount | J65: =IF( Cleaned_Data[[#This Row],[Current Price]]="", "Missing", IF( Cleaned_Data[[#This Row],[Current Price]]<=Analysis!$B$3, "Low Price", IF( Cleaned_Data[[#This Row],[Current Price]]<=Analysis!$B$4, "Medium Price", "High Price" ) ) ) -> Low Price | K65: =IF(Cleaned_Data[[#This Row],[Review]]="","Missing",IF(Cleaned_Data[[#This Row],[Review]]>=Engagement_Threshold,"Strong Engagement","Weak Engagement")) -> Strong Engagement | L65: =IF(OR(Cleaned_Data[[#This Row],[Discount]]="",Cleaned_Data[[#This Row],[Rating]]=""),"Missing",IF(AND(Cleaned_Data[[#This Row],[Discount Category]]="High Discount",Cleaned_Data[[#This Row],[Rating Category]]="Poor"),"Flag","OK")) -> Flag | M65: =IF(OR(Cleaned_Data[[#This Row],[Discount]]="",Cleaned_Data[[#This Row],[Review]]=""),"Missing",IF(AND(Cleaned_Data[[#This Row],[Discount Category]]="High Discount",Cleaned_Data[[#This Row],[Engagement]]="Weak Engagement"),"Flag","OK")) -> OK | N65: =IF(OR(Cleaned_Data[[#This Row],[Review]]="",Cleaned_Data[[#This Row],[Rating]]=""),"Missing",IF(AND(Cleaned_Data[[#This Row],[Engagement]]="Strong Engagement",Cleaned_Data[[#This Row],[Rating Category]]="Average"),"Flag","OK")) -> OK | O65: =IF(OR(Cleaned_Data[[#This Row],[Review]]="",Cleaned_Data[[#This Row],[Rating]]=""),"Missing",IF(AND(Cleaned_Data[[#This Row],[Engagement]]="Strong Engagement",Cleaned_Data[[#This Row],[Rating Category]]="Excellent"),"Flag","OK")) -> OK | P65: =IF(Cleaned_Data[[#This Row],[Rating]]="","Missing Rating","Has Rating") -> Has Rating | Q65: =IFERROR( (Cleaned_Data[[#This Row],[Old Price]]-Cleaned_Data[[#This Row],[Current Price]])/Cleaned_Data[[#This Row],[Old Price]], "" ) -> 0.52205882 | R65: =IF( Cleaned_Data[[#This Row],[Discount]] - Cleaned_Data[[#This Row],[Calculated Discount]]>2%, "Check", "OK" ) -> OK | S65: =IF(OR(Cleaned_Data[[#This Row],[Rating]]<0,Cleaned_Data[[#This Row],[Rating]]>5),"Check rating","OK") -> OK | T65: =IF(OR(Cleaned_Data[[#This Row],[Discount]]<0,Cleaned_Data[[#This Row],[Discount]]>1),"Check discount","OK") -> OK | U65: =IF(Cleaned_Data[[#This Row],[Current Price]]>Cleaned_Data[[#This Row],[Old Price]],"Check prices","OK") -> OK
A66: VIC Wireless Vacuum Cleaner Dual Use For Home And Car 120W High Power Powerful | B66: 1220 | C66: 1555 | D66: 0.22 | E66: 16 | F66: 2.9 | G66: =Cleaned_Data[[#This Row],[Old Price]]-Cleaned_Data[[#This Row],[Current Price]] -> 335 | H66: =IF(Cleaned_Data[[#This Row],[Rating]]="","Missing",IF(Cleaned_Data[[#This Row],[Rating]]<3,"Poor",IF(Cleaned_Data[[#This Row],[Rating]]<=4.5,"Average","Excellent"))) -> Poor | I66: =IF( Cleaned_Data[[#This Row],[Discount]]="", "Missing", IF( Cleaned_Data[[#This Row],[Discount]]<20%, "Low Discount", IF( Cleaned_Data[[#This Row],[Discount]]<=40%, "Medium Discount", "High Discount" ) ) ) -> Medium Discount | J66: =IF( Cleaned_Data[[#This Row],[Current Price]]="", "Missing", IF( Cleaned_Data[[#This Row],[Current Price]]<=Analysis!$B$3, "Low Price", IF( Cleaned_Data[[#This Row],[Current Price]]<=Analysis!$B$4, "Medium Price", "High Price" ) ) ) -> Medium Price | K66: =IF(Cleaned_Data[[#This Row],[Review]]="","Missing",IF(Cleaned_Data[[#This Row],[Review]]>=Engagement_Threshold,"Strong Engagement","Weak Engagement")) -> Strong Engagement | L66: =IF(OR(Cleaned_Data[[#This Row],[Discount]]="",Cleaned_Data[[#This Row],[Rating]]=""),"Missing",IF(AND(Cleaned_Data[[#This Row],[Discount Category]]="High Discount",Cleaned_Data[[#This Row],[Rating Category]]="Poor"),"Flag","OK")) -> OK | M66: =IF(OR(Cleaned_Data[[#This Row],[Discount]]="",Cleaned_Data[[#This Row],[Review]]=""),"Missing",IF(AND(Cleaned_Data[[#This Row],[Discount Category]]="High Discount",Cleaned_Data[[#This Row],[Engagement]]="Weak Engagement"),"Flag","OK")) -> OK | N66: =IF(OR(Cleaned_Data[[#This Row],[Review]]="",Cleaned_Data[[#This Row],[Rating]]=""),"Missing",IF(AND(Cleaned_Data[[#This Row],[Engagement]]="Strong Engagement",Cleaned_Data[[#This Row],[Rating Category]]="Average"),"Flag","OK")) -> OK | O66: =IF(OR(Cleaned_Data[[#This Row],[Review]]="",Cleaned_Data[[#This Row],[Rating]]=""),"Missing",IF(AND(Cleaned_Data[[#This Row],[Engagement]]="Strong Engagement",Cleaned_Data[[#This Row],[Rating Category]]="Excellent"),"Flag","OK")) -> OK | P66: =IF(Cleaned_Data[[#This Row],[Rating]]="","Missing Rating","Has Rating") -> Has Rating | Q66: =IFERROR( (Cleaned_Data[[#This Row],[Old Price]]-Cleaned_Data[[#This Row],[Current Price]])/Cleaned_Data[[#This Row],[Old Price]], "" ) -> 0.21543408 | R66: =IF( Cleaned_Data[[#This Row],[Discount]] - Cleaned_Data[[#This Row],[Calculated Discount]]>2%, "Check", "OK" ) -> OK | S66: =IF(OR(Cleaned_Data[[#This Row],[Rating]]<0,Cleaned_Data[[#This Row],[Rating]]>5),"Check rating","OK") -> OK | T66: =IF(OR(Cleaned_Data[[#This Row],[Discount]]<0,Cleaned_Data[[#This Row],[Discount]]>1),"Check discount","OK") -> OK | U66: =IF(Cleaned_Data[[#This Row],[Current Price]]>Cleaned_Data[[#This Row],[Old Price]],"Check prices","OK") -> OK
A67: Artificial Potted Flowers Room Decorative Flowers (2 Pieces) | B67: 990 | C67: 1814 | D67: 0.45 | E67: 6 | F67: 2.2 | G67: =Cleaned_Data[[#This Row],[Old Price]]-Cleaned_Data[[#This Row],[Current Price]] -> 824 | H67: =IF(Cleaned_Data[[#This Row],[Rating]]="","Missing",IF(Cleaned_Data[[#This Row],[Rating]]<3,"Poor",IF(Cleaned_Data[[#This Row],[Rating]]<=4.5,"Average","Excellent"))) -> Poor | I67: =IF( Cleaned_Data[[#This Row],[Discount]]="", "Missing", IF( Cleaned_Data[[#This Row],[Discount]]<20%, "Low Discount", IF( Cleaned_Data[[#This Row],[Discount]]<=40%, "Medium Discount", "High Discount" ) ) ) -> High Discount | J67: =IF( Cleaned_Data[[#This Row],[Current Price]]="", "Missing", IF( Cleaned_Data[[#This Row],[Current Price]]<=Analysis!$B$3, "Low Price", IF( Cleaned_Data[[#This Row],[Current Price]]<=Analysis!$B$4, "Medium Price", "High Price" ) ) ) -> Medium Price | K67: =IF(Cleaned_Data[[#This Row],[Review]]="","Missing",IF(Cleaned_Data[[#This Row],[Review]]>=Engagement_Threshold,"Strong Engagement","Weak Engagement")) -> Weak Engagement | L67: =IF(OR(Cleaned_Data[[#This Row],[Discount]]="",Cleaned_Data[[#This Row],[Rating]]=""),"Missing",IF(AND(Cleaned_Data[[#This Row],[Discount Category]]="High Discount",Cleaned_Data[[#This Row],[Rating Category]]="Poor"),"Flag","OK")) -> Flag | M67: =IF(OR(Cleaned_Data[[#This Row],[Discount]]="",Cleaned_Data[[#This Row],[Review]]=""),"Missing",IF(AND(Cleaned_Data[[#This Row],[Discount Category]]="High Discount",Cleaned_Data[[#This Row],[Engagement]]="Weak Engagement"),"Flag","OK")) -> Flag | N67: =IF(OR(Cleaned_Data[[#This Row],[Review]]="",Cleaned_Data[[#This Row],[Rating]]=""),"Missing",IF(AND(Cleaned_Data[[#This Row],[Engagement]]="Strong Engagement",Cleaned_Data[[#This Row],[Rating Category]]="Average"),"Flag","OK")) -> OK | O67: =IF(OR(Cleaned_Data[[#This Row],[Review]]="",Cleaned_Data[[#This Row],[Rating]]=""),"Missing",IF(AND(Cleaned_Data[[#This Row],[Engagement]]="Strong Engagement",Cleaned_Data[[#This Row],[Rating Category]]="Excellent"),"Flag","OK")) -> OK | P67: =IF(Cleaned_Data[[#This Row],[Rating]]="","Missing Rating","Has Rating") -> Has Rating | Q67: =IFERROR( (Cleaned_Data[[#This Row],[Old Price]]-Cleaned_Data[[#This Row],[Current Price]])/Cleaned_Data[[#This Row],[Old Price]], "" ) -> 0.45424476 | R67: =IF( Cleaned_Data[[#This Row],[Discount]] - Cleaned_Data[[#This Row],[Calculated Discount]]>2%, "Check", "OK" ) -> OK | S67: =IF(OR(Cleaned_Data[[#This Row],[Rating]]<0,Cleaned_Data[[#This Row],[Rating]]>5),"Check rating","OK") -> OK | T67: =IF(OR(Cleaned_Data[[#This Row],[Discount]]<0,Cleaned_Data[[#This Row],[Discount]]>1),"Check discount","OK") -> OK | U67: =IF(Cleaned_Data[[#This Row],[Current Price]]>Cleaned_Data[[#This Row],[Old Price]],"Check prices","OK") -> OK
A68: 380ML USB Rechargeable Portable Small Blenders And Juicers | B68: 1000 | C68: 2000 | D68: 0.5 | E68: 7 | F68: 2.3 | G68: =Cleaned_Data[[#This Row],[Old Price]]-Cleaned_Data[[#This Row],[Current Price]] -> 1000 | H68: =IF(Cleaned_Data[[#This Row],[Rating]]="","Missing",IF(Cleaned_Data[[#This Row],[Rating]]<3,"Poor",IF(Cleaned_Data[[#This Row],[Rating]]<=4.5,"Average","Excellent"))) -> Poor | I68: =IF( Cleaned_Data[[#This Row],[Discount]]="", "Missing", IF( Cleaned_Data[[#This Row],[Discount]]<20%, "Low Discount", IF( Cleaned_Data[[#This Row],[Discount]]<=40%, "Medium Discount", "High Discount" ) ) ) -> High Discount | J68: =IF( Cleaned_Data[[#This Row],[Current Price]]="", "Missing", IF( Cleaned_Data[[#This Row],[Current Price]]<=Analysis!$B$3, "Low Price", IF( Cleaned_Data[[#This Row],[Current Price]]<=Analysis!$B$4, "Medium Price", "High Price" ) ) ) -> Medium Price | K68: =IF(Cleaned_Data[[#This Row],[Review]]="","Missing",IF(Cleaned_Data[[#This Row],[Review]]>=Engagement_Threshold,"Strong Engagement","Weak Engagement")) -> Weak Engagement | L68: =IF(OR(Cleaned_Data[[#This Row],[Discount]]="",Cleaned_Data[[#This Row],[Rating]]=""),"Missing",IF(AND(Cleaned_Data[[#This Row],[Discount Category]]="High Discount",Cleaned_Data[[#This Row],[Rating Category]]="Poor"),"Flag","OK")) -> Flag | M68: =IF(OR(Cleaned_Data[[#This Row],[Discount]]="",Cleaned_Data[[#This Row],[Review]]=""),"Missing",IF(AND(Cleaned_Data[[#This Row],[Discount Category]]="High Discount",Cleaned_Data[[#This Row],[Engagement]]="Weak Engagement"),"Flag","OK")) -> Flag | N68: =IF(OR(Cleaned_Data[[#This Row],[Review]]="",Cleaned_Data[[#This Row],[Rating]]=""),"Missing",IF(AND(Cleaned_Data[[#This Row],[Engagement]]="Strong Engagement",Cleaned_Data[[#This Row],[Rating Category]]="Average"),"Flag","OK")) -> OK | O68: =IF(OR(Cleaned_Data[[#This Row],[Review]]="",Cleaned_Data[[#This Row],[Rating]]=""),"Missing",IF(AND(Cleaned_Data[[#This Row],[Engagement]]="Strong Engagement",Cleaned_Data[[#This Row],[Rating Category]]="Excellent"),"Flag","OK")) -> OK | P68: =IF(Cleaned_Data[[#This Row],[Rating]]="","Missing Rating","Has Rating") -> Has Rating | Q68: =IFERROR( (Cleaned_Data[[#This Row],[Old Price]]-Cleaned_Data[[#This Row],[Current Price]])/Cleaned_Data[[#This Row],[Old Price]], "" ) -> 0.5 | R68: =IF( Cleaned_Data[[#This Row],[Discount]] - Cleaned_Data[[#This Row],[Calculated Discount]]>2%, "Check", "OK" ) -> OK | S68: =IF(OR(Cleaned_Data[[#This Row],[Rating]]<0,Cleaned_Data[[#This Row],[Rating]]>5),"Check rating","OK") -> OK | T68: =IF(OR(Cleaned_Data[[#This Row],[Discount]]<0,Cleaned_Data[[#This Row],[Discount]]>1),"Check discount","OK") -> OK | U68: =IF(Cleaned_Data[[#This Row],[Current Price]]>Cleaned_Data[[#This Row],[Old Price]],"Check prices","OK") -> OK
A69: 32PCS Portable Cordless Drill Set With Cyclic Battery Drive -26 Variable Speed | B69: 3750 | C69: 6143 | D69: 0.39 | E69: 5 | F69: 3 | G69: =Cleaned_Data[[#This Row],[Old Price]]-Cleaned_Data[[#This Row],[Current Price]] -> 2393 | H69: =IF(Cleaned_Data[[#This Row],[Rating]]="","Missing",IF(Cleaned_Data[[#This Row],[Rating]]<3,"Poor",IF(Cleaned_Data[[#This Row],[Rating]]<=4.5,"Average","Excellent"))) -> Average | I69: =IF( Cleaned_Data[[#This Row],[Discount]]="", "Missing", IF( Cleaned_Data[[#This Row],[Discount]]<20%, "Low Discount", IF( Cleaned_Data[[#This Row],[Discount]]<=40%, "Medium Discount", "High Discount" ) ) ) -> Medium Discount | J69: =IF( Cleaned_Data[[#This Row],[Current Price]]="", "Missing", IF( Cleaned_Data[[#This Row],[Current Price]]<=Analysis!$B$3, "Low Price", IF( Cleaned_Data[[#This Row],[Current Price]]<=Analysis!$B$4, "Medium Price", "High Price" ) ) ) -> High Price | K69: =IF(Cleaned_Data[[#This Row],[Review]]="","Missing",IF(Cleaned_Data[[#This Row],[Review]]>=Engagement_Threshold,"Strong Engagement","Weak Engagement")) -> Weak Engagement | L69: =IF(OR(Cleaned_Data[[#This Row],[Discount]]="",Cleaned_Data[[#This Row],[Rating]]=""),"Missing",IF(AND(Cleaned_Data[[#This Row],[Discount Category]]="High Discount",Cleaned_Data[[#This Row],[Rating Category]]="Poor"),"Flag","OK")) -> OK | M69: =IF(OR(Cleaned_Data[[#This Row],[Discount]]="",Cleaned_Data[[#This Row],[Review]]=""),"Missing",IF(AND(Cleaned_Data[[#This Row],[Discount Category]]="High Discount",Cleaned_Data[[#This Row],[Engagement]]="Weak Engagement"),"Flag","OK")) -> OK | N69: =IF(OR(Cleaned_Data[[#This Row],[Review]]="",Cleaned_Data[[#This Row],[Rating]]=""),"Missing",IF(AND(Cleaned_Data[[#This Row],[Engagement]]="Strong Engagement",Cleaned_Data[[#This Row],[Rating Category]]="Average"),"Flag","OK")) -> OK | O69: =IF(OR(Cleaned_Data[[#This Row],[Review]]="",Cleaned_Data[[#This Row],[Rating]]=""),"Missing",IF(AND(Cleaned_Data[[#This Row],[Engagement]]="Strong Engagement",Cleaned_Data[[#This Row],[Rating Category]]="Excellent"),"Flag","OK")) -> OK | P69: =IF(Cleaned_Data[[#This Row],[Rating]]="","Missing Rating","Has Rating") -> Has Rating | Q69: =IFERROR( (Cleaned_Data[[#This Row],[Old Price]]-Cleaned_Data[[#This Row],[Current Price]])/Cleaned_Data[[#This Row],[Old Price]], "" ) -> 0.38954908 | R69: =IF( Cleaned_Data[[#This Row],[Discount]] - Cleaned_Data[[#This Row],[Calculated Discount]]>2%, "Check", "OK" ) -> OK | S69: =IF(OR(Cleaned_Data[[#This Row],[Rating]]<0,Cleaned_Data[[#This Row],[Rating]]>5),"Check rating","OK") -> OK | T69: =IF(OR(Cleaned_Data[[#This Row],[Discount]]<0,Cleaned_Data[[#This Row],[Discount]]>1),"Check discount","OK") -> OK | U69: =IF(Cleaned_Data[[#This Row],[Current Price]]>Cleaned_Data[[#This Row],[Old Price]],"Check prices","OK") -> OK
A70: Agapeon Toothbrush Holder And Toothpaste Dispenser | B70: 382 | C70: 700 | D70: 0.45 | E70: 17 | F70: 2.6 | G70: =Cleaned_Data[[#This Row],[Old Price]]-Cleaned_Data[[#This Row],[Current Price]] -> 318 | H70: =IF(Cleaned_Data[[#This Row],[Rating]]="","Missing",IF(Cleaned_Data[[#This Row],[Rating]]<3,"Poor",IF(Cleaned_Data[[#This Row],[Rating]]<=4.5,"Average","Excellent"))) -> Poor | I70: =IF( Cleaned_Data[[#This Row],[Discount]]="", "Missing", IF( Cleaned_Data[[#This Row],[Discount]]<20%, "Low Discount", IF( Cleaned_Data[[#This Row],[Discount]]<=40%, "Medium Discount", "High Discount" ) ) ) -> High Discount | J70: =IF( Cleaned_Data[[#This Row],[Current Price]]="", "Missing", IF( Cleaned_Data[[#This Row],[Current Price]]<=Analysis!$B$3, "Low Price", IF( Cleaned_Data[[#This Row],[Current Price]]<=Analysis!$B$4, "Medium Price", "High Price" ) ) ) -> Low Price | K70: =IF(Cleaned_Data[[#This Row],[Review]]="","Missing",IF(Cleaned_Data[[#This Row],[Review]]>=Engagement_Threshold,"Strong Engagement","Weak Engagement")) -> Strong Engagement | L70: =IF(OR(Cleaned_Data[[#This Row],[Discount]]="",Cleaned_Data[[#This Row],[Rating]]=""),"Missing",IF(AND(Cleaned_Data[[#This Row],[Discount Category]]="High Discount",Cleaned_Data[[#This Row],[Rating Category]]="Poor"),"Flag","OK")) -> Flag | M70: =IF(OR(Cleaned_Data[[#This Row],[Discount]]="",Cleaned_Data[[#This Row],[Review]]=""),"Missing",IF(AND(Cleaned_Data[[#This Row],[Discount Category]]="High Discount",Cleaned_Data[[#This Row],[Engagement]]="Weak Engagement"),"Flag","OK")) -> OK | N70: =IF(OR(Cleaned_Data[[#This Row],[Review]]="",Cleaned_Data[[#This Row],[Rating]]=""),"Missing",IF(AND(Cleaned_Data[[#This Row],[Engagement]]="Strong Engagement",Cleaned_Data[[#This Row],[Rating Category]]="Average"),"Flag","OK")) -> OK | O70: =IF(OR(Cleaned_Data[[#This Row],[Review]]="",Cleaned_Data[[#This Row],[Rating]]=""),"Missing",IF(AND(Cleaned_Data[[#This Row],[Engagement]]="Strong Engagement",Cleaned_Data[[#This Row],[Rating Category]]="Excellent"),"Flag","OK")) -> OK | P70: =IF(Cleaned_Data[[#This Row],[Rating]]="","Missing Rating","Has Rating") -> Has Rating | Q70: =IFERROR( (Cleaned_Data[[#This Row],[Old Price]]-Cleaned_Data[[#This Row],[Current Price]])/Cleaned_Data[[#This Row],[Old Price]], "" ) -> 0.45428571 | R70: =IF( Cleaned_Data[[#This Row],[Discount]] - Cleaned_Data[[#This Row],[Calculated Discount]]>2%, "Check", "OK" ) -> OK | S70: =IF(OR(Cleaned_Data[[#This Row],[Rating]]<0,Cleaned_Data[[#This Row],[Rating]]>5),"Check rating","OK") -> OK | T70: =IF(OR(Cleaned_Data[[#This Row],[Discount]]<0,Cleaned_Data[[#This Row],[Discount]]>1),"Check discount","OK") -> OK | U70: =IF(Cleaned_Data[[#This Row],[Current Price]]>Cleaned_Data[[#This Row],[Old Price]],"Check prices","OK") -> OK
A71: Large Lazy Inflatable Sofa Chairs PVC Lounger Seat Bag | B71: 2300 | C71: 3240 | D71: 0.29 | E71: 5 | F71: 3 | G71: =Cleaned_Data[[#This Row],[Old Price]]-Cleaned_Data[[#This Row],[Current Price]] -> 940 | H71: =IF(Cleaned_Data[[#This Row],[Rating]]="","Missing",IF(Cleaned_Data[[#This Row],[Rating]]<3,"Poor",IF(Cleaned_Data[[#This Row],[Rating]]<=4.5,"Average","Excellent"))) -> Average | I71: =IF( Cleaned_Data[[#This Row],[Discount]]="", "Missing", IF( Cleaned_Data[[#This Row],[Discount]]<20%, "Low Discount", IF( Cleaned_Data[[#This Row],[Discount]]<=40%, "Medium Discount", "High Discount" ) ) ) -> Medium Discount | J71: =IF( Cleaned_Data[[#This Row],[Current Price]]="", "Missing", IF( Cleaned_Data[[#This Row],[Current Price]]<=Analysis!$B$3, "Low Price", IF( Cleaned_Data[[#This Row],[Current Price]]<=Analysis!$B$4, "Medium Price", "High Price" ) ) ) -> High Price | K71: =IF(Cleaned_Data[[#This Row],[Review]]="","Missing",IF(Cleaned_Data[[#This Row],[Review]]>=Engagement_Threshold,"Strong Engagement","Weak Engagement")) -> Weak Engagement | L71: =IF(OR(Cleaned_Data[[#This Row],[Discount]]="",Cleaned_Data[[#This Row],[Rating]]=""),"Missing",IF(AND(Cleaned_Data[[#This Row],[Discount Category]]="High Discount",Cleaned_Data[[#This Row],[Rating Category]]="Poor"),"Flag","OK")) -> OK | M71: =IF(OR(Cleaned_Data[[#This Row],[Discount]]="",Cleaned_Data[[#This Row],[Review]]=""),"Missing",IF(AND(Cleaned_Data[[#This Row],[Discount Category]]="High Discount",Cleaned_Data[[#This Row],[Engagement]]="Weak Engagement"),"Flag","OK")) -> OK | N71: =IF(OR(Cleaned_Data[[#This Row],[Review]]="",Cleaned_Data[[#This Row],[Rating]]=""),"Missing",IF(AND(Cleaned_Data[[#This Row],[Engagement]]="Strong Engagement",Cleaned_Data[[#This Row],[Rating Category]]="Average"),"Flag","OK")) -> OK | O71: =IF(OR(Cleaned_Data[[#This Row],[Review]]="",Cleaned_Data[[#This Row],[Rating]]=""),"Missing",IF(AND(Cleaned_Data[[#This Row],[Engagement]]="Strong Engagement",Cleaned_Data[[#This Row],[Rating Category]]="Excellent"),"Flag","OK")) -> OK | P71: =IF(Cleaned_Data[[#This Row],[Rating]]="","Missing Rating","Has Rating") -> Has Rating | Q71: =IFERROR( (Cleaned_Data[[#This Row],[Old Price]]-Cleaned_Data[[#This Row],[Current Price]])/Cleaned_Data[[#This Row],[Old Price]], "" ) -> 0.29012346 | R71: =IF( Cleaned_Data[[#This Row],[Discount]] - Cleaned_Data[[#This Row],[Calculated Discount]]>2%, "Check", "OK" ) -> OK | S71: =IF(OR(Cleaned_Data[[#This Row],[Rating]]<0,Cleaned_Data[[#This Row],[Rating]]>5),"Check rating","OK") -> OK | T71: =IF(OR(Cleaned_Data[[#This Row],[Discount]]<0,Cleaned_Data[[#This Row],[Discount]]>1),"Check discount","OK") -> OK | U71: =IF(Cleaned_Data[[#This Row],[Current Price]]>Cleaned_Data[[#This Row],[Old Price]],"Check prices","OK") -> OK
A72: Watercolour Gold Foil Textured Print Pillow Cover | B72: 345 | C72: 602 | D72: 0.43 | E72: 6 | F72: 2.3 | G72: =Cleaned_Data[[#This Row],[Old Price]]-Cleaned_Data[[#This Row],[Current Price]] -> 257 | H72: =IF(Cleaned_Data[[#This Row],[Rating]]="","Missing",IF(Cleaned_Data[[#This Row],[Rating]]<3,"Poor",IF(Cleaned_Data[[#This Row],[Rating]]<=4.5,"Average","Excellent"))) -> Poor | I72: =IF( Cleaned_Data[[#This Row],[Discount]]="", "Missing", IF( Cleaned_Data[[#This Row],[Discount]]<20%, "Low Discount", IF( Cleaned_Data[[#This Row],[Discount]]<=40%, "Medium Discount", "High Discount" ) ) ) -> High Discount | J72: =IF( Cleaned_Data[[#This Row],[Current Price]]="", "Missing", IF( Cleaned_Data[[#This Row],[Current Price]]<=Analysis!$B$3, "Low Price", IF( Cleaned_Data[[#This Row],[Current Price]]<=Analysis!$B$4, "Medium Price", "High Price" ) ) ) -> Low Price | K72: =IF(Cleaned_Data[[#This Row],[Review]]="","Missing",IF(Cleaned_Data[[#This Row],[Review]]>=Engagement_Threshold,"Strong Engagement","Weak Engagement")) -> Weak Engagement | L72: =IF(OR(Cleaned_Data[[#This Row],[Discount]]="",Cleaned_Data[[#This Row],[Rating]]=""),"Missing",IF(AND(Cleaned_Data[[#This Row],[Discount Category]]="High Discount",Cleaned_Data[[#This Row],[Rating Category]]="Poor"),"Flag","OK")) -> Flag | M72: =IF(OR(Cleaned_Data[[#This Row],[Discount]]="",Cleaned_Data[[#This Row],[Review]]=""),"Missing",IF(AND(Cleaned_Data[[#This Row],[Discount Category]]="High Discount",Cleaned_Data[[#This Row],[Engagement]]="Weak Engagement"),"Flag","OK")) -> Flag | N72: =IF(OR(Cleaned_Data[[#This Row],[Review]]="",Cleaned_Data[[#This Row],[Rating]]=""),"Missing",IF(AND(Cleaned_Data[[#This Row],[Engagement]]="Strong Engagement",Cleaned_Data[[#This Row],[Rating Category]]="Average"),"Flag","OK")) -> OK | O72: =IF(OR(Cleaned_Data[[#This Row],[Review]]="",Cleaned_Data[[#This Row],[Rating]]=""),"Missing",IF(AND(Cleaned_Data[[#This Row],[Engagement]]="Strong Engagement",Cleaned_Data[[#This Row],[Rating Category]]="Excellent"),"Flag","OK")) -> OK | P72: =IF(Cleaned_Data[[#This Row],[Rating]]="","Missing Rating","Has Rating") -> Has Rating | Q72: =IFERROR( (Cleaned_Data[[#This Row],[Old Price]]-Cleaned_Data[[#This Row],[Current Price]])/Cleaned_Data[[#This Row],[Old Price]], "" ) -> 0.4269103 | R72: =IF( Cleaned_Data[[#This Row],[Discount]] - Cleaned_Data[[#This Row],[Calculated Discount]]>2%, "Check", "OK" ) -> OK | S72: =IF(OR(Cleaned_Data[[#This Row],[Rating]]<0,Cleaned_Data[[#This Row],[Rating]]>5),"Check rating","OK") -> OK | T72: =IF(OR(Cleaned_Data[[#This Row],[Discount]]<0,Cleaned_Data[[#This Row],[Discount]]>1),"Check discount","OK") -> OK | U72: =IF(Cleaned_Data[[#This Row],[Current Price]]>Cleaned_Data[[#This Row],[Old Price]],"Check prices","OK") -> OK
... A75: Electric LED UV Mosquito Killer Lamp, Outdoor/Indoor Fly Killer Trap Light -USB | B75: 1570 | C75: 2988 | D75: 0.47 | E75: 7 | F75: 2.1 | G75: =Cleaned_Data[[#This Row],[Old Price]]-Cleaned_Data[[#This Row],[Current Price]] -> 1418 | H75: =IF(Cleaned_Data[[#This Row],[Rating]]="","Missing",IF(Cleaned_Data[[#This Row],[Rating]]<3,"Poor",IF(Cleaned_Data[[#This Row],[Rating]]<=4.5,"Average","Excellent"))) -> Poor | I75: =IF( Cleaned_Data[[#This Row],[Discount]]="", "Missing", IF( Cleaned_Data[[#This Row],[Discount]]<20%, "Low Discount", IF( Cleaned_Data[[#This Row],[Discount]]<=40%, "Medium Discount", "High Discount" ) ) ) -> High Discount | J75: =IF( Cleaned_Data[[#This Row],[Current Price]]="", "Missing", IF( Cleaned_Data[[#This Row],[Current Price]]<=Analysis!$B$3, "Low Price", IF( Cleaned_Data[[#This Row],[Current Price]]<=Analysis!$B$4, "Medium Price", "High Price" ) ) ) -> Medium Price | K75: =IF(Cleaned_Data[[#This Row],[Review]]="","Missing",IF(Cleaned_Data[[#This Row],[Review]]>=Engagement_Threshold,"Strong Engagement","Weak Engagement")) -> Weak Engagement | L75: =IF(OR(Cleaned_Data[[#This Row],[Discount]]="",Cleaned_Data[[#This Row],[Rating]]=""),"Missing",IF(AND(Cleaned_Data[[#This Row],[Discount Category]]="High Discount",Cleaned_Data[[#This Row],[Rating Category]]="Poor"),"Flag","OK")) -> Flag | M75: =IF(OR(Cleaned_Data[[#This Row],[Discount]]="",Cleaned_Data[[#This Row],[Review]]=""),"Missing",IF(AND(Cleaned_Data[[#This Row],[Discount Category]]="High Discount",Cleaned_Data[[#This Row],[Engagement]]="Weak Engagement"),"Flag","OK")) -> Flag | N75: =IF(OR(Cleaned_Data[[#This Row],[Review]]="",Cleaned_Data[[#This Row],[Rating]]=""),"Missing",IF(AND(Cleaned_Data[[#This Row],[Engagement]]="Strong Engagement",Cleaned_Data[[#This Row],[Rating Category]]="Average"),"Flag","OK")) -> OK | O75: =IF(OR(Cleaned_Data[[#This Row],[Review]]="",Cleaned_Data[[#This Row],[Rating]]=""),"Missing",IF(AND(Cleaned_Data[[#This Row],[Engagement]]="Strong Engagement",Cleaned_Data[[#This Row],[Rating Category]]="Excellent"),"Flag","OK")) -> OK | P75: =IF(Cleaned_Data[[#This Row],[Rating]]="","Missing Rating","Has Rating") -> Has Rating | Q75: =IFERROR( (Cleaned_Data[[#This Row],[Old Price]]-Cleaned_Data[[#This Row],[Current Price]])/Cleaned_Data[[#This Row],[Old Price]], "" ) -> 0.47456493 | R75: =IF( Cleaned_Data[[#This Row],[Discount]] - Cleaned_Data[[#This Row],[Calculated Discount]]>2%, "Check", "OK" ) -> OK | S75: =IF(OR(Cleaned_Data[[#This Row],[Rating]]<0,Cleaned_Data[[#This Row],[Rating]]>5),"Check rating","OK") -> OK | T75: =IF(OR(Cleaned_Data[[#This Row],[Discount]]<0,Cleaned_Data[[#This Row],[Discount]]>1),"Check discount","OK") -> OK | U75: =IF(Cleaned_Data[[#This Row],[Current Price]]>Cleaned_Data[[#This Row],[Old Price]],"Check prices","OK") -> OK
A76: 2PCS/LOT Solar LED Outdoor Intelligent Light Controlled Wall Lamp | B76: 790 | C76: 1485 | D76: 0.47 | G76: =Cleaned_Data[[#This Row],[Old Price]]-Cleaned_Data[[#This Row],[Current Price]] -> 695 | H76: =IF(Cleaned_Data[[#This Row],[Rating]]="","Missing",IF(Cleaned_Data[[#This Row],[Rating]]<3,"Poor",IF(Cleaned_Data[[#This Row],[Rating]]<=4.5,"Average","Excellent"))) -> Missing | I76: =IF( Cleaned_Data[[#This Row],[Discount]]="", "Missing", IF( Cleaned_Data[[#This Row],[Discount]]<20%, "Low Discount", IF( Cleaned_Data[[#This Row],[Discount]]<=40%, "Medium Discount", "High Discount" ) ) ) -> High Discount | J76: =IF( Cleaned_Data[[#This Row],[Current Price]]="", "Missing", IF( Cleaned_Data[[#This Row],[Current Price]]<=Analysis!$B$3, "Low Price", IF( Cleaned_Data[[#This Row],[Current Price]]<=Analysis!$B$4, "Medium Price", "High Price" ) ) ) -> Medium Price | K76: =IF(Cleaned_Data[[#This Row],[Review]]="","Missing",IF(Cleaned_Data[[#This Row],[Review]]>=Engagement_Threshold,"Strong Engagement","Weak Engagement")) -> Missing | L76: =IF(OR(Cleaned_Data[[#This Row],[Discount]]="",Cleaned_Data[[#This Row],[Rating]]=""),"Missing",IF(AND(Cleaned_Data[[#This Row],[Discount Category]]="High Discount",Cleaned_Data[[#This Row],[Rating Category]]="Poor"),"Flag","OK")) -> Missing | M76: =IF(OR(Cleaned_Data[[#This Row],[Discount]]="",Cleaned_Data[[#This Row],[Review]]=""),"Missing",IF(AND(Cleaned_Data[[#This Row],[Discount Category]]="High Discount",Cleaned_Data[[#This Row],[Engagement]]="Weak Engagement"),"Flag","OK")) -> Missing | N76: =IF(OR(Cleaned_Data[[#This Row],[Review]]="",Cleaned_Data[[#This Row],[Rating]]=""),"Missing",IF(AND(Cleaned_Data[[#This Row],[Engagement]]="Strong Engagement",Cleaned_Data[[#This Row],[Rating Category]]="Average"),"Flag","OK")) -> Missing | O76: =IF(OR(Cleaned_Data[[#This Row],[Review]]="",Cleaned_Data[[#This Row],[Rating]]=""),"Missing",IF(AND(Cleaned_Data[[#This Row],[Engagement]]="Strong Engagement",Cleaned_Data[[#This Row],[Rating Category]]="Excellent"),"Flag","OK")) -> Missing | P76: =IF(Cleaned_Data[[#This Row],[Rating]]="","Missing Rating","Has Rating") -> Missing Rating | Q76: =IFERROR( (Cleaned_Data[[#This Row],[Old Price]]-Cleaned_Data[[#This Row],[Current Price]])/Cleaned_Data[[#This Row],[Old Price]], "" ) -> 0.46801347 | R76: =IF( Cleaned_Data[[#This Row],[Discount]] - Cleaned_Data[[#This Row],[Calculated Discount]]>2%, "Check", "OK" ) -> OK | S76: =IF(OR(Cleaned_Data[[#This Row],[Rating]]<0,Cleaned_Data[[#This Row],[Rating]]>5),"Check rating","OK") -> OK | T76: =IF(OR(Cleaned_Data[[#This Row],[Discount]]<0,Cleaned_Data[[#This Row],[Discount]]>1),"Check discount","OK") -> OK | U76: =IF(Cleaned_Data[[#This Row],[Current Price]]>Cleaned_Data[[#This Row],[Old Price]],"Check prices","OK") -> OK
A77: 3PCS Rotary Scraper Thermomix For Kitchen | B77: 690 | C77: 1200 | D77: 0.43 | G77: =Cleaned_Data[[#This Row],[Old Price]]-Cleaned_Data[[#This Row],[Current Price]] -> 510 | H77: =IF(Cleaned_Data[[#This Row],[Rating]]="","Missing",IF(Cleaned_Data[[#This Row],[Rating]]<3,"Poor",IF(Cleaned_Data[[#This Row],[Rating]]<=4.5,"Average","Excellent"))) -> Missing | I77: =IF( Cleaned_Data[[#This Row],[Discount]]="", "Missing", IF( Cleaned_Data[[#This Row],[Discount]]<20%, "Low Discount", IF( Cleaned_Data[[#This Row],[Discount]]<=40%, "Medium Discount", "High Discount" ) ) ) -> High Discount | J77: =IF( Cleaned_Data[[#This Row],[Current Price]]="", "Missing", IF( Cleaned_Data[[#This Row],[Current Price]]<=Analysis!$B$3, "Low Price", IF( Cleaned_Data[[#This Row],[Current Price]]<=Analysis!$B$4, "Medium Price", "High Price" ) ) ) -> Medium Price | K77: =IF(Cleaned_Data[[#This Row],[Review]]="","Missing",IF(Cleaned_Data[[#This Row],[Review]]>=Engagement_Threshold,"Strong Engagement","Weak Engagement")) -> Missing | L77: =IF(OR(Cleaned_Data[[#This Row],[Discount]]="",Cleaned_Data[[#This Row],[Rating]]=""),"Missing",IF(AND(Cleaned_Data[[#This Row],[Discount Category]]="High Discount",Cleaned_Data[[#This Row],[Rating Category]]="Poor"),"Flag","OK")) -> Missing | M77: =IF(OR(Cleaned_Data[[#This Row],[Discount]]="",Cleaned_Data[[#This Row],[Review]]=""),"Missing",IF(AND(Cleaned_Data[[#This Row],[Discount Category]]="High Discount",Cleaned_Data[[#This Row],[Engagement]]="Weak Engagement"),"Flag","OK")) -> Missing | N77: =IF(OR(Cleaned_Data[[#This Row],[Review]]="",Cleaned_Data[[#This Row],[Rating]]=""),"Missing",IF(AND(Cleaned_Data[[#This Row],[Engagement]]="Strong Engagement",Cleaned_Data[[#This Row],[Rating Category]]="Average"),"Flag","OK")) -> Missing | O77: =IF(OR(Cleaned_Data[[#This Row],[Review]]="",Cleaned_Data[[#This Row],[Rating]]=""),"Missing",IF(AND(Cleaned_Data[[#This Row],[Engagement]]="Strong Engagement",Cleaned_Data[[#This Row],[Rating Category]]="Excellent"),"Flag","OK")) -> Missing | P77: =IF(Cleaned_Data[[#This Row],[Rating]]="","Missing Rating","Has Rating") -> Missing Rating | Q77: =IFERROR( (Cleaned_Data[[#This Row],[Old Price]]-Cleaned_Data[[#This Row],[Current Price]])/Cleaned_Data[[#This Row],[Old Price]], "" ) -> 0.425 | R77: =IF( Cleaned_Data[[#This Row],[Discount]] - Cleaned_Data[[#This Row],[Calculated Discount]]>2%, "Check", "OK" ) -> OK | S77: =IF(OR(Cleaned_Data[[#This Row],[Rating]]<0,Cleaned_Data[[#This Row],[Rating]]>5),"Check rating","OK") -> OK | T77: =IF(OR(Cleaned_Data[[#This Row],[Discount]]<0,Cleaned_Data[[#This Row],[Discount]]>1),"Check discount","OK") -> OK | U77: =IF(Cleaned_Data[[#This Row],[Current Price]]>Cleaned_Data[[#This Row],[Old Price]],"Check prices","OK") -> OK
A78: Cushion Silicone Butt Cushion Summer Ice Cushion Honeycomb Gel Cushion | B78: 1732 | C78: 1799 | D78: 0.04 | G78: =Cleaned_Data[[#This Row],[Old Price]]-Cleaned_Data[[#This Row],[Current Price]] -> 67 | H78: =IF(Cleaned_Data[[#This Row],[Rating]]="","Missing",IF(Cleaned_Data[[#This Row],[Rating]]<3,"Poor",IF(Cleaned_Data[[#This Row],[Rating]]<=4.5,"Average","Excellent"))) -> Missing | I78: =IF( Cleaned_Data[[#This Row],[Discount]]="", "Missing", IF( Cleaned_Data[[#This Row],[Discount]]<20%, "Low Discount", IF( Cleaned_Data[[#This Row],[Discount]]<=40%, "Medium Discount", "High Discount" ) ) ) -> Low Discount | J78: =IF( Cleaned_Data[[#This Row],[Current Price]]="", "Missing", IF( Cleaned_Data[[#This Row],[Current Price]]<=Analysis!$B$3, "Low Price", IF( Cleaned_Data[[#This Row],[Current Price]]<=Analysis!$B$4, "Medium Price", "High Price" ) ) ) -> High Price | K78: =IF(Cleaned_Data[[#This Row],[Review]]="","Missing",IF(Cleaned_Data[[#This Row],[Review]]>=Engagement_Threshold,"Strong Engagement","Weak Engagement")) -> Missing | L78: =IF(OR(Cleaned_Data[[#This Row],[Discount]]="",Cleaned_Data[[#This Row],[Rating]]=""),"Missing",IF(AND(Cleaned_Data[[#This Row],[Discount Category]]="High Discount",Cleaned_Data[[#This Row],[Rating Category]]="Poor"),"Flag","OK")) -> Missing | M78: =IF(OR(Cleaned_Data[[#This Row],[Discount]]="",Cleaned_Data[[#This Row],[Review]]=""),"Missing",IF(AND(Cleaned_Data[[#This Row],[Discount Category]]="High Discount",Cleaned_Data[[#This Row],[Engagement]]="Weak Engagement"),"Flag","OK")) -> Missing | N78: =IF(OR(Cleaned_Data[[#This Row],[Review]]="",Cleaned_Data[[#This Row],[Rating]]=""),"Missing",IF(AND(Cleaned_Data[[#This Row],[Engagement]]="Strong Engagement",Cleaned_Data[[#This Row],[Rating Category]]="Average"),"Flag","OK")) -> Missing | O78: =IF(OR(Cleaned_Data[[#This Row],[Review]]="",Cleaned_Data[[#This Row],[Rating]]=""),"Missing",IF(AND(Cleaned_Data[[#This Row],[Engagement]]="Strong Engagement",Cleaned_Data[[#This Row],[Rating Category]]="Excellent"),"Flag","OK")) -> Missing | P78: =IF(Cleaned_Data[[#This Row],[Rating]]="","Missing Rating","Has Rating") -> Missing Rating | Q78: =IFERROR( (Cleaned_Data[[#This Row],[Old Price]]-Cleaned_Data[[#This Row],[Current Price]])/Cleaned_Data[[#This Row],[Old Price]], "" ) -> 0.037242913 | R78: =IF( Cleaned_Data[[#This Row],[Discount]] - Cleaned_Data[[#This Row],[Calculated Discount]]>2%, "Check", "OK" ) -> OK | S78: =IF(OR(Cleaned_Data[[#This Row],[Rating]]<0,Cleaned_Data[[#This Row],[Rating]]>5),"Check rating","OK") -> OK | T78: =IF(OR(Cleaned_Data[[#This Row],[Discount]]<0,Cleaned_Data[[#This Row],[Discount]]>1),"Check discount","OK") -> OK | U78: =IF(Cleaned_Data[[#This Row],[Current Price]]>Cleaned_Data[[#This Row],[Old Price]],"Check prices","OK") -> OK
A79: 7PCS Silicone Thumb Knife Finger Protector Vegetable Harvesting Knife | B79: 230 | C79: 450 | D79: 0.49 | G79: =Cleaned_Data[[#This Row],[Old Price]]-Cleaned_Data[[#This Row],[Current Price]] -> 220 | H79: =IF(Cleaned_Data[[#This Row],[Rating]]="","Missing",IF(Cleaned_Data[[#This Row],[Rating]]<3,"Poor",IF(Cleaned_Data[[#This Row],[Rating]]<=4.5,"Average","Excellent"))) -> Missing | I79: =IF( Cleaned_Data[[#This Row],[Discount]]="", "Missing", IF( Cleaned_Data[[#This Row],[Discount]]<20%, "Low Discount", IF( Cleaned_Data[[#This Row],[Discount]]<=40%, "Medium Discount", "High Discount" ) ) ) -> High Discount | J79: =IF( Cleaned_Data[[#This Row],[Current Price]]="", "Missing", IF( Cleaned_Data[[#This Row],[Current Price]]<=Analysis!$B$3, "Low Price", IF( Cleaned_Data[[#This Row],[Current Price]]<=Analysis!$B$4, "Medium Price", "High Price" ) ) ) -> Low Price | K79: =IF(Cleaned_Data[[#This Row],[Review]]="","Missing",IF(Cleaned_Data[[#This Row],[Review]]>=Engagement_Threshold,"Strong Engagement","Weak Engagement")) -> Missing | L79: =IF(OR(Cleaned_Data[[#This Row],[Discount]]="",Cleaned_Data[[#This Row],[Rating]]=""),"Missing",IF(AND(Cleaned_Data[[#This Row],[Discount Category]]="High Discount",Cleaned_Data[[#This Row],[Rating Category]]="Poor"),"Flag","OK")) -> Missing | M79: =IF(OR(Cleaned_Data[[#This Row],[Discount]]="",Cleaned_Data[[#This Row],[Review]]=""),"Missing",IF(AND(Cleaned_Data[[#This Row],[Discount Category]]="High Discount",Cleaned_Data[[#This Row],[Engagement]]="Weak Engagement"),"Flag","OK")) -> Missing | N79: =IF(OR(Cleaned_Data[[#This Row],[Review]]="",Cleaned_Data[[#This Row],[Rating]]=""),"Missing",IF(AND(Cleaned_Data[[#This Row],[Engagement]]="Strong Engagement",Cleaned_Data[[#This Row],[Rating Category]]="Average"),"Flag","OK")) -> Missing | O79: =IF(OR(Cleaned_Data[[#This Row],[Review]]="",Cleaned_Data[[#This Row],[Rating]]=""),"Missing",IF(AND(Cleaned_Data[[#This Row],[Engagement]]="Strong Engagement",Cleaned_Data[[#This Row],[Rating Category]]="Excellent"),"Flag","OK")) -> Missing | P79: =IF(Cleaned_Data[[#This Row],[Rating]]="","Missing Rating","Has Rating") -> Missing Rating | Q79: =IFERROR( (Cleaned_Data[[#This Row],[Old Price]]-Cleaned_Data[[#This Row],[Current Price]])/Cleaned_Data[[#This Row],[Old Price]], "" ) -> 0.48888889 | R79: =IF( Cleaned_Data[[#This Row],[Discount]] - Cleaned_Data[[#This Row],[Calculated Discount]]>2%, "Check", "OK" ) -> OK | S79: =IF(OR(Cleaned_Data[[#This Row],[Rating]]<0,Cleaned_Data[[#This Row],[Rating]]>5),"Check rating","OK") -> OK | T79: =IF(OR(Cleaned_Data[[#This Row],[Discount]]<0,Cleaned_Data[[#This Row],[Discount]]>1),"Check discount","OK") -> OK | U79: =IF(Cleaned_Data[[#This Row],[Current Price]]>Cleaned_Data[[#This Row],[Old Price]],"Check prices","OK") -> OK
A80: Memory Foam Neck Pillow Cover, With Pillow Core - 50*30cm | B80: 1189 | C80: 2199 | D80: 0.46 | E80: 1 | F80: 3 | G80: =Cleaned_Data[[#This Row],[Old Price]]-Cleaned_Data[[#This Row],[Current Price]] -> 1010 | H80: =IF(Cleaned_Data[[#This Row],[Rating]]="","Missing",IF(Cleaned_Data[[#This Row],[Rating]]<3,"Poor",IF(Cleaned_Data[[#This Row],[Rating]]<=4.5,"Average","Excellent"))) -> Average | I80: =IF( Cleaned_Data[[#This Row],[Discount]]="", "Missing", IF( Cleaned_Data[[#This Row],[Discount]]<20%, "Low Discount", IF( Cleaned_Data[[#This Row],[Discount]]<=40%, "Medium Discount", "High Discount" ) ) ) -> High Discount | J80: =IF( Cleaned_Data[[#This Row],[Current Price]]="", "Missing", IF( Cleaned_Data[[#This Row],[Current Price]]<=Analysis!$B$3, "Low Price", IF( Cleaned_Data[[#This Row],[Current Price]]<=Analysis!$B$4, "Medium Price", "High Price" ) ) ) -> Medium Price | K80: =IF(Cleaned_Data[[#This Row],[Review]]="","Missing",IF(Cleaned_Data[[#This Row],[Review]]>=Engagement_Threshold,"Strong Engagement","Weak Engagement")) -> Weak Engagement | L80: =IF(OR(Cleaned_Data[[#This Row],[Discount]]="",Cleaned_Data[[#This Row],[Rating]]=""),"Missing",IF(AND(Cleaned_Data[[#This Row],[Discount Category]]="High Discount",Cleaned_Data[[#This Row],[Rating Category]]="Poor"),"Flag","OK")) -> OK | M80: =IF(OR(Cleaned_Data[[#This Row],[Discount]]="",Cleaned_Data[[#This Row],[Review]]=""),"Missing",IF(AND(Cleaned_Data[[#This Row],[Discount Category]]="High Discount",Cleaned_Data[[#This Row],[Engagement]]="Weak Engagement"),"Flag","OK")) -> Flag | N80: =IF(OR(Cleaned_Data[[#This Row],[Review]]="",Cleaned_Data[[#This Row],[Rating]]=""),"Missing",IF(AND(Cleaned_Data[[#This Row],[Engagement]]="Strong Engagement",Cleaned_Data[[#This Row],[Rating Category]]="Average"),"Flag","OK")) -> OK | O80: =IF(OR(Cleaned_Data[[#This Row],[Review]]="",Cleaned_Data[[#This Row],[Rating]]=""),"Missing",IF(AND(Cleaned_Data[[#This Row],[Engagement]]="Strong Engagement",Cleaned_Data[[#This Row],[Rating Category]]="Excellent"),"Flag","OK")) -> OK | P80: =IF(Cleaned_Data[[#This Row],[Rating]]="","Missing Rating","Has Rating") -> Has Rating | Q80: =IFERROR( (Cleaned_Data[[#This Row],[Old Price]]-Cleaned_Data[[#This Row],[Current Price]])/Cleaned_Data[[#This Row],[Old Price]], "" ) -> 0.45929968 | R80: =IF( Cleaned_Data[[#This Row],[Discount]] - Cleaned_Data[[#This Row],[Calculated Discount]]>2%, "Check", "OK" ) -> OK | S80: =IF(OR(Cleaned_Data[[#This Row],[Rating]]<0,Cleaned_Data[[#This Row],[Rating]]>5),"Check rating","OK") -> OK | T80: =IF(OR(Cleaned_Data[[#This Row],[Discount]]<0,Cleaned_Data[[#This Row],[Discount]]>1),"Check discount","OK") -> OK | U80: =IF(Cleaned_Data[[#This Row],[Current Price]]>Cleaned_Data[[#This Row],[Old Price]],"Check prices","OK") -> OK
A81: Bedroom Simple Floor Hanging Clothes Rack Single Pole Hat Rack - White | B81: 979 | C81: 1920 | D81: 0.49 | E81: 1 | F81: 5 | G81: =Cleaned_Data[[#This Row],[Old Price]]-Cleaned_Data[[#This Row],[Current Price]] -> 941 | H81: =IF(Cleaned_Data[[#This Row],[Rating]]="","Missing",IF(Cleaned_Data[[#This Row],[Rating]]<3,"Poor",IF(Cleaned_Data[[#This Row],[Rating]]<=4.5,"Average","Excellent"))) -> Excellent | I81: =IF( Cleaned_Data[[#This Row],[Discount]]="", "Missing", IF( Cleaned_Data[[#This Row],[Discount]]<20%, "Low Discount", IF( Cleaned_Data[[#This Row],[Discount]]<=40%, "Medium Discount", "High Discount" ) ) ) -> High Discount | J81: =IF( Cleaned_Data[[#This Row],[Current Price]]="", "Missing", IF( Cleaned_Data[[#This Row],[Current Price]]<=Analysis!$B$3, "Low Price", IF( Cleaned_Data[[#This Row],[Current Price]]<=Analysis!$B$4, "Medium Price", "High Price" ) ) ) -> Medium Price | K81: =IF(Cleaned_Data[[#This Row],[Review]]="","Missing",IF(Cleaned_Data[[#This Row],[Review]]>=Engagement_Threshold,"Strong Engagement","Weak Engagement")) -> Weak Engagement | L81: =IF(OR(Cleaned_Data[[#This Row],[Discount]]="",Cleaned_Data[[#This Row],[Rating]]=""),"Missing",IF(AND(Cleaned_Data[[#This Row],[Discount Category]]="High Discount",Cleaned_Data[[#This Row],[Rating Category]]="Poor"),"Flag","OK")) -> OK | M81: =IF(OR(Cleaned_Data[[#This Row],[Discount]]="",Cleaned_Data[[#This Row],[Review]]=""),"Missing",IF(AND(Cleaned_Data[[#This Row],[Discount Category]]="High Discount",Cleaned_Data[[#This Row],[Engagement]]="Weak Engagement"),"Flag","OK")) -> Flag | N81: =IF(OR(Cleaned_Data[[#This Row],[Review]]="",Cleaned_Data[[#This Row],[Rating]]=""),"Missing",IF(AND(Cleaned_Data[[#This Row],[Engagement]]="Strong Engagement",Cleaned_Data[[#This Row],[Rating Category]]="Average"),"Flag","OK")) -> OK | O81: =IF(OR(Cleaned_Data[[#This Row],[Review]]="",Cleaned_Data[[#This Row],[Rating]]=""),"Missing",IF(AND(Cleaned_Data[[#This Row],[Engagement]]="Strong Engagement",Cleaned_Data[[#This Row],[Rating Category]]="Excellent"),"Flag","OK")) -> OK | P81: =IF(Cleaned_Data[[#This Row],[Rating]]="","Missing Rating","Has Rating") -> Has Rating | Q81: =IFERROR( (Cleaned_Data[[#This Row],[Old Price]]-Cleaned_Data[[#This Row],[Current Price]])/Cleaned_Data[[#This Row],[Old Price]], "" ) -> 0.49010417 | R81: =IF( Cleaned_Data[[#This Row],[Discount]] - Cleaned_Data[[#This Row],[Calculated Discount]]>2%, "Check", "OK" ) -> OK | S81: =IF(OR(Cleaned_Data[[#This Row],[Rating]]<0,Cleaned_Data[[#This Row],[Rating]]>5),"Check rating","OK") -> OK | T81: =IF(OR(Cleaned_Data[[#This Row],[Discount]]<0,Cleaned_Data[[#This Row],[Discount]]>1),"Check discount","OK") -> OK | U81: =IF(Cleaned_Data[[#This Row],[Current Price]]>Cleaned_Data[[#This Row],[Old Price]],"Check prices","OK") -> OK
A82: 5m Waterproof Spherical LED String Lights Outdoor Ball Chain Lights Party Lighting Decoration Adjustable | B82: 1460 | C82: 2290 | D82: 0.36 | G82: =Cleaned_Data[[#This Row],[Old Price]]-Cleaned_Data[[#This Row],[Current Price]] -> 830 | H82: =IF(Cleaned_Data[[#This Row],[Rating]]="","Missing",IF(Cleaned_Data[[#This Row],[Rating]]<3,"Poor",IF(Cleaned_Data[[#This Row],[Rating]]<=4.5,"Average","Excellent"))) -> Missing | I82: =IF( Cleaned_Data[[#This Row],[Discount]]="", "Missing", IF( Cleaned_Data[[#This Row],[Discount]]<20%, "Low Discount", IF( Cleaned_Data[[#This Row],[Discount]]<=40%, "Medium Discount", "High Discount" ) ) ) -> Medium Discount | J82: =IF( Cleaned_Data[[#This Row],[Current Price]]="", "Missing", IF( Cleaned_Data[[#This Row],[Current Price]]<=Analysis!$B$3, "Low Price", IF( Cleaned_Data[[#This Row],[Current Price]]<=Analysis!$B$4, "Medium Price", "High Price" ) ) ) -> Medium Price | K82: =IF(Cleaned_Data[[#This Row],[Review]]="","Missing",IF(Cleaned_Data[[#This Row],[Review]]>=Engagement_Threshold,"Strong Engagement","Weak Engagement")) -> Missing | L82: =IF(OR(Cleaned_Data[[#This Row],[Discount]]="",Cleaned_Data[[#This Row],[Rating]]=""),"Missing",IF(AND(Cleaned_Data[[#This Row],[Discount Category]]="High Discount",Cleaned_Data[[#This Row],[Rating Category]]="Poor"),"Flag","OK")) -> Missing | M82: =IF(OR(Cleaned_Data[[#This Row],[Discount]]="",Cleaned_Data[[#This Row],[Review]]=""),"Missing",IF(AND(Cleaned_Data[[#This Row],[Discount Category]]="High Discount",Cleaned_Data[[#This Row],[Engagement]]="Weak Engagement"),"Flag","OK")) -> Missing | N82: =IF(OR(Cleaned_Data[[#This Row],[Review]]="",Cleaned_Data[[#This Row],[Rating]]=""),"Missing",IF(AND(Cleaned_Data[[#This Row],[Engagement]]="Strong Engagement",Cleaned_Data[[#This Row],[Rating Category]]="Average"),"Flag","OK")) -> Missing | O82: =IF(OR(Cleaned_Data[[#This Row],[Review]]="",Cleaned_Data[[#This Row],[Rating]]=""),"Missing",IF(AND(Cleaned_Data[[#This Row],[Engagement]]="Strong Engagement",Cleaned_Data[[#This Row],[Rating Category]]="Excellent"),"Flag","OK")) -> Missing | P82: =IF(Cleaned_Data[[#This Row],[Rating]]="","Missing Rating","Has Rating") -> Missing Rating | Q82: =IFERROR( (Cleaned_Data[[#This Row],[Old Price]]-Cleaned_Data[[#This Row],[Current Price]])/Cleaned_Data[[#This Row],[Old Price]], "" ) -> 0.36244541 | R82: =IF( Cleaned_Data[[#This Row],[Discount]] - Cleaned_Data[[#This Row],[Calculated Discount]]>2%, "Check", "OK" ) -> OK | S82: =IF(OR(Cleaned_Data[[#This Row],[Rating]]<0,Cleaned_Data[[#This Row],[Rating]]>5),"Check rating","OK") -> OK | T82: =IF(OR(Cleaned_Data[[#This Row],[Discount]]<0,Cleaned_Data[[#This Row],[Discount]]>1),"Check discount","OK") -> OK | U82: =IF(Cleaned_Data[[#This Row],[Current Price]]>Cleaned_Data[[#This Row],[Old Price]],"Check prices","OK") -> OK
A83: 2 Pairs Cowhide Split Leather Work Gloves.32℉ Or Above Welding Gloves | B83: 1666 | C83: 1699 | D83: 0.02 | G83: =Cleaned_Data[[#This Row],[Old Price]]-Cleaned_Data[[#This Row],[Current Price]] -> 33 | H83: =IF(Cleaned_Data[[#This Row],[Rating]]="","Missing",IF(Cleaned_Data[[#This Row],[Rating]]<3,"Poor",IF(Cleaned_Data[[#This Row],[Rating]]<=4.5,"Average","Excellent"))) -> Missing | I83: =IF( Cleaned_Data[[#This Row],[Discount]]="", "Missing", IF( Cleaned_Data[[#This Row],[Discount]]<20%, "Low Discount", IF( Cleaned_Data[[#This Row],[Discount]]<=40%, "Medium Discount", "High Discount" ) ) ) -> Low Discount | J83: =IF( Cleaned_Data[[#This Row],[Current Price]]="", "Missing", IF( Cleaned_Data[[#This Row],[Current Price]]<=Analysis!$B$3, "Low Price", IF( Cleaned_Data[[#This Row],[Current Price]]<=Analysis!$B$4, "Medium Price", "High Price" ) ) ) -> Medium Price | K83: =IF(Cleaned_Data[[#This Row],[Review]]="","Missing",IF(Cleaned_Data[[#This Row],[Review]]>=Engagement_Threshold,"Strong Engagement","Weak Engagement")) -> Missing | L83: =IF(OR(Cleaned_Data[[#This Row],[Discount]]="",Cleaned_Data[[#This Row],[Rating]]=""),"Missing",IF(AND(Cleaned_Data[[#This Row],[Discount Category]]="High Discount",Cleaned_Data[[#This Row],[Rating Category]]="Poor"),"Flag","OK")) -> Missing | M83: =IF(OR(Cleaned_Data[[#This Row],[Discount]]="",Cleaned_Data[[#This Row],[Review]]=""),"Missing",IF(AND(Cleaned_Data[[#This Row],[Discount Category]]="High Discount",Cleaned_Data[[#This Row],[Engagement]]="Weak Engagement"),"Flag","OK")) -> Missing | N83: =IF(OR(Cleaned_Data[[#This Row],[Review]]="",Cleaned_Data[[#This Row],[Rating]]=""),"Missing",IF(AND(Cleaned_Data[[#This Row],[Engagement]]="Strong Engagement",Cleaned_Data[[#This Row],[Rating Category]]="Average"),"Flag","OK")) -> Missing | O83: =IF(OR(Cleaned_Data[[#This Row],[Review]]="",Cleaned_Data[[#This Row],[Rating]]=""),"Missing",IF(AND(Cleaned_Data[[#This Row],[Engagement]]="Strong Engagement",Cleaned_Data[[#This Row],[Rating Category]]="Excellent"),"Flag","OK")) -> Missing | P83: =IF(Cleaned_Data[[#This Row],[Rating]]="","Missing Rating","Has Rating") -> Missing Rating | Q83: =IFERROR( (Cleaned_Data[[#This Row],[Old Price]]-Cleaned_Data[[#This Row],[Current Price]])/Cleaned_Data[[#This Row],[Old Price]], "" ) -> 0.01942319 | R83: =IF( Cleaned_Data[[#This Row],[Discount]] - Cleaned_Data[[#This Row],[Calculated Discount]]>2%, "Check", "OK" ) -> OK | S83: =IF(OR(Cleaned_Data[[#This Row],[Rating]]<0,Cleaned_Data[[#This Row],[Rating]]>5),"Check rating","OK") -> OK | T83: =IF(OR(Cleaned_Data[[#This Row],[Discount]]<0,Cleaned_Data[[#This Row],[Discount]]>1),"Check discount","OK") -> OK | U83: =IF(Cleaned_Data[[#This Row],[Current Price]]>Cleaned_Data[[#This Row],[Old Price]],"Check prices","OK") -> OK
A84: Household Pineapple Peeler Peeler | B84: 330 | C84: 647 | D84: 0.49 | E84: 1 | F84: 4 | G84: =Cleaned_Data[[#This Row],[Old Price]]-Cleaned_Data[[#This Row],[Current Price]] -> 317 | H84: =IF(Cleaned_Data[[#This Row],[Rating]]="","Missing",IF(Cleaned_Data[[#This Row],[Rating]]<3,"Poor",IF(Cleaned_Data[[#This Row],[Rating]]<=4.5,"Average","Excellent"))) -> Average | I84: =IF( Cleaned_Data[[#This Row],[Discount]]="", "Missing", IF( Cleaned_Data[[#This Row],[Discount]]<20%, "Low Discount", IF( Cleaned_Data[[#This Row],[Discount]]<=40%, "Medium Discount", "High Discount" ) ) ) -> High Discount | J84: =IF( Cleaned_Data[[#This Row],[Current Price]]="", "Missing", IF( Cleaned_Data[[#This Row],[Current Price]]<=Analysis!$B$3, "Low Price", IF( Cleaned_Data[[#This Row],[Current Price]]<=Analysis!$B$4, "Medium Price", "High Price" ) ) ) -> Low Price | K84: =IF(Cleaned_Data[[#This Row],[Review]]="","Missing",IF(Cleaned_Data[[#This Row],[Review]]>=Engagement_Threshold,"Strong Engagement","Weak Engagement")) -> Weak Engagement | L84: =IF(OR(Cleaned_Data[[#This Row],[Discount]]="",Cleaned_Data[[#This Row],[Rating]]=""),"Missing",IF(AND(Cleaned_Data[[#This Row],[Discount Category]]="High Discount",Cleaned_Data[[#This Row],[Rating Category]]="Poor"),"Flag","OK")) -> OK | M84: =IF(OR(Cleaned_Data[[#This Row],[Discount]]="",Cleaned_Data[[#This Row],[Review]]=""),"Missing",IF(AND(Cleaned_Data[[#This Row],[Discount Category]]="High Discount",Cleaned_Data[[#This Row],[Engagement]]="Weak Engagement"),"Flag","OK")) -> Flag | N84: =IF(OR(Cleaned_Data[[#This Row],[Review]]="",Cleaned_Data[[#This Row],[Rating]]=""),"Missing",IF(AND(Cleaned_Data[[#This Row],[Engagement]]="Strong Engagement",Cleaned_Data[[#This Row],[Rating Category]]="Average"),"Flag","OK")) -> OK | O84: =IF(OR(Cleaned_Data[[#This Row],[Review]]="",Cleaned_Data[[#This Row],[Rating]]=""),"Missing",IF(AND(Cleaned_Data[[#This Row],[Engagement]]="Strong Engagement",Cleaned_Data[[#This Row],[Rating Category]]="Excellent"),"Flag","OK")) -> OK | P84: =IF(Cleaned_Data[[#This Row],[Rating]]="","Missing Rating","Has Rating") -> Has Rating | Q84: =IFERROR( (Cleaned_Data[[#This Row],[Old Price]]-Cleaned_Data[[#This Row],[Current Price]])/Cleaned_Data[[#This Row],[Old Price]], "" ) -> 0.48995363 | R84: =IF( Cleaned_Data[[#This Row],[Discount]] - Cleaned_Data[[#This Row],[Calculated Discount]]>2%, "Check", "OK" ) -> OK | S84: =IF(OR(Cleaned_Data[[#This Row],[Rating]]<0,Cleaned_Data[[#This Row],[Rating]]>5),"Check rating","OK") -> OK | T84: =IF(OR(Cleaned_Data[[#This Row],[Discount]]<0,Cleaned_Data[[#This Row],[Discount]]>1),"Check discount","OK") -> OK | U84: =IF(Cleaned_Data[[#This Row],[Current Price]]>Cleaned_Data[[#This Row],[Old Price]],"Check prices","OK") -> OK
A85: Creative Owl Shape Keychain Black | B85: 176 | C85: 345 | D85: 0.49 | G85: =Cleaned_Data[[#This Row],[Old Price]]-Cleaned_Data[[#This Row],[Current Price]] -> 169 | H85: =IF(Cleaned_Data[[#This Row],[Rating]]="","Missing",IF(Cleaned_Data[[#This Row],[Rating]]<3,"Poor",IF(Cleaned_Data[[#This Row],[Rating]]<=4.5,"Average","Excellent"))) -> Missing | I85: =IF( Cleaned_Data[[#This Row],[Discount]]="", "Missing", IF( Cleaned_Data[[#This Row],[Discount]]<20%, "Low Discount", IF( Cleaned_Data[[#This Row],[Discount]]<=40%, "Medium Discount", "High Discount" ) ) ) -> High Discount | J85: =IF( Cleaned_Data[[#This Row],[Current Price]]="", "Missing", IF( Cleaned_Data[[#This Row],[Current Price]]<=Analysis!$B$3, "Low Price", IF( Cleaned_Data[[#This Row],[Current Price]]<=Analysis!$B$4, "Medium Price", "High Price" ) ) ) -> Low Price | K85: =IF(Cleaned_Data[[#This Row],[Review]]="","Missing",IF(Cleaned_Data[[#This Row],[Review]]>=Engagement_Threshold,"Strong Engagement","Weak Engagement")) -> Missing | L85: =IF(OR(Cleaned_Data[[#This Row],[Discount]]="",Cleaned_Data[[#This Row],[Rating]]=""),"Missing",IF(AND(Cleaned_Data[[#This Row],[Discount Category]]="High Discount",Cleaned_Data[[#This Row],[Rating Category]]="Poor"),"Flag","OK")) -> Missing | M85: =IF(OR(Cleaned_Data[[#This Row],[Discount]]="",Cleaned_Data[[#This Row],[Review]]=""),"Missing",IF(AND(Cleaned_Data[[#This Row],[Discount Category]]="High Discount",Cleaned_Data[[#This Row],[Engagement]]="Weak Engagement"),"Flag","OK")) -> Missing | N85: =IF(OR(Cleaned_Data[[#This Row],[Review]]="",Cleaned_Data[[#This Row],[Rating]]=""),"Missing",IF(AND(Cleaned_Data[[#This Row],[Engagement]]="Strong Engagement",Cleaned_Data[[#This Row],[Rating Category]]="Average"),"Flag","OK")) -> Missing | O85: =IF(OR(Cleaned_Data[[#This Row],[Review]]="",Cleaned_Data[[#This Row],[Rating]]=""),"Missing",IF(AND(Cleaned_Data[[#This Row],[Engagement]]="Strong Engagement",Cleaned_Data[[#This Row],[Rating Category]]="Excellent"),"Flag","OK")) -> Missing | P85: =IF(Cleaned_Data[[#This Row],[Rating]]="","Missing Rating","Has Rating") -> Missing Rating | Q85: =IFERROR( (Cleaned_Data[[#This Row],[Old Price]]-Cleaned_Data[[#This Row],[Current Price]])/Cleaned_Data[[#This Row],[Old Price]], "" ) -> 0.48985507 | R85: =IF( Cleaned_Data[[#This Row],[Discount]] - Cleaned_Data[[#This Row],[Calculated Discount]]>2%, "Check", "OK" ) -> OK | S85: =IF(OR(Cleaned_Data[[#This Row],[Rating]]<0,Cleaned_Data[[#This Row],[Rating]]>5),"Check rating","OK") -> OK | T85: =IF(OR(Cleaned_Data[[#This Row],[Discount]]<0,Cleaned_Data[[#This Row],[Discount]]>1),"Check discount","OK") -> OK | U85: =IF(Cleaned_Data[[#This Row],[Current Price]]>Cleaned_Data[[#This Row],[Old Price]],"Check prices","OK") -> OK
